Workbook

Sheet Reena
A1: CLIENT | B1: INVOICE NO. | C1: INVOICE DATE | D1: CLIENT TRN | E1: DESCRIPTION | F1: INVOICE SUB-TOTAL | G1: REBATE | H1: INVOICE SUB-TOTAL AFTER REBATE | I1: VAT % AMOUNT | J1: TOTAL INVOICE AMOUNT | K1: Sales Person | L1: =COUNTA(B:B)-1 -> 189 | M1: =GETPIVOTDATA("Count of INVOICE NO.",#REF!)+GETPIVOTDATA("Count of INVOICE NO.",#REF!) -> #REF! | N1: =SUM(F:F) -> 542386.71
A2: Stellar Advertising LLC | B2: 24-0001 | C2: 45293 | D2: 100542487200003 | E2: A3 Poster - Jebel Ali School | F2: 425.49 | H2: =F2-G2 -> 425.49 | I2: =F2*5% -> 21.2745 | J2: =F2+I2 -> 446.7645 | K2: REENA
A3: Stellar Advertising LLC | B3: 24-0002 | C3: 45295 | D3: 100542487200003 | E3: A5 Booklet - DBSJP (Nov/Dec) | F3: 415 | H3: =F3-G3 -> 415 | I3: =F3*5% -> 20.75 | J3: =F3+I3 -> 435.75 | K3: REENA
A4: Aurantius Real Estate Broker | B4: 24-0003 | C4: 45295 | D4: 104166051300003 | E4: Business Cards ( Ferhat Doghan ) | F4: 475 | H4: =F4-G4 -> 475 | I4: =F4*5% -> 23.75 | J4: =F4+I4 -> 498.75 | K4: REENA
A5: A-Technologies FZCO | B5: 24-0004 | C5: 45306 | D5: 100312976200003 | E5: Water Bottle , A5 Notebook (Anti-Microbial) , Metal Pen , Box | F5: 5850 | H5: =F5-G5 -> 5850 | I5: =F5*5% -> 292.5 | J5: =F5+I5 -> 6142.5 | K5: MARINELLE
A6: EMIRATES FOR UNIVERSAL TYRES L.L.C. | B6: 24-0005 | C6: 45297 | D6: 100032677500003 | E6: Sticker (Paper) | F6: 425 | H6: =F6-G6 -> 425 | I6: =F6*5% -> 21.25 | J6: =F6+I6 -> 446.25 | K6: REENA
A7: GRAND STAR ALUMINUM & GLASS L.L.C | B7: 24-0006 | C7: 45296 | D7: 100522321700003 | E7: Wooden Board | F7: 7600 | H7: =F7-G7 -> 7600 | I7: =F7*5% -> 380 | J7: =F7+I7 -> 7980 | K7: REENA
A8: VISIONARY FURNITURE TRADING L.L.C | B8: 24-0007 | C8: 45302 | D8: 104037069200003 | E8: Business Cards , Polo Shirts | F8: 848 | H8: =F8-G8 -> 848 | I8: =F8*5% -> 42.4 | J8: =F8+I8 -> 890.4 | K8: REENA
A9: Navitas Middle East FZ - LLC | B9: 24-0008 | C9: 45300 | D9: 100430750800003 | E9: Round neck Tshirt | F9: 380 | H9: =F9-G9 -> 380 | I9: =F9*5% -> 19 | J9: =F9+I9 -> 399 | K9: REENA
A10: Trane BVBA (Abu Dhabi) | B10: 24-0009 | C10: 45316 | D10: 100348311000003 | E10: Business Card ( Mohamed Ben Hamouda ) | F10: 405 | H10: =F10-G10 -> 405 | I10: =F10*5% -> 20.25 | J10: =F10+I10 -> 425.25 | K10: REENA
A11: M Y WORLD TRADING L.L.C | B11: 24-0010 | C11: 45300 | D11: 104014963300003 | E11: Business Cards ( Mr. Mehdi M Taki , Mr. Muhammed Midlaj ) | F11: 530 | H11: =F11-G11 -> 530 | I11: =F11*5% -> 26.5 | J11: =F11+I11 -> 556.5 | K11: REENA
A12: GRAND STAR ALUMINUM & GLASS L.L.C | B12: 24-0011 | C12: 45302 | D12: 100522321700003 | E12: Acrylic Stand | F12: 760 | H12: =F12-G12 -> 760 | I12: =F12*5% -> 38 | J12: =F12+I12 -> 798 | K12: REENA
A13: IDP Education Services Nigeria Limited | B13: 24-0012 | C13: 45300 | D13: - | E13: Polo Shirt | F13: =3.67*62.1 -> 227.907 | H13: =F13-G13 -> 227.907 | I13: =F13*5% -> 11.39535 | J13: =F13+I13 -> 239.30235 | K13: REENA
A14: M E A D Medical Supplies & Equipment L.L.C | B14: 24-0013 | C14: 45303 | D14: 100540543400003 | E14: NCR Book | F14: 475 | H14: =F14-G14 -> 475 | I14: =F14*5% -> 23.75 | J14: =F14+I14 -> 498.75 | K14: MARINELLE
A15: Stellar Advertising LLC | B15: 24-0014 | C15: 45303 | D15: 100542487200003 | E15: Poster , Flag ( Raha International School ) | F15: 440 | H15: =F15-G15 -> 440 | I15: =F15*5% -> 22 | J15: =F15+I15 -> 462 | K15: REENA
A16: Lloyds Energy DMCC | B16: 24-0015 | C16: 45303 | D16: 100056728700003 | E16: Signage (Without Light) | F16: 1250 | H16: =F16-G16 -> 1250 | I16: =F16*5% -> 62.5 | J16: =F16+I16 -> 1312.5 | K16: MARINELLE
A17: EMIRATES FOR UNIVERSAL TYRES L.L.C. | B17: 24-0016 | C17: 45303 | D17: 100032677500003 | E17: Business card ( Rineesh Ali ) | F17: 165 | H17: =F17-G17 -> 165 | I17: =F17*5% -> 8.25 | J17: =F17+I17 -> 173.25 | K17: REENA
A18: Bianca and Bianco Trading LLC | B18: 24-0017 | C18: 45304 | D18: 100482284500003 | E18: Business Card | F18: 825 | H18: =F18-G18 -> 825 | I18: =F18*5% -> 41.25 | J18: =F18+I18 -> 866.25 | K18: REENA
A19: Logic Utilities District Cooling Services LLC | B19: 24-0018 | C19: 45316 | D19: 100567483100003 | E19: Polo Shirts | F19: 4252.5 | H19: =F19-G19 -> 4252.5 | I19: =F19*5% -> 212.625 | J19: =F19+I19 -> 4465.125 | K19: MARINELLE
A20: FAD Institute of Luxury Fashion and Style Dubai | B20: 24-0019 | C20: 45307 | D20: - | E20: Certificate Holder | F20: 1690 | H20: =F20-G20 -> 1690 | I20: =F20*5% -> 84.5 | J20: =F20+I20 -> 1774.5 | K20: MARINELLE
A21: Ingersoll-Rand Technical and Services S A R L (Dubai Branch) | B21: 24-0020 | C21: 45306 | D21: 100399495900003 | E21: Business Card | F21: 310 | H21: =F21-G21 -> 310 | I21: =F21*5% -> 15.5 | J21: =F21+I21 -> 325.5 | K21: MARINELLE
A22: JUBAILI BROS S.A.L. | B22: 24-0021 | C22: 45307 | D22: 100293287700003 | E22: Car Sunshades (Tyvek) | F22: 5975 | H22: =F22-G22 -> 5975 | I22: =F22*5% -> 298.75 | J22: =F22+I22 -> 6273.75 | K22: MARINELLE
A23: Global Connect | B23: 24-0022 | C23: 45303 | D23: - | E23: Rubber stamp | F23: 120 | H23: =F23-G23 -> 120 | I23: =F23*5% -> 6 | J23: =F23+I23 -> 126 | K23: REENA
A24: A-Technologies FZCO | B24: 24-0024 | C24: 45307 | D24: 100312976200003 | E24: Prints for Gift Box | F24: 200 | H24: =F24-G24 -> 200 | I24: =F24*5% -> 10 | J24: =F24+I24 -> 210 | K24: MARINELLE
A25: Radiometer Medical ApS | B25: 24-0025 | C25: 45313 | D25: - | E25: Pop Up Banner (Straight) , Roll up , Book Mark (Steel) , Table Flag with Stand | F25: 7595.24 | H25: =F25-G25 -> 7595.24 | I25: =F25*5% -> 379.762 | J25: =F25+I25 -> 7975.002 | K25: MARINELLE
... A92: Trane BVBA (Dubai Branch) | B92: 24-0093 | C92: 45335 | D92: 100235699400003 | E92: Crystal Trophy | F92: 1800 | H92: =F92-G92 -> 1800 | I92: =F92*5% -> 90 | J92: =F92+I92 -> 1890 | K92: REENA
A93: Krishna International FZCO | B93: 24-0094 | C93: 45332 | D93: 100060213400003 | E93: Wedding Luggage Tags | F93: 13000 | H93: =F93-G93 -> 13000 | I93: =F93*5% -> 650 | J93: =F93+I93 -> 13650 | K93: REENA
A94: One Blue Clover FZCO | B94: 24-0095 | C94: 45338 | D94: - | E94: Letterhead | F94: 525 | H94: =F94-G94 -> 525 | I94: =F94*5% -> 26.25 | J94: =F94+I94 -> 551.25 | K94: REENA
A95: Stellar Advertising LLC | B95: 24-0096 | C95: 45337 | D95: 100542487200003 | E95: Selfie Frame - DBSJP , Prop - #Outstanding | F95: 595 | H95: =F95-G95 -> 595 | I95: =F95*5% -> 29.75 | J95: =F95+I95 -> 624.75 | K95: REENA
A96: Stellar Advertising LLC | B96: 24-0097 | C96: 45338 | D96: 100542487200003 | E96: Roll Up - AAG | F96: 145 | H96: =F96-G96 -> 145 | I96: =F96*5% -> 7.25 | J96: =F96+I96 -> 152.25 | K96: REENA
A97: M E A D Medical Supplies & Equipment L.L.C | B97: 24-0098 | C97: 45341 | D97: 100540543400003 | E97: NCR Book , Business Cards | F97: 860 | H97: =F97-G97 -> 860 | I97: =F97*5% -> 43 | J97: =F97+I97 -> 903 | K97: MARINELLE
A98: Stellar Advertising LLC | B98: 24-0099 | C98: 45342 | D98: 100542487200003 | E98: Letterhead - FICHTE | F98: 625 | H98: =F98-G98 -> 625 | I98: =F98*5% -> 31.25 | J98: =F98+I98 -> 656.25 | K98: REENA
A99: Golden Tower Technologies | B99: 24-0100 | C99: 45338 | D99: 100470289800003 | E99: Flex to be changed for existing light box | F99: 8850 | H99: =F99-G99 -> 8850 | I99: =F99*5% -> 442.5 | J99: =F99+I99 -> 9292.5 | K99: PROFORMA
A100: Thermo Fisher Scientific S.P.A. | B100: 24-0101 | C100: 45338 | D100: IT 07817950152 | E100: Flyer , Recycled 6-in-1 Charging Cable | F100: 3335 | H100: =F100-G100 -> 3335 | I100: =F100*5% -> 166.75 | J100: =F100+I100 -> 3501.75 | K100: MARINELLE
A101: Griffith College | B101: 24-0102 | C101: 45338 | D101: - | E101: Brochure | F101: 1225 | H101: =F101-G101 -> 1225 | I101: =F101*5% -> 61.25 | J101: =F101+I101 -> 1286.25 | K101: REENA
A102: IDP EDUCATION L.L.C | B102: 24-0103 | C102: 45341 | D102: 100593105800003 | E102: Dubai Roadshow Millenium Downtown, 17th Feb 2024 | F102: 103245.5 | H102: =F102-G102 -> 103245.5 | I102: =F102*5% -> 5162.275 | J102: =F102+I102 -> 108407.77 | K102: REENA
A103: IDP EDUCATION L.L.C | B103: 24-0104 | C103: 45341 | D103: 100593105800003 | E103: Abu Dhabi Roadshow 18 Feb 2024, InterContinental | F103: 51717.75 | H103: =F103-G103 -> 51717.75 | I103: =F103*5% -> 2585.8875 | J103: =F103+I103 -> 54303.637 | K103: REENA
A104: DYNAMIC EMPLOYMENT SERVICES L.L.C | B104: 24-0105 | C104: 45343 | D104: 100323347300003 | E104: Parking Signage | F104: 892.5 | H104: =F104-G104 -> 892.5 | I104: =F104*5% -> 44.625 | J104: =F104+I104 -> 937.125 | K104: MARINELLE
A105: Stellar Advertising LLC | B105: 24-0106 | C105: 45343 | D105: 100542487200003 | E105: Flyer - Taylor Wessing | F105: 190 | H105: =F105-G105 -> 190 | I105: =F105*5% -> 9.5 | J105: =F105+I105 -> 199.5 | K105: REENA
A106: Stellar Advertising LLC | B106: 24-0107 | C106: 45342 | D106: 100542487200003 | E106: Journal - DBSEH | F106: 585 | H106: =F106-G106 -> 585 | I106: =F106*5% -> 29.25 | J106: =F106+I106 -> 614.25 | K106: REENA
A107: Crescent Real Estate | B107: 24-0108 | C107: 45343 | D107: 100359923800003 | E107: Polo Shirts | F107: 1920 | H107: =F107-G107 -> 1920 | I107: =F107*5% -> 96 | J107: =F107+I107 -> 2016 | K107: MARINELLE
A108: Indo Tausch Trading DMCC | B108: 24-0109 | C108: 45344 | D108: 100484375900003 | E108: Business Cards , ID Cards | F108: 420 | H108: =F108-G108 -> 420 | I108: =F108*5% -> 21 | J108: =F108+I108 -> 441 | K108: REENA
A109: Stellar Advertising LLC | B109: 24-0110 | C109: 45344 | D109: 100542487200003 | E109: Top Curve Flags - Al Salaam Charter School | F109: 6250 | H109: =F109-G109 -> 6250 | I109: =F109*5% -> 312.5 | J109: =F109+I109 -> 6562.5 | K109: REENA
A110: Stellar Advertising LLC | B110: 24-0111 | C110: 45345 | D110: 100542487200003 | E110: Rollup Banners (GIS) , Designing charges | F110: 390 | H110: =F110-G110 -> 390 | I110: =F110*5% -> 19.5 | J110: =F110+I110 -> 409.5 | K110: REENA
A111: Stellar Advertising LLC | B111: 24-0112 | C111: 45345 | D111: 100542487200003 | E111: Round Neck Tshirts (Wellbeing) - Charter School | F111: 4220.5 | H111: =F111-G111 -> 4220.5 | I111: =F111*5% -> 211.025 | J111: =F111+I111 -> 4431.525 | K111: REENA
A112: Trane BVBA (Dubai Branch) | B112: 24-0113 | C112: 45345 | D112: 100235699400003 | E112: Business Cards ( Dipak M Shelke ) | F112: 405 | H112: =F112-G112 -> 405 | I112: =F112*5% -> 20.25 | J112: =F112+I112 -> 425.25 | K112: REENA
A113: Huxley Associates Global Limited | B113: 24-0114 | C113: 45348 | D113: 100349055200003 | E113: Vertical Matt Veneer Wooden Plaque | F113: 225 | H113: =F113-G113 -> 225 | I113: =F113*5% -> 11.25 | J113: =F113+I113 -> 236.25 | K113: MARINELLE
... A118: IDP EDUCATION L.L.C | B118: 24-0120 | C118: 45345 | D118: 100593105800003 | E118: IDP Business Cards - (Abu Dhabi) | F118: 960 | H118: =F118-G118 -> 960 | I118: =F118*5% -> 48 | J118: =F118+I118 -> 1008 | K118: REENA
A119: AL RASHED UNITED DMCC | B119: 24-0122 | C119: 45351 | D119: 100246622300003 | E119: Business card , Ribbons with printing , Paper Bag , Paper Stickers , Wrapping Paper | F119: 3490 | H119: =F119-G119 -> 3490 | I119: 174 | J119: =F119+I119 -> 3664 | K119: REENA
A120: Bianca and Bianco Trading LLC | B120: 24-0124 | C120: 45351 | D120: 100482284500003 | E120: Business Card | F120: 310 | H120: =F120-G120 -> 310 | I120: =F120*5% -> 15.5 | J120: =F120+I120 -> 325.5 | K120: REENA
A121: Liquid Telecommunications International FZE | B121: 24-0125 | C121: 45349 | D121: 100247605700003 | E121: Gift Box - Black , Paper Bag | F121: 6775 | H121: =F121-G121 -> 6775 | I121: =F121*5% -> 338.75 | J121: =F121+I121 -> 7113.75 | K121: REENA
A122: Shory Technology L.L.C | B122: 24-0126 | C122: 45349 | D122: 100435244700003 | E122: Big Card, Small Card, Thank You Card | F122: 915 | H122: =F122-G122 -> 915 | I122: =F122*5% -> 45.75 | J122: =F122+I122 -> 960.75 | K122: MARINELLE
A123: Technological University of the Shannon - Ireland | B123: 24-0127 | C123: 45349 | D123: - | E123: Brochure 2024 , Courier Charges to Abu Dhabi | F123: 1925 | H123: =F123-G123 -> 1925 | I123: =F123*5% -> 96.25 | J123: =F123+I123 -> 2021.25 | K123: REENA
A124: Aram Precious Metals Trading FZE | B124: 24-0128 | C124: 45350 | D124: 104020641700003 | E124: Website Designing and Development ( 75% Advance Invoice ) | F124: 2362.38 | H124: =F124-G124 -> 2362.38 | I124: =F124*5% -> 118.119 | J124: =F124+I124 -> 2480.499 | K124: REENA
A125: Al Naser International FZE | B125: 24-0129 | C125: 45350 | D125: 100566746200003 | E125: Website Designing and Development ( 75% Advance Invoice ) | F125: 2362.38 | H125: =F125-G125 -> 2362.38 | I125: =F125*5% -> 118.119 | J125: =F125+I125 -> 2480.499 | K125: REENA
A126: AUSTRAL INTERNATIONAL DMCC | B126: 24-0130 | C126: 45350 | D126: 100494671900003 | E126: Website Designing and Development ( 75% Advance Invoice ) | F126: 2362.38 | H126: =F126-G126 -> 2362.38 | I126: =F126*5% -> 118.119 | J126: =F126+I126 -> 2480.499 | K126: REENA
A127: ADIRONDACK ARCHITECTURAL MODELS INDUSTRY L.L.C | B127: 24-0131 | C127: 45350 | D127: 104061117800003 | E127: Sampling Charges - Polo Shirt | F127: 47.62 | H127: =F127-G127 -> 47.62 | I127: =F127*5% -> 2.381 | J127: =F127+I127 -> 50.001 | K127: REENA
A128: Aurantius Real Estate Broker | B128: 24-0132 | C128: 45351 | D128: 104166051300003 | E128: A4 Envelopes (customized) , DL Envelopes (customized) , Top spiral Notebook | F128: 1248 | H128: =F128-G128 -> 1248 | I128: =F128*5% -> 62.4 | J128: =F128+I128 -> 1310.4 | K128: REENA
A129: Unique World Business Centre LLC | B129: 24-0133 | C129: 45351 | D129: 100048520900003 | E129: Board Supply February, 2024 | F129: 90 | H129: =F129-G129 -> 90 | I129: =F129*5% -> 4.5 | J129: =F129+I129 -> 94.5 | K129: REENA
A130: Unique World Business Centre LLC | B130: 24-0134 | C130: 45351 | D130: 100048520900003 | E130: Board Supply February, 2024 | F130: 105 | H130: =F130-G130 -> 105 | I130: =F130*5% -> 5.25 | J130: =F130+I130 -> 110.25 | K130: REENA
A131: Navitas SAE FZ-LLC | B131: 24-0135 | C131: 45352 | D131: 100282822400003 | E131: Table cloth - Bridal Satin , A4 Flyer (ICN) | F131: 485 | H131: =F131-G131 -> 485 | I131: =F131*5% -> 24.25 | J131: =F131+I131 -> 509.25 | K131: REENA
A132: Stellar Advertising LLC | B132: 24-0136 | C132: 45351 | D132: 100542487200003 | E132: Customized Vest - Taaleem | F132: 1890 | H132: =F132-G132 -> 1890 | I132: =F132*5% -> 94.5 | J132: =F132+I132 -> 1984.5 | K132: REENA
A133: M E A D Medical Supplies & Equipment L.L.C | B133: 24-0137 | C133: 45351 | D133: 100540543400003 | E133: Receipt Voucher | F133: 487.5 | H133: =F133-G133 -> 487.5 | I133: =F133*5% -> 24.375 | J133: =F133+I133 -> 511.875 | K133: MARINELLE
A134: Aurantius Real Estate Broker | B134: 24-0138 | C134: 45351 | D134: 104166051300003 | E134: Metal Pen , A4 Notepad | F134: 1162.5 | H134: =F134-G134 -> 1162.5 | I134: =F134*5% -> 58.125 | J134: =F134+I134 -> 1220.625 | K134: REENA
A135: Aram Precious Metals Trading FZE | B135: 24-0139 | C135: 45350 | D135: 104020641700003 | E135: Website Designing and Development ( 25% Final Invoice ) | F135: 787.62 | H135: =F135-G135 -> 787.62 | I135: =F135*5% -> 39.381 | J135: =F135+I135 -> 827.001 | K135: PROFORMA
... A137: AUSTRAL INTERNATIONAL DMCC | B137: 24-0141 | C137: 45350 | D137: 100494671900003 | E137: Website Designing and Development ( 25% Final Invoice ) | F137: 787.62 | H137: =F137-G137 -> 787.62 | I137: =F137*5% -> 39.381 | J137: =F137+I137 -> 827.001 | K137: PROFORMA
A138: Stellar Advertising LLC | B138: 24-0142 | C138: 45352 | D138: 100542487200003 | E138: Business cards (Taaleem) | F138: 450 | H138: =F138-G138 -> 450 | I138: =F138*5% -> 22.5 | J138: =F138+I138 -> 472.5 | K138: REENA
A139: Navitas Middle East FZ - LLC | B139: 24-0143 | C139: 45355 | D139: 100430750800003 | E139: Business card | F139: 275 | H139: =F139-G139 -> 275 | I139: =F139*5% -> 13.75 | J139: =F139+I139 -> 288.75 | K139: REENA
A140: Navitas SAE FZ-LLC | B140: 24-0144 | C140: 45355 | D140: 100282822400003 | E140: Rollup Banner , A3 Desktop Rollup , A4 Flyer (ICN) | F140: 505 | H140: =F140-G140 -> 505 | I140: =F140*5% -> 25.25 | J140: =F140+I140 -> 530.25 | K140: REENA
A141: Stellar Advertising LLC | B141: 24-0145 | C141: 45355 | D141: 100542487200003 | E141: Business Card - DBSJ | F141: 220 | H141: =F141-G141 -> 220 | I141: =F141*5% -> 11 | J141: =F141+I141 -> 231 | K141: REENA
A142: Trane BVBA (Dubai Branch) | B142: 24-0146 | C142: 45356 | D142: 100235699400003 | E142: Business Cards (Jomer Pinohermoso) | F142: 405 | H142: =F142-G142 -> 405 | I142: =F142*5% -> 20.25 | J142: =F142+I142 -> 425.25 | K142: REENA
A143: GrokGlobal Services | B143: 24-0147 | C143: 45353 | D143: - | E143: Student Gift Set of A5 Notebook and Pen With Bamboo Element , Jute Bag | F143: 18930 | H143: =F143-G143 -> 18930 | I143: =F143*5% -> 946.5 | J143: =F143+I143 -> 19876.5 | K143: REENA
A144: GrokGlobal Services | B144: 24-0148 | C144: 45355 | D144: - | E144: Brochure - Pre Departure | F144: 2585 | H144: =F144-G144 -> 2585 | I144: =F144*5% -> 129.25 | J144: =F144+I144 -> 2714.25 | K144: REENA
A145: ANB AUTOMOBILES L.L.C | B145: 24-0149 | C145: 45358 | D145: 100433257100003 | E145: Black Mug | F145: 1130 | H145: =F145-G145 -> 1130 | I145: =F145*5% -> 56.5 | J145: =F145+I145 -> 1186.5 | K145: MARINELLE
A146: Trane BVBA (Dubai Branch) | B146: 24-0150 | C146: 45356 | D146: 100235699400003 | E146: Business Cards (HAKIM LABRAHMI) | F146: 405 | H146: =F146-G146 -> 405 | I146: =F146*5% -> 20.25 | J146: =F146+I146 -> 425.25 | K146: REENA
A147: Stellar Advertising LLC | B147: 24-0151 | C147: 45357 | D147: 100542487200003 | E147: Leaflet - 3 fold (DBSJ) | F147: 840 | H147: =F147-G147 -> 840 | I147: =F147*5% -> 42 | J147: =F147+I147 -> 882 | K147: REENA
A148: Trane BVBA (Abu Dhabi) | B148: 24-0152 | C148: 45360 | D148: 100348311000003 | E148: A5 Envelopes | F148: 540 | H148: =F148-G148 -> 540 | I148: =F148*5% -> 27 | J148: =F148+I148 -> 567 | K148: REENA
A149: GOOD VIBES TRANSPORT L.L.C | B149: 24-0153 | C149: 45360 | D149: 100483620900003 | E149: Job card | F149: 925 | H149: =F149-G149 -> 925 | I149: =F149*5% -> 46.25 | J149: =F149+I149 -> 971.25 | K149: REENA
... A155: Navitas SAE FZ-LLC | B155: 24-0159 | C155: 45362 | D155: 100282822400003 | E155: Business Cards (Alejandro Celli) | F155: 135 | H155: =F155-G155 -> 135 | I155: =F155*5% -> 6.75 | J155: =F155+I155 -> 141.75 | K155: REENA
A156: Stellar Advertising LLC | B156: 24-0160 | C156: March 13,2024 | E156: Taaleem Items | F156: 3703.5 | H156: =F156-G156 -> 3703.5 | I156: =F156*5% -> 185.175 | J156: =F156+I156 -> 3888.675 | K156: REENA
A157: Stellar Advertising LLC | B157: 24-0161 | C157: 45364 | E157: GIS Tshirts | F157: 3360 | H157: =F157-G157 -> 3360 | I157: =F157*5% -> 168 | J157: =F157+I157 -> 3528 | K157: REENA
A158: Stellar Advertising LLC | B158: 24-0162 | C158: 45364 | E158: DBSJP Journal 23 | F158: 475 | H158: =F158-G158 -> 475 | I158: =F158*5% -> 23.75 | J158: =F158+I158 -> 498.75 | K158: REENA
A159: Nanjing Stationery | B159: 24-0163 | C159: 45364 | E159: Note Books 50 | F159: 750 | H159: =F159-G159 -> 750 | I159: =F159*5% -> 37.5 | J159: =F159+I159 -> 787.5 | K159: MARINELLE
A160: Trane BVBA (Dubai Branch) | B160: 24-0164 | C160: 45365 | E160: BC Ifthikar | F160: 405 | H160: =F160-G160 -> 405 | I160: =F160*5% -> 20.25 | J160: =F160+I160 -> 425.25 | K160: REENA
A161: Stellar Advertising LLC | B161: 24-0165 | C161: 45366 | E161: AAG Gift Hampera | F161: 3600 | H161: =F161-G161 -> 3600 | I161: =F161*5% -> 180 | J161: =F161+I161 -> 3780 | K161: REENA
A162: Stellar Advertising LLC | B162: 24-0166 | C162: 45366 | E162: Taylor Wessing Journal | F162: 2242.5 | H162: =F162-G162 -> 2242.5 | I162: =F162*5% -> 112.125 | J162: =F162+I162 -> 2354.625 | K162: REENA
A163: Navitas Middle East FZ - LLC | B163: 24-0167 | C163: 45366 | E163: BC Yulia | F163: 275 | H163: =F163-G163 -> 275 | I163: =F163*5% -> 13.75 | J163: =F163+I163 -> 288.75 | K163: REENA
A164: Pacific Link | B164: 24-0168 | C164: 45369 | E164: Office Branding | F164: 5350 | H164: =F164-G164 -> 5350 | I164: =F164*5% -> 267.5 | J164: =F164+I164 -> 5617.5 | K164: REENA
A165: Stellar Advertising LLC | B165: 24-0169 | C165: 45370 | E165: DBSJ Flyer | F165: 290 | H165: =F165-G165 -> 290 | I165: =F165*5% -> 14.5 | J165: =F165+I165 -> 304.5 | K165: REENA
A166: The Woolwich Institute | B166: 24-0170 | C166: 45371 | E166: BC Anugha | F166: 195 | H166: =F166-G166 -> 195 | I166: =F166*5% -> 9.75 | J166: =F166+I166 -> 204.75 | K166: REENA
A167: BinGhatti | B167: 24-0171 | C167: 45377 | E167: Non Woven Bags | F167: 1725 | H167: =F167-G167 -> 1725 | I167: =F167*5% -> 86.25 | J167: =F167+I167 -> 1811.25 | K167: MARINELLE
A168: Byyu Gifts Trading | B168: 24-0172 | C168: 45371 | E168: RU/Tags/A6 Cards/Tent Cards | F168: 1925 | H168: =F168-G168 -> 1925 | I168: =F168*5% -> 96.25 | J168: =F168+I168 -> 2021.25 | K168: REENA
... A176: Stellar Advertising LLC | B176: 24-0180 | C176: 45378 | E176: Journal (DBSEH) | F176: 450 | H176: =F176-G176 -> 450 | I176: =F176*5% -> 22.5 | J176: =F176+I176 -> 472.5 | K176: REENA
A177: Stellar Advertising LLC | B177: 24-0181 | C177: 45378 | E177: Business card - FICHTE | F177: =210*3 -> 630 | H177: =F177-G177 -> 630 | I177: =F177*5% -> 31.5 | J177: =F177+I177 -> 661.5 | K177: REENA
A178: POWER LEASE VEHICLE RENTAL DMCC | B178: 24-0182 | C178: 45377 | E178: A6 Ramadan Cards -Power Lease/Ikonic | F178: 435 | H178: =F178-G178 -> 435 | I178: =F178*5% -> 21.75 | J178: =F178+I178 -> 456.75 | K178: REENA
A179: Trane BVBA (Dubai Branch) | B179: 24-0183 | C179: 45378 | E179: A3 & A4 ENVELOPES | F179: =1190+425 -> 1615 | H179: =F179-G179 -> 1615 | I179: =F179*5% -> 80.75 | J179: =F179+I179 -> 1695.75 | K179: REENA
A180: Dubai Academic Health Corporation (DAHC) | B180: 24-0184 | C180: 45378 | E180: A4 & A5 Paper Bags | F180: =3950+2970 -> 6920 | H180: =F180-G180 -> 6920 | I180: =F180*5% -> 346 | J180: =F180+I180 -> 7266 | K180: MARINELLE
A181: Lloyds Energy DMCC | B181: 24-0185 | C181: 45379 | E181: Sticker on CRETA Signage | F181: 350 | H181: =F181-G181 -> 350 | I181: =F181*5% -> 17.5 | J181: =F181+I181 -> 367.5 | K181: MARINELLE
A182: Menlo Electric FZE | B182: 24-0186 | C182: 45379 | E182: Polo shirts | F182: =1440 -> 1440 | H182: =F182-G182 -> 1440 | I182: =F182*5% -> 72 | J182: =F182+I182 -> 1512 | K182: MARINELLE
A183: Lloyds Energy DMCC | B183: 24-0187 | C183: 45379 | E183: Notebooks & Business cards | F183: =1100+6775 -> 7875 | H183: =F183-G183 -> 7875 | I183: =F183*5% -> 393.75 | J183: =F183+I183 -> 8268.75 | K183: MARINELLE
...

Sheet Summary REA Adv - AR- 25 Mar24
C3: 2024
B4: Client Names | C4: Jan | D4: Feb | E4: Mar | F4: Grand Total
B5: ADIRONDACK ARCHITECTURAL MODELS INDUSTRY L.L.C | D5: 47.62 | F5: =SUM(C5:E5) -> 47.62
B6: Al Naser International FZE | D6: 3150 | F6: =SUM(C6:E6) -> 3150
B7: AL RASHED UNITED DMCC | D7: 3490 | F7: =SUM(C7:E7) -> 3490
B8: Al Tayer Insignia LLC | D8: 10965 | F8: =SUM(C8:E8) -> 10965
B9: Ali Salim Ali Salim Alqaydi | D9: 2715 | F9: =SUM(C9:E9) -> 2715
B10: AMANI INVESTMENTS L.L.C - FZ | C10: 995 | F10: =SUM(C10:E10) -> 995
B11: ANB AUTOMOBILES L.L.C | D11: 1580 | E11: 1130 | F11: =SUM(C11:E11) -> 2710
B12: Aram Precious Metals Trading FZE | C12: 250 | D12: 3150 | F12: =SUM(C12:E12) -> 3400
B13: A-Technologies FZCO | C13: 6050 | F13: =SUM(C13:E13) -> 6050
B14: Aurantius Real Estate Broker | C14: 553.75 | D14: 2410.5 | E14: =+'REA Adv - Invoices'!G191 -> 792.5 | F14: =SUM(C14:E14) -> 3756.75
B15: AUSTRAL INTERNATIONAL DMCC | C15: 745 | D15: 3150 | F15: =SUM(C15:E15) -> 3895
B16: Austral International FZE | C16: 250 | F16: =SUM(C16:E16) -> 250
B17: Bianca and Bianco Trading LLC | C17: 825 | D17: 310 | F17: =SUM(C17:E17) -> 1135
B18: Bin Ghatti | E18: 1725 | F18: =SUM(C18:E18) -> 1725
B19: Blu Orbit | C19: 1250 | F19: =SUM(C19:E19) -> 1250
B20: BorgRollsWarner Middle East LLC | C20: 14375 | F20: =SUM(C20:E20) -> 14375
B21: Byyus Gift Trading | E21: =1925+'REA Adv - Invoices'!G184+'REA Adv - Invoices'!G190 -> 4660 | F21: =SUM(C21:E21) -> 4660
B22: CJ ICM FZCO | C22: 3150 | F22: =SUM(C22:E22) -> 3150
B23: CLARION SCHOOL LLC | C23: 0 | F23: =SUM(C23:E23) -> 0
B24: Continental Middle East DMCC | D24: 3835 | F24: =SUM(C24:E24) -> 3835
B25: Crescent Real Estate | D25: 1920 | F25: =SUM(C25:E25) -> 1920
B26: Dubai Academic Health /MBRU | E26: =+'REA Adv - Invoices'!G186 -> 6920 | F26: =SUM(C26:E26) -> 6920
B27: DUNECREST AMERICAN SCHOOL L.L.C | C27: 19193.5 | F27: =SUM(C27:E27) -> 19193.5
B28: DYNAMIC EMPLOYMENT SERVICES L.L.C | D28: 892.5 | F28: =SUM(C28:E28) -> 892.5
B29: E and S Luxury Car Rental LLC | C29: 300 | F29: =SUM(C29:E29) -> 300
B30: E V OFFSHORE LIMITED (DUBAI BRANCH) | D30: 1400 | F30: =SUM(C30:E30) -> 1400
B31: EMIRATES FOR UNIVERSAL TYRES L.L.C. | C31: 1315 | F31: =SUM(C31:E31) -> 1315
B32: Enara Properties | C32: 95 | F32: =SUM(C32:E32) -> 95
B33: FAD Institute of Luxury Fashion and Style Dubai | C33: 1690 | F33: =SUM(C33:E33) -> 1690
B34: Global Connect | C34: 120 | D34: 190 | F34: =SUM(C34:E34) -> 310
B35: Golden Tower Technologies | D35: 8850 | F35: =SUM(C35:E35) -> 8850
B36: GOOD VIBES TRANSPORT L.L.C | E36: 925 | F36: =SUM(C36:E36) -> 925
B37: Grandmatic Technical | E37: 285 | F37: =SUM(C37:E37) -> 285
B38: GRAND STAR ALUMINUM & GLASS L.L.C | C38: 8360 | F38: =SUM(C38:E38) -> 8360
B39: Griffith College | D39: 1225 | F39: =SUM(C39:E39) -> 1225
B40: GrokGlobal Services | C40: 4475 | E40: 22177.5 | F40: =SUM(C40:E40) -> 26652.5
B41: Gulftainer | E41: =+'REA Adv - Invoices'!G196 -> 2358.75 | F41: =SUM(C41:E41) -> 2358.75
B42: HOLO MORTGAGE CONSULTANT | C42: 1060 | F42: =SUM(C42:E42) -> 1060
B43: Huxley Associates Global Limited | C43: 1125 | D43: 225 | F43: =SUM(C43:E43) -> 1350
B44: IDP EDUCATION L.L.C | C44: 4813 | D44: 165010.85 | E44: =+'REA Adv - Invoices'!G193 -> 585 | F44: =SUM(C44:E44) -> 170408.85
B45: IDP Education Services Nigeria Limited | C45: 227.907 | F45: =SUM(C45:E45) -> 227.907
B46: Indo Tausch Trading DMCC | D46: 420 | E46: 185 | F46: =SUM(C46:E46) -> 605
B47: Ingersoll-Rand Technical and Services S A R L (Dubai Branch) | C47: 310 | F47: =SUM(C47:E47) -> 310
B48: J C S ARTIFICIAL FLOWERS & PLANTS TRADING L.L.C | D48: 779 | F48: =SUM(C48:E48) -> 779
B49: JUBAILI BROS S.A.L. | C49: 5975 | F49: =SUM(C49:E49) -> 5975
B50: Krishna International FZCO | D50: 13000 | F50: =SUM(C50:E50) -> 13000
B51: Lane Community College | D51: 140 | F51: =SUM(C51:E51) -> 140
B52: LAYAN TRADING FZE | C52: 200 | F52: =SUM(C52:E52) -> 200
B53: Liquid Telecommunications International FZE | D53: 6775 | F53: =SUM(C53:E53) -> 6775
B54: Lloyds Energy DMCC | C54: 1250 | E54: =1250+'REA Adv - Invoices'!G187+'REA Adv - Invoices'!G189 -> 9475 | F54: =SUM(C54:E54) -> 10725
B55: Logic Utilities District Cooling Services LLC | C55: 4252.5 | F55: =SUM(C55:E55) -> 4252.5
B56: M E A D Medical Supplies & Equipment L.L.C | C56: 475 | D56: 1347.5 | F56: =SUM(C56:E56) -> 1822.5
B57: Menlo Electricals FZCo | E57: =+'REA Adv - Invoices'!G188 -> 1440 | F57: =SUM(C57:E57) -> 1440
B58: M Y WORLD TRADING L.L.C | C58: 530 | F58: =SUM(C58:E58) -> 530
B59: MIRA REAL ESTATE BROKERS L.L.C | D59: 3150 | F59: =SUM(C59:E59) -> 3150
B60: Ms. Eunice Lara Rosete | C60: 400 | F60: =SUM(C60:E60) -> 400
B61: Ms. Karine Leonian | C61: 4687.5 | F61: =SUM(C61:E61) -> 4687.5
B62: Nanjing Stationery | E62: =+'REA Adv - Invoices'!G165 -> 750 | F62: =SUM(C62:E62) -> 750
B63: Navitas Middle East FZ - LLC | C63: 10803.35 | E63: =275+'REA Adv - Invoices'!G169+10720 -> 11270 | F63: =SUM(C63:E63) -> 22073.35
B64: Navitas SAE FZ-LLC | E64: 1125 | F64: =SUM(C64:E64) -> 1125
B65: One Blue Clover FZCO | D65: 525 | E65: 550 | F65: =SUM(C65:E65) -> 1075
B66: Orthopro Clinic | C66: 525 | F66: =SUM(C66:E66) -> 525
B67: Pacific Link | E67: 6625 | F67: =SUM(C67:E67) -> 6625
B68: PHARMAPAL DRUG STORE L.L.C | C68: 5781 | F68: =SUM(C68:E68) -> 5781
B69: Radiometer Medical ApS | C69: 14677.74 | F69: =SUM(C69:E69) -> 14677.74
B70: RIF TRUST INVESTMENTS LLC | C70: 380 | F70: =SUM(C70:E70) -> 380
B71: Sea Centre Shipping Services LLC | C71: 3950 | F71: =SUM(C71:E71) -> 3950
B72: Shory Technology L.L.C | C72: 150 | D72: 915 | F72: =SUM(C72:E72) -> 1065
B73: SPECIALISED SPORTS EQUIPMENT LLC | D73: 625 | F73: =SUM(C73:E73) -> 625
B74: SPH Global Holdings LLC | C74: 1250 | F74: =SUM(C74:E74) -> 1250
B75: Stellar Advertising LLC | C75: 9650.49 | D75: 16015.5 | E75: =1960+'REA Adv - Invoices'!G162+'REA Adv - Invoices'!G163+'REA Adv - Invoices'!G164+'REA Adv - Invoices'!G167+'REA Adv - Invoices'!G168+290+'REA Adv - Invoices'!G181+'REA Adv - Invoices'!G182+'REA Adv - Invoices'!G183+'REA Adv - Invoices'!G192 -> 18431 | F75: =SUM(C75:E75) -> 44096.99
B76: Tappy Toes Nursery DWC-LLC | D76: 989 | F76: =SUM(C76:E76) -> 989
B77: Technological University of the Shannon - Ireland | D77: 1925 | F77: =SUM(C77:E77) -> 1925
B78: The Woolwich Institute | E78: =210+195 -> 405 | F78: =SUM(C78:E78) -> 405
B79: Thermo Fisher Scientific S.P.A. | D79: 3335 | F79: =SUM(C79:E79) -> 3335
B80: Trane BVBA (Abu Dhabi) | C80: 405 | E80: 540 | F80: =SUM(C80:E80) -> 945
B81: Trane BVBA (Dubai Branch) | C81: 5975 | D81: 3000 | E81: =810+'REA Adv - Invoices'!G166+'REA Adv - Invoices'!G185 -> 2830 | F81: =SUM(C81:E81) -> 11805
B82: Tristar Transport LLC | C82: 1140 | F82: =SUM(C82:E82) -> 1140
B83: Unique World Business Centre LLC | C83: 375 | D83: 195 | E83: =+'REA Adv - Invoices'!G194+'REA Adv - Invoices'!G195 -> 150 | F83: =SUM(C83:E83) -> 720
B84: VISIONARY FURNITURE TRADING L.L.C | C84: 5373 | F84: =SUM(C84:E84) -> 5373
B85: World Data Feasibility Studies Consultancies | C85: 1780 | F85: =SUM(C85:E85) -> 1780
B87: Grand Total | C87: =SUM(C5:C85) -> 151513.74 | D87: =SUM(D5:D85) -> 267652.47 | E87: =SUM(E5:E85) -> 95334.75 | F87: =SUM(F5:F85) -> 514500.96
B92: Summary Sales per Month | C92: 2024
B93: Team | C93: Jan | D93: Feb | E93: Mar | F93: Grand Total
B94: PROFORMA | D94: 11212.86 | F94: =SUM(C94:E94) -> 11212.86
B95: REENA | C95: 76931.497 | D95: 228941.61 | E95: =28757.5+'REA Adv - Invoices'!G162+'REA Adv - Invoices'!G163+'REA Adv - Invoices'!G164+'REA Adv - Invoices'!G166+'REA Adv - Invoices'!G167+'REA Adv - Invoices'!G168+'REA Adv - Invoices'!G169+20040+'REA Adv - Invoices'!G181+'REA Adv - Invoices'!G182+'REA Adv - Invoices'!G183+'REA Adv - Invoices'!G184+'REA Adv - Invoices'!G185+'REA Adv - Invoices'!G190+'REA Adv - Invoices'!G191+'REA Adv - Invoices'!G192+'REA Adv - Invoices'!G193+'REA Adv - Invoices'!G194+'REA Adv - Invoices'!G195 -> 71536 | F95: =SUM(C95:E95) -> 377409.11
B96: MARINELLE | C96: 68501.24 | D96: 27498 | E96: =1130+750+2975+'REA Adv - Invoices'!G186+'REA Adv - Invoices'!G187+'REA Adv - Invoices'!G188+'REA Adv - Invoices'!G189+'REA Adv - Invoices'!G196 -> 23798.75 | F96: =SUM(C96:E96) -> 119797.99
B97: GLEN | C97: 6081 | F97: =SUM(C97:E97) -> 6081
B98: Grand Total | C98: =SUM(C94:C97) -> 151513.74 | D98: =SUM(D94:D97) -> 267652.47 | E98: =SUM(E94:E97) -> 95334.75 | F98: =SUM(F94:F97) -> 514500.96

Sheet For Pivot
B2: CLIENT | C2: INVOICE NO. | D2: INVOICE DATE | E2: CLIENT TRN | F2: DESCRIPTION | G2: INVOICE SUB-TOTAL | H2: REBATE | I2: INVOICE SUB-TOTAL AFTER REBATE | J2: VAT % AMOUNT | K2: TOTAL INVOICE AMOUNT | L2: Sales Person | M2: =COUNTA(C:C)-1 -> 466 | N2: =GETPIVOTDATA("Count of INVOICE NO.",#REF!)+GETPIVOTDATA("Count of INVOICE NO.",#REF!) -> #REF! | O2: =SUM(G:G) -> 1160237.7 | P2: No of invoice
B3: Stellar Advertising LLC | C3: 24-0001 | D3: 45293 | E3: 100542487200003 | F3: A3 Poster - Jebel Ali School | G3: 425.49 | I3: =G3-H3 -> 425.49 | J3: =G3*5% -> 21.2745 | K3: =G3+J3 -> 446.7645 | L3: REENA | P3: 1
B4: Stellar Advertising LLC | C4: 24-0002 | D4: 45295 | E4: 100542487200003 | F4: A5 Booklet - DBSJP (Nov/Dec) | G4: 415 | I4: =G4-H4 -> 415 | J4: =G4*5% -> 20.75 | K4: =G4+J4 -> 435.75 | L4: REENA | P4: 1
B5: Aurantius Real Estate Broker | C5: 24-0003 | D5: 45295 | E5: 104166051300003 | F5: Business Cards ( Ferhat Doghan ) | G5: 475 | I5: =G5-H5 -> 475 | J5: =G5*5% -> 23.75 | K5: =G5+J5 -> 498.75 | L5: REENA | P5: 1
B6: A-Technologies FZCO | C6: 24-0004 | D6: 45306 | E6: 100312976200003 | F6: Water Bottle , A5 Notebook (Anti-Microbial) , Metal Pen , Box | G6: 5850 | I6: =G6-H6 -> 5850 | J6: =G6*5% -> 292.5 | K6: =G6+J6 -> 6142.5 | L6: MARINELLE | P6: 1
B7: EMIRATES FOR UNIVERSAL TYRES L.L.C. | C7: 24-0005 | D7: 45297 | E7: 100032677500003 | F7: Sticker (Paper) | G7: 425 | I7: =G7-H7 -> 425 | J7: =G7*5% -> 21.25 | K7: =G7+J7 -> 446.25 | L7: REENA | P7: 1
B8: GRAND STAR ALUMINUM & GLASS L.L.C | C8: 24-0006 | D8: 45296 | E8: 100522321700003 | F8: Wooden Board | G8: 7600 | I8: =G8-H8 -> 7600 | J8: =G8*5% -> 380 | K8: =G8+J8 -> 7980 | L8: REENA | P8: 1
B9: VISIONARY FURNITURE TRADING L.L.C | C9: 24-0007 | D9: 45302 | E9: 104037069200003 | F9: Business Cards , Polo Shirts | G9: 848 | I9: =G9-H9 -> 848 | J9: =G9*5% -> 42.4 | K9: =G9+J9 -> 890.4 | L9: REENA | P9: 1
B10: Navitas Middle East FZ - LLC | C10: 24-0008 | D10: 45300 | E10: 100430750800003 | F10: Round neck Tshirt | G10: 380 | I10: =G10-H10 -> 380 | J10: =G10*5% -> 19 | K10: =G10+J10 -> 399 | L10: REENA | P10: 1
B11: Trane BVBA (Abu Dhabi) | C11: 24-0009 | D11: 45316 | E11: 100348311000003 | F11: Business Card ( Mohamed Ben Hamouda ) | G11: 405 | I11: =G11-H11 -> 405 | J11: =G11*5% -> 20.25 | K11: =G11+J11 -> 425.25 | L11: REENA | P11: 1
B12: M Y WORLD TRADING L.L.C | C12: 24-0010 | D12: 45300 | E12: 104014963300003 | F12: Business Cards ( Mr. Mehdi M Taki , Mr. Muhammed Midlaj ) | G12: 530 | I12: =G12-H12 -> 530 | J12: =G12*5% -> 26.5 | K12: =G12+J12 -> 556.5 | L12: REENA | P12: 1
B13: GRAND STAR ALUMINUM & GLASS L.L.C | C13: 24-0011 | D13: 45302 | E13: 100522321700003 | F13: Acrylic Stand | G13: 760 | I13: =G13-H13 -> 760 | J13: =G13*5% -> 38 | K13: =G13+J13 -> 798 | L13: REENA | P13: 1
B14: IDP Education Services Nigeria Limited | C14: 24-0012 | D14: 45300 | E14: - | F14: Polo Shirt | G14: =3.67*62.1 -> 227.907 | I14: =G14-H14 -> 227.907 | J14: =G14*5% -> 11.39535 | K14: =G14+J14 -> 239.30235 | L14: REENA | P14: 1
B15: M E A D Medical Supplies & Equipment L.L.C | C15: 24-0013 | D15: 45303 | E15: 100540543400003 | F15: NCR Book | G15: 475 | I15: =G15-H15 -> 475 | J15: =G15*5% -> 23.75 | K15: =G15+J15 -> 498.75 | L15: MARINELLE | P15: 1
B16: Stellar Advertising LLC | C16: 24-0014 | D16: 45303 | E16: 100542487200003 | F16: Poster , Flag ( Raha International School ) | G16: 440 | I16: =G16-H16 -> 440 | J16: =G16*5% -> 22 | K16: =G16+J16 -> 462 | L16: REENA | P16: 1
B17: Lloyds Energy DMCC | C17: 24-0015 | D17: 45303 | E17: 100056728700003 | F17: Signage (Without Light) | G17: 1250 | I17: =G17-H17 -> 1250 | J17: =G17*5% -> 62.5 | K17: =G17+J17 -> 1312.5 | L17: MARINELLE | P17: 1
B18: EMIRATES FOR UNIVERSAL TYRES L.L.C. | C18: 24-0016 | D18: 45303 | E18: 100032677500003 | F18: Business card ( Rineesh Ali ) | G18: 165 | I18: =G18-H18 -> 165 | J18: =G18*5% -> 8.25 | K18: =G18+J18 -> 173.25 | L18: REENA | P18: 1
B19: Bianca and Bianco Trading LLC | C19: 24-0017 | D19: 45304 | E19: 100482284500003 | F19: Business Card | G19: 825 | I19: =G19-H19 -> 825 | J19: =G19*5% -> 41.25 | K19: =G19+J19 -> 866.25 | L19: REENA | P19: 1
B20: Logic Utilities District Cooling Services LLC | C20: 24-0018 | D20: 45316 | E20: 100567483100003 | F20: Polo Shirts | G20: 4252.5 | I20: =G20-H20 -> 4252.5 | J20: =G20*5% -> 212.625 | K20: =G20+J20 -> 4465.125 | L20: MARINELLE | P20: 1
B21: FAD Institute of Luxury Fashion and Style Dubai | C21: 24-0019 | D21: 45307 | E21: - | F21: Certificate Holder | G21: 1690 | I21: =G21-H21 -> 1690 | J21: =G21*5% -> 84.5 | K21: =G21+J21 -> 1774.5 | L21: MARINELLE | P21: 1
B22: Ingersoll-Rand Technical and Services S A R L (Dubai Branch) | C22: 24-0020 | D22: 45306 | E22: 100399495900003 | F22: Business Card | G22: 310 | I22: =G22-H22 -> 310 | J22: =G22*5% -> 15.5 | K22: =G22+J22 -> 325.5 | L22: MARINELLE | P22: 1
B23: JUBAILI BROS S.A.L. | C23: 24-0021 | D23: 45307 | E23: 100293287700003 | F23: Car Sunshades (Tyvek) | G23: 5975 | I23: =G23-H23 -> 5975 | J23: =G23*5% -> 298.75 | K23: =G23+J23 -> 6273.75 | L23: MARINELLE | P23: 1
B24: Global Connect | C24: 24-0022 | D24: 45303 | E24: - | F24: Rubber stamp | G24: 120 | I24: =G24-H24 -> 120 | J24: =G24*5% -> 6 | K24: =G24+J24 -> 126 | L24: REENA | P24: 1
B25: IDP EDUCATION L.L.C | C25: 24-0023 | D25: 45303 | E25: 100593105800003 | F25: Rubber Stamp | G25: 0 | I25: =G25-H25 -> 0 | J25: =G25*5% -> 0 | K25: =G25+J25 -> 0 | L25: REENA | P25: 1
B26: A-Technologies FZCO | C26: 24-0024 | D26: 45307 | E26: 100312976200003 | F26: Prints for Gift Box | G26: 200 | I26: =G26-H26 -> 200 | J26: =G26*5% -> 10 | K26: =G26+J26 -> 210 | L26: MARINELLE | P26: 1
... B95: Trane BVBA (Dubai Branch) | C95: 24-0093 | D95: 45335 | E95: 100235699400003 | F95: Crystal Trophy | G95: 1800 | I95: =G95-H95 -> 1800 | J95: =G95*5% -> 90 | K95: =G95+J95 -> 1890 | L95: REENA | P95: 1
B96: Krishna International FZCO | C96: 24-0094 | D96: 45332 | E96: 100060213400003 | F96: Wedding Luggage Tags | G96: 13000 | I96: =G96-H96 -> 13000 | J96: =G96*5% -> 650 | K96: =G96+J96 -> 13650 | L96: REENA | P96: 1
B97: One Blue Clover FZCO | C97: 24-0095 | D97: 45338 | E97: - | F97: Letterhead | G97: 525 | I97: =G97-H97 -> 525 | J97: =G97*5% -> 26.25 | K97: =G97+J97 -> 551.25 | L97: REENA | P97: 1
B98: Stellar Advertising LLC | C98: 24-0096 | D98: 45337 | E98: 100542487200003 | F98: Selfie Frame - DBSJP , Prop - #Outstanding | G98: 595 | I98: =G98-H98 -> 595 | J98: =G98*5% -> 29.75 | K98: =G98+J98 -> 624.75 | L98: REENA | P98: 1
B99: Stellar Advertising LLC | C99: 24-0097 | D99: 45338 | E99: 100542487200003 | F99: Roll Up - AAG | G99: 145 | I99: =G99-H99 -> 145 | J99: =G99*5% -> 7.25 | K99: =G99+J99 -> 152.25 | L99: REENA | P99: 1
B100: M E A D Medical Supplies & Equipment L.L.C | C100: 24-0098 | D100: 45341 | E100: 100540543400003 | F100: NCR Book , Business Cards | G100: 860 | I100: =G100-H100 -> 860 | J100: =G100*5% -> 43 | K100: =G100+J100 -> 903 | L100: MARINELLE | P100: 1
B101: Stellar Advertising LLC | C101: 24-0099 | D101: 45342 | E101: 100542487200003 | F101: Letterhead - FICHTE | G101: 625 | I101: =G101-H101 -> 625 | J101: =G101*5% -> 31.25 | K101: =G101+J101 -> 656.25 | L101: REENA | P101: 1
B102: Golden Tower Technologies | C102: 24-0100 | D102: 45338 | E102: 100470289800003 | F102: Flex to be changed for existing light box | G102: 8850 | I102: =G102-H102 -> 8850 | J102: =G102*5% -> 442.5 | K102: =G102+J102 -> 9292.5 | L102: REENA | P102: 1
B103: Thermo Fisher Scientific S.P.A. | C103: 24-0101 | D103: 45338 | E103: IT 07817950152 | F103: Flyer , Recycled 6-in-1 Charging Cable | G103: 3335 | I103: =G103-H103 -> 3335 | J103: =G103*5% -> 166.75 | K103: =G103+J103 -> 3501.75 | L103: MARINELLE | P103: 1
B104: Griffith College | C104: 24-0102 | D104: 45338 | E104: - | F104: Brochure | G104: 1225 | I104: =G104-H104 -> 1225 | J104: =G104*5% -> 61.25 | K104: =G104+J104 -> 1286.25 | L104: REENA | P104: 1
B105: IDP EDUCATION L.L.C | C105: 24-0103 | D105: 45341 | E105: 100593105800003 | F105: Dubai Roadshow Millenium Downtown, 17th Feb 2024 | G105: 103245.5 | I105: =G105-H105 -> 103245.5 | J105: =G105*5% -> 5162.275 | K105: =G105+J105 -> 108407.77 | L105: REENA | P105: 1
B106: IDP EDUCATION L.L.C | C106: 24-0104 | D106: 45341 | E106: 100593105800003 | F106: Abu Dhabi Roadshow 18 Feb 2024, InterContinental | G106: 51717.75 | I106: =G106-H106 -> 51717.75 | J106: =G106*5% -> 2585.8875 | K106: =G106+J106 -> 54303.637 | L106: REENA | P106: 1
B107: DYNAMIC EMPLOYMENT SERVICES L.L.C | C107: 24-0105 | D107: 45343 | E107: 100323347300003 | F107: Parking Signage | G107: 892.5 | I107: =G107-H107 -> 892.5 | J107: =G107*5% -> 44.625 | K107: =G107+J107 -> 937.125 | L107: MARINELLE | P107: 1
B108: Stellar Advertising LLC | C108: 24-0106 | D108: 45343 | E108: 100542487200003 | F108: Flyer - Taylor Wessing | G108: 190 | I108: =G108-H108 -> 190 | J108: =G108*5% -> 9.5 | K108: =G108+J108 -> 199.5 | L108: REENA | P108: 1
B109: Stellar Advertising LLC | C109: 24-0107 | D109: 45342 | E109: 100542487200003 | F109: Journal - DBSEH | G109: 585 | I109: =G109-H109 -> 585 | J109: =G109*5% -> 29.25 | K109: =G109+J109 -> 614.25 | L109: REENA | P109: 1
B110: Crescent Real Estate | C110: 24-0108 | D110: 45343 | E110: 100359923800003 | F110: Polo Shirts | G110: 1920 | I110: =G110-H110 -> 1920 | J110: =G110*5% -> 96 | K110: =G110+J110 -> 2016 | L110: MARINELLE | P110: 1
B111: Indo Tausch Trading DMCC | C111: 24-0109 | D111: 45344 | E111: 100484375900003 | F111: Business Cards , ID Cards | G111: 420 | I111: =G111-H111 -> 420 | J111: =G111*5% -> 21 | K111: =G111+J111 -> 441 | L111: REENA | P111: 1
B112: Stellar Advertising LLC | C112: 24-0110 | D112: 45344 | E112: 100542487200003 | F112: Top Curve Flags - Al Salaam Charter School | G112: 6250 | I112: =G112-H112 -> 6250 | J112: =G112*5% -> 312.5 | K112: =G112+J112 -> 6562.5 | L112: REENA | P112: 1
B113: Stellar Advertising LLC | C113: 24-0111 | D113: 45345 | E113: 100542487200003 | F113: Rollup Banners (GIS) , Designing charges | G113: 390 | I113: =G113-H113 -> 390 | J113: =G113*5% -> 19.5 | K113: =G113+J113 -> 409.5 | L113: REENA | P113: 1
B114: Stellar Advertising LLC | C114: 24-0112 | D114: 45345 | E114: 100542487200003 | F114: Round Neck Tshirts (Wellbeing) - Charter School | G114: 4220.5 | I114: =G114-H114 -> 4220.5 | J114: =G114*5% -> 211.025 | K114: =G114+J114 -> 4431.525 | L114: REENA | P114: 1
B115: Trane BVBA (Dubai Branch) | C115: 24-0113 | D115: 45345 | E115: 100235699400003 | F115: Business Cards ( Dipak M Shelke ) | G115: 405 | I115: =G115-H115 -> 405 | J115: =G115*5% -> 20.25 | K115: =G115+J115 -> 425.25 | L115: REENA | P115: 1
B116: Huxley Associates Global Limited | C116: 24-0114 | D116: 45348 | E116: 100349055200003 | F116: Vertical Matt Veneer Wooden Plaque | G116: 225 | I116: =G116-H116 -> 225 | J116: =G116*5% -> 11.25 | K116: =G116+J116 -> 236.25 | L116: MARINELLE | P116: 1
... B118: Continental Middle East DMCC | C118: 24-0116 | D118: 45350 | E118: 100377505100003 | F118: Trophy | G118: 3150 | I118: =G118-H118 -> 3150 | J118: =G118*5% -> 157.5 | K118: =G118+J118 -> 3307.5 | L118: REENA | P118: 1
B119: IDP EDUCATION L.L.C | C119: 24-0117 | D119: 45345 | E119: 100593105800003 | F119: Name Tags , Expo Cards | G119: 0 | I119: =G119-H119 -> 0 | J119: =G119*5% -> 0 | K119: =G119+J119 -> 0 | L119: REENA | P119: 1
B120: IDP EDUCATION L.L.C | C120: 24-0118 | D120: 45345 | E120: 100593105800003 | F120: IDP Excellence Awards - 21-Feb-24 | G120: 7142.1 | I120: =G120-H120 -> 7142.1 | J120: =G120*5% -> 357.105 | K120: =G120+J120 -> 7499.205 | L120: REENA | P120: 1
B121: IDP EDUCATION L.L.C | C121: 24-0119 | D121: 45345 | E121: 100593105800003 | F121: Roll up , A3 Posters , Certificates | G121: 1419 | I121: =G121-H121 -> 1419 | J121: =G121*5% -> 70.95 | K121: =G121+J121 -> 1489.95 | L121: REENA | P121: 1
B122: IDP EDUCATION L.L.C | C122: 24-0120 | D122: 45345 | E122: 100593105800003 | F122: IDP Business Cards - (Abu Dhabi) | G122: 960 | I122: =G122-H122 -> 960 | J122: =G122*5% -> 48 | K122: =G122+J122 -> 1008 | L122: REENA | P122: 1
B123: IDP EDUCATION L.L.C | C123: 24-0121 | D123: 45345 | E123: 100593105800003 | F123: IDP Business Cards - (Dubai ) | G123: 0 | I123: =G123-H123 -> 0 | J123: =G123*5% -> 0 | K123: =G123+J123 -> 0 | L123: REENA | P123: 1
B124: AL RASHED UNITED DMCC | C124: 24-0122 | D124: 45351 | E124: 100246622300003 | F124: Business card , Ribbons with printing , Paper Bag , Paper Stickers , Wrapping Paper | G124: 3490 | I124: =G124-H124 -> 3490 | J124: 174 | K124: =G124+J124 -> 3664 | L124: REENA | P124: 1
B125: Liquid Telecommunications International FZE | C125: 24-0123 | D125: 45348 | E125: 100247605700003 | F125: Gift Box - Black , Paper Bag | G125: 0 | I125: =G125-H125 -> 0 | J125: =G125*5% -> 0 | K125: =G125+J125 -> 0 | L125: REENA | P125: 1
B126: Bianca and Bianco Trading LLC | C126: 24-0124 | D126: 45351 | E126: 100482284500003 | F126: Business Card | G126: 310 | I126: =G126-H126 -> 310 | J126: =G126*5% -> 15.5 | K126: =G126+J126 -> 325.5 | L126: REENA | P126: 1
B127: Liquid Telecommunications International FZE | C127: 24-0125 | D127: 45349 | E127: 100247605700003 | F127: Gift Box - Black , Paper Bag | G127: 6775 | I127: =G127-H127 -> 6775 | J127: =G127*5% -> 338.75 | K127: =G127+J127 -> 7113.75 | L127: REENA | P127: 1
B128: Shory Technology L.L.C | C128: 24-0126 | D128: 45349 | E128: 100435244700003 | F128: Big Card, Small Card, Thank You Card | G128: 915 | I128: =G128-H128 -> 915 | J128: =G128*5% -> 45.75 | K128: =G128+J128 -> 960.75 | L128: MARINELLE | P128: 1
B129: Technological University of the Shannon - Ireland | C129: 24-0127 | D129: 45349 | E129: - | F129: Brochure 2024 , Courier Charges to Abu Dhabi | G129: 1925 | I129: =G129-H129 -> 1925 | J129: =G129*5% -> 96.25 | K129: =G129+J129 -> 2021.25 | L129: REENA | P129: 1
B130: Aram Precious Metals Trading FZE | C130: 24-0128 | D130: 45350 | E130: 104020641700003 | F130: Website Designing and Development ( 75% Advance Invoice ) | G130: 2362.38 | I130: =G130-H130 -> 2362.38 | J130: =G130*5% -> 118.119 | K130: =G130+J130 -> 2480.499 | L130: MARINELLE | P130: 1
B131: Al Naser International FZE | C131: 24-0129 | D131: 45350 | E131: 100566746200003 | F131: Website Designing and Development ( 75% Advance Invoice ) | G131: 2362.38 | I131: =G131-H131 -> 2362.38 | J131: =G131*5% -> 118.119 | K131: =G131+J131 -> 2480.499 | L131: MARINELLE | P131: 1
B132: AUSTRAL INTERNATIONAL DMCC | C132: 24-0130 | D132: 45350 | E132: 100494671900003 | F132: Website Designing and Development ( 75% Advance Invoice ) | G132: 2362.38 | I132: =G132-H132 -> 2362.38 | J132: =G132*5% -> 118.119 | K132: =G132+J132 -> 2480.499 | L132: MARINELLE | P132: 1
B133: ADIRONDACK ARCHITECTURAL MODELS INDUSTRY L.L.C | C133: 24-0131 | D133: 45350 | E133: 104061117800003 | F133: Sampling Charges - Polo Shirt | G133: 47.62 | I133: =G133-H133 -> 47.62 | J133: =G133*5% -> 2.381 | K133: =G133+J133 -> 50.001 | L133: REENA | P133: 1
B134: Aurantius Real Estate Broker | C134: 24-0132 | D134: 45351 | E134: 104166051300003 | F134: A4 Envelopes (customized) , DL Envelopes (customized) , Top spiral Notebook | G134: 1248 | I134: =G134-H134 -> 1248 | J134: =G134*5% -> 62.4 | K134: =G134+J134 -> 1310.4 | L134: REENA | P134: 1
B135: Unique World Business Centre LLC | C135: 24-0133 | D135: 45351 | E135: 100048520900003 | F135: Board Supply February, 2024 | G135: 90 | I135: =G135-H135 -> 90 | J135: =G135*5% -> 4.5 | K135: =G135+J135 -> 94.5 | L135: REENA | P135: 1
B136: Unique World Business Centre LLC | C136: 24-0134 | D136: 45351 | E136: 100048520900003 | F136: Board Supply February, 2024 | G136: 105 | I136: =G136-H136 -> 105 | J136: =G136*5% -> 5.25 | K136: =G136+J136 -> 110.25 | L136: REENA | P136: 1
B137: Navitas SAE FZ-LLC | C137: 24-0135 | D137: 45352 | E137: 100282822400003 | F137: Table cloth - Bridal Satin , A4 Flyer (ICN) | G137: 485 | I137: =G137-H137 -> 485 | J137: =G137*5% -> 24.25 | K137: =G137+J137 -> 509.25 | L137: REENA | P137: 1
B138: Stellar Advertising LLC | C138: 24-0136 | D138: 45351 | E138: 100542487200003 | F138: Customized Vest - Taaleem | G138: 1890 | I138: =G138-H138 -> 1890 | J138: =G138*5% -> 94.5 | K138: =G138+J138 -> 1984.5 | L138: REENA | P138: 1
B139: M E A D Medical Supplies & Equipment L.L.C | C139: 24-0137 | D139: 45351 | E139: 100540543400003 | F139: Receipt Voucher | G139: 487.5 | I139: =G139-H139 -> 487.5 | J139: =G139*5% -> 24.375 | K139: =G139+J139 -> 511.875 | L139: MARINELLE | P139: 1
B140: Aurantius Real Estate Broker | C140: 24-0138 | D140: 45351 | E140: 104166051300003 | F140: Metal Pen , A4 Notepad | G140: 1162.5 | I140: =G140-H140 -> 1162.5 | J140: =G140*5% -> 58.125 | K140: =G140+J140 -> 1220.625 | L140: REENA | P140: 1
B141: Aram Precious Metals Trading FZE | C141: 24-0139 | D141: 45350 | E141: 104020641700003 | F141: Website Designing and Development ( 25% Final Invoice ) | G141: 787.62 | I141: =G141-H141 -> 787.62 | J141: =G141*5% -> 39.381 | K141: =G141+J141 -> 827.001 | L141: MARINELLE | P141: 1 | Q141: IN
B142: Al Naser International FZE | C142: 24-0140 | D142: 45350 | E142: 100566746200003 | F142: Website Designing and Development ( 25% Final Invoice ) | G142: 787.62 | I142: =G142-H142 -> 787.62 | J142: =G142*5% -> 39.381 | K142: =G142+J142 -> 827.001 | L142: MARINELLE | P142: 1 | Q142: IN
B143: AUSTRAL INTERNATIONAL DMCC | C143: 24-0141 | D143: 45350 | E143: 100494671900003 | F143: Website Designing and Development ( 25% Final Invoice ) | G143: 787.62 | I143: =G143-H143 -> 787.62 | J143: =G143*5% -> 39.381 | K143: =G143+J143 -> 827.001 | L143: MARINELLE | P143: 1 | Q143: IN
B144: Stellar Advertising LLC | C144: 24-0142 | D144: 45352 | E144: 100542487200003 | F144: Business cards (Taaleem) | G144: 450 | I144: =G144-H144 -> 450 | J144: =G144*5% -> 22.5 | K144: =G144+J144 -> 472.5 | L144: REENA | P144: 1
B145: Navitas Middle East FZ - LLC | C145: 24-0143 | D145: 45355 | E145: 100430750800003 | F145: Business card | G145: 275 | I145: =G145-H145 -> 275 | J145: =G145*5% -> 13.75 | K145: =G145+J145 -> 288.75 | L145: REENA | P145: 1
B146: Navitas SAE FZ-LLC | C146: 24-0144 | D146: 45355 | E146: 100282822400003 | F146: Rollup Banner , A3 Desktop Rollup , A4 Flyer (ICN) | G146: 505 | I146: =G146-H146 -> 505 | J146: =G146*5% -> 25.25 | K146: =G146+J146 -> 530.25 | L146: REENA | P146: 1
B147: Stellar Advertising LLC | C147: 24-0145 | D147: 45355 | E147: 100542487200003 | F147: Business Card - DBSJ | G147: 220 | I147: =G147-H147 -> 220 | J147: =G147*5% -> 11 | K147: =G147+J147 -> 231 | L147: REENA | P147: 1
B148: Trane BVBA (Dubai Branch) | C148: 24-0146 | D148: 45356 | E148: 100235699400003 | F148: Business Cards (Jomer Pinohermoso) | G148: 405 | I148: =G148-H148 -> 405 | J148: =G148*5% -> 20.25 | K148: =G148+J148 -> 425.25 | L148: REENA | P148: 1
B149: GrokGlobal Services | C149: 24-0147 | D149: 45353 | E149: - | F149: Student Gift Set of A5 Notebook and Pen With Bamboo Element , Jute Bag | G149: 18930 | I149: =G149-H149 -> 18930 | J149: =G149*5% -> 946.5 | K149: =G149+J149 -> 19876.5 | L149: REENA | P149: 1
B150: GrokGlobal Services | C150: 24-0148 | D150: 45355 | E150: - | F150: Brochure - Pre Departure | G150: 2585 | I150: =G150-H150 -> 2585 | J150: =G150*5% -> 129.25 | K150: =G150+J150 -> 2714.25 | L150: REENA | P150: 1
B151: ANB AUTOMOBILES L.L.C | C151: 24-0149 | D151: 45358 | E151: 100433257100003 | F151: Black Mug | G151: 1130 | I151: =G151-H151 -> 1130 | J151: =G151*5% -> 56.5 | K151: =G151+J151 -> 1186.5 | L151: MARINELLE | P151: 1
B152: Trane BVBA (Dubai Branch) | C152: 24-0150 | D152: 45356 | E152: 100235699400003 | F152: Business Cards (HAKIM LABRAHMI) | G152: 405 | I152: =G152-H152 -> 405 | J152: =G152*5% -> 20.25 | K152: =G152+J152 -> 425.25 | L152: REENA | P152: 1
B153: Stellar Advertising LLC | C153: 24-0151 | D153: 45357 | E153: 100542487200003 | F153: Leaflet - 3 fold (DBSJ) | G153: 840 | I153: =G153-H153 -> 840 | J153: =G153*5% -> 42 | K153: =G153+J153 -> 882 | L153: REENA | P153: 1
B154: Trane BVBA (Abu Dhabi) | C154: 24-0152 | D154: 45360 | E154: 100348311000003 | F154: A5 Envelopes | G154: 540 | I154: =G154-H154 -> 540 | J154: =G154*5% -> 27 | K154: =G154+J154 -> 567 | L154: REENA | P154: 1
B155: GOOD VIBES TRANSPORT L.L.C | C155: 24-0153 | D155: 45360 | E155: 100483620900003 | F155: Job card | G155: 925 | I155: =G155-H155 -> 925 | J155: =G155*5% -> 46.25 | K155: =G155+J155 -> 971.25 | L155: REENA | P155: 1
... B161: Navitas SAE FZ-LLC | C161: 24-0159 | D161: 45362 | E161: 100282822400003 | F161: Business Cards (Alejandro Celli) | G161: 135 | I161: =G161-H161 -> 135 | J161: =G161*5% -> 6.75 | K161: =G161+J161 -> 141.75 | L161: REENA | P161: 1
B162: Stellar Advertising LLC | C162: 24-0160 | D162: 45364 | F162: Taaleem Items | G162: 3703.5 | I162: =G162-H162 -> 3703.5 | J162: =G162*5% -> 185.175 | K162: =G162+J162 -> 3888.675 | L162: REENA | P162: 1
B163: Stellar Advertising LLC | C163: 24-0161 | D163: 45364 | F163: GIS Tshirts | G163: 3360 | I163: =G163-H163 -> 3360 | J163: =G163*5% -> 168 | K163: =G163+J163 -> 3528 | L163: REENA | P163: 1
B164: Stellar Advertising LLC | C164: 24-0162 | D164: 45364 | F164: DBSJP Journal 23 | G164: 475 | I164: =G164-H164 -> 475 | J164: =G164*5% -> 23.75 | K164: =G164+J164 -> 498.75 | L164: REENA | P164: 1
B165: Nanjing Stationery | C165: 24-0163 | D165: 45364 | F165: Note Books 50 | G165: 750 | I165: =G165-H165 -> 750 | J165: =G165*5% -> 37.5 | K165: =G165+J165 -> 787.5 | L165: MARINELLE | P165: 1
B166: Trane BVBA (Dubai Branch) | C166: 24-0164 | D166: 45365 | F166: BC Ifthikar | G166: 405 | I166: =G166-H166 -> 405 | J166: =G166*5% -> 20.25 | K166: =G166+J166 -> 425.25 | L166: REENA | P166: 1
B167: Stellar Advertising LLC | C167: 24-0165 | D167: 45366 | F167: AAG Gift Hampera | G167: 3600 | I167: =G167-H167 -> 3600 | J167: =G167*5% -> 180 | K167: =G167+J167 -> 3780 | L167: REENA | P167: 1
B168: Stellar Advertising LLC | C168: 24-0166 | D168: 45366 | F168: Taylor Wessing Journal | G168: 2242.5 | I168: =G168-H168 -> 2242.5 | J168: =G168*5% -> 112.125 | K168: =G168+J168 -> 2354.625 | L168: REENA | P168: 1
B169: Navitas Middle East FZ - LLC | C169: 24-0167 | D169: 45366 | F169: BC Yulia | G169: 275 | I169: =G169-H169 -> 275 | J169: =G169*5% -> 13.75 | K169: =G169+J169 -> 288.75 | L169: REENA | P169: 1
B170: Pacific Link | C170: 24-0168 | D170: 45369 | F170: Office Branding | G170: 5350 | I170: =G170-H170 -> 5350 | J170: =G170*5% -> 267.5 | K170: =G170+J170 -> 5617.5 | L170: REENA | P170: 1
B171: Stellar Advertising LLC | C171: 24-0169 | D171: 45370 | F171: DBSJ Flyer | G171: 290 | I171: =G171-H171 -> 290 | J171: =G171*5% -> 14.5 | K171: =G171+J171 -> 304.5 | L171: REENA | P171: 1
B172: The Woolwich Institute | C172: 24-0170 | D172: 45371 | F172: BC Anugha | G172: 195 | I172: =G172-H172 -> 195 | J172: =G172*5% -> 9.75 | K172: =G172+J172 -> 204.75 | L172: REENA | P172: 1
B173: BinGhatti | C173: 24-0171 | D173: 45377 | F173: Non Woven Bags | G173: 1725 | I173: =G173-H173 -> 1725 | J173: =G173*5% -> 86.25 | K173: =G173+J173 -> 1811.25 | L173: MARINELLE | P173: 1
... B177: Grandmatic | C177: 24-0175 | D177: 45374 | F177: NCR Book | G177: 285 | I177: =G177-H177 -> 285 | J177: =G177*5% -> 14.25 | K177: =G177+J177 -> 299.25 | L177: REENA | P177: 1
B178: Lloyds Energy DMCC | C178: 24-0176 | D178: 45376 | E178: 100056728700003 | F178: Office Signage | G178: 1250 | I178: =G178-H178 -> 1250 | J178: =G178*5% -> 62.5 | K178: =G178+J178 -> 1312.5 | L178: MARINELLE | P178: 1
...

Sheet calc
B2: CLIENT | C2: INVOICE NO. | D2: INVOICE DATE | E2: CLIENT TRN | F2: DESCRIPTION | G2: INVOICE SUB-TOTAL | H2: REBATE | I2: INVOICE SUB-TOTAL AFTER REBATE | J2: VAT % AMOUNT | K2: TOTAL INVOICE AMOUNT | L2: Sales Person | M2: =COUNTA(C:C)-1 -> 404 | N2: =GETPIVOTDATA("Count of INVOICE NO.",#REF!)+GETPIVOTDATA("Count of INVOICE NO.",#REF!) -> #REF! | O2: =SUM(G:G) -> 1049942.5 | P2: No of invoice
B3: Stellar Advertising LLC | C3: 24-0001 | D3: 45293 | E3: 100542487200003 | F3: A3 Poster - Jebel Ali School | G3: 425.49 | I3: =G3-H3 -> 425.49 | J3: =G3*5% -> 21.2745 | K3: =G3+J3 -> 446.7645 | L3: REENA | P3: 1
B4: Stellar Advertising LLC | C4: 24-0002 | D4: 45295 | E4: 100542487200003 | F4: A5 Booklet - DBSJP (Nov/Dec) | G4: 415 | I4: =G4-H4 -> 415 | J4: =G4*5% -> 20.75 | K4: =G4+J4 -> 435.75 | L4: REENA | P4: 1
B5: Aurantius Real Estate Broker | C5: 24-0003 | D5: 45295 | E5: 104166051300003 | F5: Business Cards ( Ferhat Doghan ) | G5: 475 | I5: =G5-H5 -> 475 | J5: =G5*5% -> 23.75 | K5: =G5+J5 -> 498.75 | L5: REENA | P5: 1
B6: A-Technologies FZCO | C6: 24-0004 | D6: 45306 | E6: 100312976200003 | F6: Water Bottle , A5 Notebook (Anti-Microbial) , Metal Pen , Box | G6: 5850 | I6: =G6-H6 -> 5850 | J6: =G6*5% -> 292.5 | K6: =G6+J6 -> 6142.5 | L6: MARINELLE | P6: 1
B7: EMIRATES FOR UNIVERSAL TYRES L.L.C. | C7: 24-0005 | D7: 45297 | E7: 100032677500003 | F7: Sticker (Paper) | G7: 425 | I7: =G7-H7 -> 425 | J7: =G7*5% -> 21.25 | K7: =G7+J7 -> 446.25 | L7: REENA | P7: 1
B8: GRAND STAR ALUMINUM & GLASS L.L.C | C8: 24-0006 | D8: 45296 | E8: 100522321700003 | F8: Wooden Board | G8: 7600 | I8: =G8-H8 -> 7600 | J8: =G8*5% -> 380 | K8: =G8+J8 -> 7980 | L8: REENA | P8: 1
B9: VISIONARY FURNITURE TRADING L.L.C | C9: 24-0007 | D9: 45302 | E9: 104037069200003 | F9: Business Cards , Polo Shirts | G9: 848 | I9: =G9-H9 -> 848 | J9: =G9*5% -> 42.4 | K9: =G9+J9 -> 890.4 | L9: REENA | P9: 1
B10: Navitas Middle East FZ - LLC | C10: 24-0008 | D10: 45300 | E10: 100430750800003 | F10: Round neck Tshirt | G10: 380 | I10: =G10-H10 -> 380 | J10: =G10*5% -> 19 | K10: =G10+J10 -> 399 | L10: REENA | P10: 1
B11: Trane BVBA (Dubai Branch) | C11: 24-0009 | D11: 45316 | E11: 100348311000003 | F11: Business Card ( Mohamed Ben Hamouda ) | G11: 405 | I11: =G11-H11 -> 405 | J11: =G11*5% -> 20.25 | K11: =G11+J11 -> 425.25 | L11: REENA | P11: 1
B12: M Y WORLD TRADING L.L.C | C12: 24-0010 | D12: 45300 | E12: 104014963300003 | F12: Business Cards ( Mr. Mehdi M Taki , Mr. Muhammed Midlaj ) | G12: 530 | I12: =G12-H12 -> 530 | J12: =G12*5% -> 26.5 | K12: =G12+J12 -> 556.5 | L12: REENA | P12: 1
B13: GRAND STAR ALUMINUM & GLASS L.L.C | C13: 24-0011 | D13: 45302 | E13: 100522321700003 | F13: Acrylic Stand | G13: 760 | I13: =G13-H13 -> 760 | J13: =G13*5% -> 38 | K13: =G13+J13 -> 798 | L13: REENA | P13: 1
B14: IDP EDUCATION L.L.C | C14: 24-0012 | D14: 45300 | E14: - | F14: Polo Shirt | G14: =3.67*62.1 -> 227.907 | I14: =G14-H14 -> 227.907 | J14: =G14*5% -> 11.39535 | K14: =G14+J14 -> 239.30235 | L14: REENA | P14: 1
B15: M E A D Medical Supplies & Equipment L.L.C | C15: 24-0013 | D15: 45303 | E15: 100540543400003 | F15: NCR Book | G15: 475 | I15: =G15-H15 -> 475 | J15: =G15*5% -> 23.75 | K15: =G15+J15 -> 498.75 | L15: MARINELLE | P15: 1
B16: Stellar Advertising LLC | C16: 24-0014 | D16: 45303 | E16: 100542487200003 | F16: Poster , Flag ( Raha International School ) | G16: 440 | I16: =G16-H16 -> 440 | J16: =G16*5% -> 22 | K16: =G16+J16 -> 462 | L16: REENA | P16: 1
B17: Lloyds Energy DMCC | C17: 24-0015 | D17: 45303 | E17: 100056728700003 | F17: Signage (Without Light) | G17: 1250 | I17: =G17-H17 -> 1250 | J17: =G17*5% -> 62.5 | K17: =G17+J17 -> 1312.5 | L17: MARINELLE | P17: 1
B18: EMIRATES FOR UNIVERSAL TYRES L.L.C. | C18: 24-0016 | D18: 45303 | E18: 100032677500003 | F18: Business card ( Rineesh Ali ) | G18: 165 | I18: =G18-H18 -> 165 | J18: =G18*5% -> 8.25 | K18: =G18+J18 -> 173.25 | L18: REENA | P18: 1
B19: Bianca and Bianco Trading LLC | C19: 24-0017 | D19: 45304 | E19: 100482284500003 | F19: Business Card | G19: 825 | I19: =G19-H19 -> 825 | J19: =G19*5% -> 41.25 | K19: =G19+J19 -> 866.25 | L19: REENA | P19: 1
B20: Logic Utilities District Cooling Services LLC | C20: 24-0018 | D20: 45316 | E20: 100567483100003 | F20: Polo Shirts | G20: 4252.5 | I20: =G20-H20 -> 4252.5 | J20: =G20*5% -> 212.625 | K20: =G20+J20 -> 4465.125 | L20: MARINELLE | P20: 1
B21: FAD Institute of Luxury Fashion and Style Dubai | C21: 24-0019 | D21: 45307 | E21: - | F21: Certificate Holder | G21: 1690 | I21: =G21-H21 -> 1690 | J21: =G21*5% -> 84.5 | K21: =G21+J21 -> 1774.5 | L21: MARINELLE | P21: 1
B22: Ingersoll-Rand Technical and Services S A R L (Dubai Branch) | C22: 24-0020 | D22: 45306 | E22: 100399495900003 | F22: Business Card | G22: 310 | I22: =G22-H22 -> 310 | J22: =G22*5% -> 15.5 | K22: =G22+J22 -> 325.5 | L22: MARINELLE | P22: 1
B23: JUBAILI BROS S.A.L. | C23: 24-0021 | D23: 45307 | E23: 100293287700003 | F23: Car Sunshades (Tyvek) | G23: 5975 | I23: =G23-H23 -> 5975 | J23: =G23*5% -> 298.75 | K23: =G23+J23 -> 6273.75 | L23: MARINELLE | P23: 1
B24: Global Connect | C24: 24-0022 | D24: 45303 | E24: - | F24: Rubber stamp | G24: 120 | I24: =G24-H24 -> 120 | J24: =G24*5% -> 6 | K24: =G24+J24 -> 126 | L24: REENA | P24: 1
B25: IDP EDUCATION L.L.C | C25: 24-0023 | D25: 45303 | E25: 100593105800003 | F25: Rubber Stamp | G25: 0 | I25: =G25-H25 -> 0 | J25: =G25*5% -> 0 | K25: =G25+J25 -> 0 | L25: REENA | P25: 1
B26: A-Technologies FZCO | C26: 24-0024 | D26: 45307 | E26: 100312976200003 | F26: Prints for Gift Box | G26: 200 | I26: =G26-H26 -> 200 | J26: =G26*5% -> 10 | K26: =G26+J26 -> 210 | L26: MARINELLE | P26: 1
... B95: Trane BVBA (Dubai Branch) | C95: 24-0093 | D95: 45335 | E95: 100235699400003 | F95: Crystal Trophy | G95: 1800 | I95: =G95-H95 -> 1800 | J95: =G95*5% -> 90 | K95: =G95+J95 -> 1890 | L95: REENA | P95: 1
B96: Krishna International FZCO | C96: 24-0094 | D96: 45332 | E96: 100060213400003 | F96: Wedding Luggage Tags | G96: 13000 | I96: =G96-H96 -> 13000 | J96: =G96*5% -> 650 | K96: =G96+J96 -> 13650 | L96: REENA | P96: 1
B97: One Blue Clover FZCO | C97: 24-0095 | D97: 45338 | E97: - | F97: Letterhead | G97: 525 | I97: =G97-H97 -> 525 | J97: =G97*5% -> 26.25 | K97: =G97+J97 -> 551.25 | L97: REENA | P97: 1
B98: Stellar Advertising LLC | C98: 24-0096 | D98: 45337 | E98: 100542487200003 | F98: Selfie Frame - DBSJP , Prop - #Outstanding | G98: 595 | I98: =G98-H98 -> 595 | J98: =G98*5% -> 29.75 | K98: =G98+J98 -> 624.75 | L98: REENA | P98: 1
B99: Stellar Advertising LLC | C99: 24-0097 | D99: 45338 | E99: 100542487200003 | F99: Roll Up - AAG | G99: 145 | I99: =G99-H99 -> 145 | J99: =G99*5% -> 7.25 | K99: =G99+J99 -> 152.25 | L99: REENA | P99: 1
B100: M E A D Medical Supplies & Equipment L.L.C | C100: 24-0098 | D100: 45341 | E100: 100540543400003 | F100: NCR Book , Business Cards | G100: 860 | I100: =G100-H100 -> 860 | J100: =G100*5% -> 43 | K100: =G100+J100 -> 903 | L100: MARINELLE | P100: 1
B101: Stellar Advertising LLC | C101: 24-0099 | D101: 45342 | E101: 100542487200003 | F101: Letterhead - FICHTE | G101: 625 | I101: =G101-H101 -> 625 | J101: =G101*5% -> 31.25 | K101: =G101+J101 -> 656.25 | L101: REENA | P101: 1
B102: Golden Tower Technologies | C102: 24-0100 | D102: 45338 | E102: 100470289800003 | F102: Flex to be changed for existing light box | G102: 8850 | I102: =G102-H102 -> 8850 | J102: =G102*5% -> 442.5 | K102: =G102+J102 -> 9292.5 | L102: REENA | P102: 1
B103: Thermo Fisher Scientific S.P.A. | C103: 24-0101 | D103: 45338 | E103: IT 07817950152 | F103: Flyer , Recycled 6-in-1 Charging Cable | G103: 3335 | I103: =G103-H103 -> 3335 | J103: =G103*5% -> 166.75 | K103: =G103+J103 -> 3501.75 | L103: MARINELLE | P103: 1
B104: Griffith College | C104: 24-0102 | D104: 45338 | E104: - | F104: Brochure | G104: 1225 | I104: =G104-H104 -> 1225 | J104: =G104*5% -> 61.25 | K104: =G104+J104 -> 1286.25 | L104: REENA | P104: 1
B105: IDP EDUCATION L.L.C | C105: 24-0103 | D105: 45341 | E105: 100593105800003 | F105: Dubai Roadshow Millenium Downtown, 17th Feb 2024 | G105: 103245.5 | I105: =G105-H105 -> 103245.5 | J105: =G105*5% -> 5162.275 | K105: =G105+J105 -> 108407.77 | L105: REENA | P105: 1
B106: IDP EDUCATION L.L.C | C106: 24-0104 | D106: 45341 | E106: 100593105800003 | F106: Abu Dhabi Roadshow 18 Feb 2024, InterContinental | G106: 51717.75 | I106: =G106-H106 -> 51717.75 | J106: =G106*5% -> 2585.8875 | K106: =G106+J106 -> 54303.637 | L106: REENA | P106: 1
B107: DYNAMIC EMPLOYMENT SERVICES L.L.C | C107: 24-0105 | D107: 45343 | E107: 100323347300003 | F107: Parking Signage | G107: 892.5 | I107: =G107-H107 -> 892.5 | J107: =G107*5% -> 44.625 | K107: =G107+J107 -> 937.125 | L107: MARINELLE | P107: 1
B108: Stellar Advertising LLC | C108: 24-0106 | D108: 45343 | E108: 100542487200003 | F108: Flyer - Taylor Wessing | G108: 190 | I108: =G108-H108 -> 190 | J108: =G108*5% -> 9.5 | K108: =G108+J108 -> 199.5 | L108: REENA | P108: 1
B109: Stellar Advertising LLC | C109: 24-0107 | D109: 45342 | E109: 100542487200003 | F109: Journal - DBSEH | G109: 585 | I109: =G109-H109 -> 585 | J109: =G109*5% -> 29.25 | K109: =G109+J109 -> 614.25 | L109: REENA | P109: 1
B110: Crescent Real Estate | C110: 24-0108 | D110: 45343 | E110: 100359923800003 | F110: Polo Shirts | G110: 1920 | I110: =G110-H110 -> 1920 | J110: =G110*5% -> 96 | K110: =G110+J110 -> 2016 | L110: MARINELLE | P110: 1
B111: Indo Tausch Trading DMCC | C111: 24-0109 | D111: 45344 | E111: 100484375900003 | F111: Business Cards , ID Cards | G111: 420 | I111: =G111-H111 -> 420 | J111: =G111*5% -> 21 | K111: =G111+J111 -> 441 | L111: REENA | P111: 1
B112: Stellar Advertising LLC | C112: 24-0110 | D112: 45344 | E112: 100542487200003 | F112: Top Curve Flags - Al Salaam Charter School | G112: 6250 | I112: =G112-H112 -> 6250 | J112: =G112*5% -> 312.5 | K112: =G112+J112 -> 6562.5 | L112: REENA | P112: 1
B113: Stellar Advertising LLC | C113: 24-0111 | D113: 45345 | E113: 100542487200003 | F113: Rollup Banners (GIS) , Designing charges | G113: 390 | I113: =G113-H113 -> 390 | J113: =G113*5% -> 19.5 | K113: =G113+J113 -> 409.5 | L113: REENA | P113: 1
B114: Stellar Advertising LLC | C114: 24-0112 | D114: 45345 | E114: 100542487200003 | F114: Round Neck Tshirts (Wellbeing) - Charter School | G114: 4220.5 | I114: =G114-H114 -> 4220.5 | J114: =G114*5% -> 211.025 | K114: =G114+J114 -> 4431.525 | L114: REENA | P114: 1
B115: Trane BVBA (Dubai Branch) | C115: 24-0113 | D115: 45345 | E115: 100235699400003 | F115: Business Cards ( Dipak M Shelke ) | G115: 405 | I115: =G115-H115 -> 405 | J115: =G115*5% -> 20.25 | K115: =G115+J115 -> 425.25 | L115: REENA | P115: 1
B116: Huxley Associates Global Limited | C116: 24-0114 | D116: 45348 | E116: 100349055200003 | F116: Vertical Matt Veneer Wooden Plaque | G116: 225 | I116: =G116-H116 -> 225 | J116: =G116*5% -> 11.25 | K116: =G116+J116 -> 236.25 | L116: MARINELLE | P116: 1
... B118: Continental Middle East DMCC | C118: 24-0116 | D118: 45350 | E118: 100377505100003 | F118: Trophy | G118: 3150 | I118: =G118-H118 -> 3150 | J118: =G118*5% -> 157.5 | K118: =G118+J118 -> 3307.5 | L118: REENA | P118: 1
B119: IDP EDUCATION L.L.C | C119: 24-0117 | D119: 45345 | E119: 100593105800003 | F119: Name Tags , Expo Cards | G119: 0 | I119: =G119-H119 -> 0 | J119: =G119*5% -> 0 | K119: =G119+J119 -> 0 | L119: REENA | P119: 1
B120: IDP EDUCATION L.L.C | C120: 24-0118 | D120: 45345 | E120: 100593105800003 | F120: IDP Excellence Awards - 21-Feb-24 | G120: 7142.1 | I120: =G120-H120 -> 7142.1 | J120: =G120*5% -> 357.105 | K120: =G120+J120 -> 7499.205 | L120: REENA | P120: 1
B121: IDP EDUCATION L.L.C | C121: 24-0119 | D121: 45345 | E121: 100593105800003 | F121: Roll up , A3 Posters , Certificates | G121: 1419 | I121: =G121-H121 -> 1419 | J121: =G121*5% -> 70.95 | K121: =G121+J121 -> 1489.95 | L121: REENA | P121: 1
B122: IDP EDUCATION L.L.C | C122: 24-0120 | D122: 45345 | E122: 100593105800003 | F122: IDP Business Cards - (Abu Dhabi) | G122: 960 | I122: =G122-H122 -> 960 | J122: =G122*5% -> 48 | K122: =G122+J122 -> 1008 | L122: REENA | P122: 1
B123: IDP EDUCATION L.L.C | C123: 24-0121 | D123: 45345 | E123: 100593105800003 | F123: IDP Business Cards - (Dubai ) | G123: 0 | I123: =G123-H123 -> 0 | J123: =G123*5% -> 0 | K123: =G123+J123 -> 0 | L123: REENA | P123: 1
B124: AL RASHED UNITED DMCC | C124: 24-0122 | D124: 45351 | E124: 100246622300003 | F124: Business card , Ribbons with printing , Paper Bag , Paper Stickers , Wrapping Paper | G124: 3490 | I124: =G124-H124 -> 3490 | J124: 174 | K124: =G124+J124 -> 3664 | L124: REENA | P124: 1
B125: Liquid Telecommunications International FZE | C125: 24-0123 | D125: 45348 | E125: 100247605700003 | F125: Gift Box - Black , Paper Bag | G125: 0 | I125: =G125-H125 -> 0 | J125: =G125*5% -> 0 | K125: =G125+J125 -> 0 | L125: REENA | P125: 1
B126: Bianca and Bianco Trading LLC | C126: 24-0124 | D126: 45351 | E126: 100482284500003 | F126: Business Card | G126: 310 | I126: =G126-H126 -> 310 | J126: =G126*5% -> 15.5 | K126: =G126+J126 -> 325.5 | L126: REENA | P126: 1
B127: Liquid Telecommunications International FZE | C127: 24-0125 | D127: 45349 | E127: 100247605700003 | F127: Gift Box - Black , Paper Bag | G127: 6775 | I127: =G127-H127 -> 6775 | J127: =G127*5% -> 338.75 | K127: =G127+J127 -> 7113.75 | L127: REENA | P127: 1
B128: Shory Technology L.L.C | C128: 24-0126 | D128: 45349 | E128: 100435244700003 | F128: Big Card, Small Card, Thank You Card | G128: 915 | I128: =G128-H128 -> 915 | J128: =G128*5% -> 45.75 | K128: =G128+J128 -> 960.75 | L128: MARINELLE | P128: 1
B129: Technological University of the Shannon - Ireland | C129: 24-0127 | D129: 45349 | E129: - | F129: Brochure 2024 , Courier Charges to Abu Dhabi | G129: 1925 | I129: =G129-H129 -> 1925 | J129: =G129*5% -> 96.25 | K129: =G129+J129 -> 2021.25 | L129: REENA | P129: 1
B130: Aram Precious Metals Trading FZE | C130: 24-0128 | D130: 45350 | E130: 104020641700003 | F130: Website Designing and Development ( 75% Advance Invoice ) | G130: 2362.38 | I130: =G130-H130 -> 2362.38 | J130: =G130*5% -> 118.119 | K130: =G130+J130 -> 2480.499 | L130: REENA | P130: 1
B131: Al Naser International FZE | C131: 24-0129 | D131: 45350 | E131: 100566746200003 | F131: Website Designing and Development ( 75% Advance Invoice ) | G131: 2362.38 | I131: =G131-H131 -> 2362.38 | J131: =G131*5% -> 118.119 | K131: =G131+J131 -> 2480.499 | L131: REENA | P131: 1
B132: Al Naser International FZE | C132: 24-0130 | D132: 45350 | E132: 100494671900003 | F132: Website Designing and Development ( 75% Advance Invoice ) | G132: 2362.38 | I132: =G132-H132 -> 2362.38 | J132: =G132*5% -> 118.119 | K132: =G132+J132 -> 2480.499 | L132: REENA | P132: 1
B133: ADIRONDACK ARCHITECTURAL MODELS INDUSTRY L.L.C | C133: 24-0131 | D133: 45350 | E133: 104061117800003 | F133: Sampling Charges - Polo Shirt | G133: 47.62 | I133: =G133-H133 -> 47.62 | J133: =G133*5% -> 2.381 | K133: =G133+J133 -> 50.001 | L133: REENA | P133: 1
B134: Aurantius Real Estate Broker | C134: 24-0132 | D134: 45351 | E134: 104166051300003 | F134: A4 Envelopes (customized) , DL Envelopes (customized) , Top spiral Notebook | G134: 1248 | I134: =G134-H134 -> 1248 | J134: =G134*5% -> 62.4 | K134: =G134+J134 -> 1310.4 | L134: REENA | P134: 1
B135: Unique World Business Centre LLC | C135: 24-0133 | D135: 45351 | E135: 100048520900003 | F135: Board Supply February, 2024 | G135: 90 | I135: =G135-H135 -> 90 | J135: =G135*5% -> 4.5 | K135: =G135+J135 -> 94.5 | L135: REENA | P135: 1
B136: Unique World Business Centre LLC | C136: 24-0134 | D136: 45351 | E136: 100048520900003 | F136: Board Supply February, 2024 | G136: 105 | I136: =G136-H136 -> 105 | J136: =G136*5% -> 5.25 | K136: =G136+J136 -> 110.25 | L136: REENA | P136: 1
B137: Navitas Middle East FZ - LLC | C137: 24-0135 | D137: 45352 | E137: 100282822400003 | F137: Table cloth - Bridal Satin , A4 Flyer (ICN) | G137: 485 | I137: =G137-H137 -> 485 | J137: =G137*5% -> 24.25 | K137: =G137+J137 -> 509.25 | L137: REENA | P137: 1
B138: Stellar Advertising LLC | C138: 24-0136 | D138: 45351 | E138: 100542487200003 | F138: Customized Vest - Taaleem | G138: 1890 | I138: =G138-H138 -> 1890 | J138: =G138*5% -> 94.5 | K138: =G138+J138 -> 1984.5 | L138: REENA | P138: 1
B139: M E A D Medical Supplies & Equipment L.L.C | C139: 24-0137 | D139: 45351 | E139: 100540543400003 | F139: Receipt Voucher | G139: 487.5 | I139: =G139-H139 -> 487.5 | J139: =G139*5% -> 24.375 | K139: =G139+J139 -> 511.875 | L139: MARINELLE | P139: 1
B140: Aurantius Real Estate Broker | C140: 24-0138 | D140: 45351 | E140: 104166051300003 | F140: Metal Pen , A4 Notepad | G140: 1162.5 | I140: =G140-H140 -> 1162.5 | J140: =G140*5% -> 58.125 | K140: =G140+J140 -> 1220.625 | L140: REENA | P140: 1
B141: Aram Precious Metals Trading FZE | C141: 24-0139 | D141: 45350 | E141: 104020641700003 | F141: Website Designing and Development ( 25% Final Invoice ) | G141: 787.62 | I141: =G141-H141 -> 787.62 | J141: =G141*5% -> 39.381 | K141: =G141+J141 -> 827.001 | L141: MARINELLE | P141: 1
... B143: Al Naser International FZE | C143: 24-0141 | D143: 45350 | E143: 100494671900003 | F143: Website Designing and Development ( 25% Final Invoice ) | G143: 787.62 | I143: =G143-H143 -> 787.62 | J143: =G143*5% -> 39.381 | K143: =G143+J143 -> 827.001 | L143: MARINELLE | P143: 1
B144: Stellar Advertising LLC | C144: 24-0142 | D144: 45352 | E144: 100542487200003 | F144: Business cards (Taaleem) | G144: 450 | I144: =G144-H144 -> 450 | J144: =G144*5% -> 22.5 | K144: =G144+J144 -> 472.5 | L144: REENA | P144: 1
B145: Navitas Middle East FZ - LLC | C145: 24-0143 | D145: 45355 | E145: 100430750800003 | F145: Business card | G145: 275 | I145: =G145-H145 -> 275 | J145: =G145*5% -> 13.75 | K145: =G145+J145 -> 288.75 | L145: REENA | P145: 1
B146: Navitas Middle East FZ - LLC | C146: 24-0144 | D146: 45355 | E146: 100282822400003 | F146: Rollup Banner , A3 Desktop Rollup , A4 Flyer (ICN) | G146: 505 | I146: =G146-H146 -> 505 | J146: =G146*5% -> 25.25 | K146: =G146+J146 -> 530.25 | L146: REENA | P146: 1
B147: Stellar Advertising LLC | C147: 24-0145 | D147: 45355 | E147: 100542487200003 | F147: Business Card - DBSJ | G147: 220 | I147: =G147-H147 -> 220 | J147: =G147*5% -> 11 | K147: =G147+J147 -> 231 | L147: REENA | P147: 1
B148: Trane BVBA (Dubai Branch) | C148: 24-0146 | D148: 45356 | E148: 100235699400003 | F148: Business Cards (Jomer Pinohermoso) | G148: 405 | I148: =G148-H148 -> 405 | J148: =G148*5% -> 20.25 | K148: =G148+J148 -> 425.25 | L148: REENA | P148: 1
B149: GrokGlobal Services | C149: 24-0147 | D149: 45353 | E149: - | F149: Student Gift Set of A5 Notebook and Pen With Bamboo Element , Jute Bag | G149: 18930 | I149: =G149-H149 -> 18930 | J149: =G149*5% -> 946.5 | K149: =G149+J149 -> 19876.5 | L149: REENA | P149: 1
B150: GrokGlobal Services | C150: 24-0148 | D150: 45355 | E150: - | F150: Brochure - Pre Departure | G150: 2585 | I150: =G150-H150 -> 2585 | J150: =G150*5% -> 129.25 | K150: =G150+J150 -> 2714.25 | L150: REENA | P150: 1
B151: ANB AUTOMOBILES L.L.C | C151: 24-0149 | D151: 45358 | E151: 100433257100003 | F151: Black Mug | G151: 1130 | I151: =G151-H151 -> 1130 | J151: =G151*5% -> 56.5 | K151: =G151+J151 -> 1186.5 | L151: MARINELLE | P151: 1
B152: Trane BVBA (Dubai Branch) | C152: 24-0150 | D152: 45356 | E152: 100235699400003 | F152: Business Cards (HAKIM LABRAHMI) | G152: 405 | I152: =G152-H152 -> 405 | J152: =G152*5% -> 20.25 | K152: =G152+J152 -> 425.25 | L152: REENA | P152: 1
B153: Stellar Advertising LLC | C153: 24-0151 | D153: 45357 | E153: 100542487200003 | F153: Leaflet - 3 fold (DBSJ) | G153: 840 | I153: =G153-H153 -> 840 | J153: =G153*5% -> 42 | K153: =G153+J153 -> 882 | L153: REENA | P153: 1
B154: Trane BVBA (Dubai Branch) | C154: 24-0152 | D154: 45360 | E154: 100348311000003 | F154: A5 Envelopes | G154: 540 | I154: =G154-H154 -> 540 | J154: =G154*5% -> 27 | K154: =G154+J154 -> 567 | L154: REENA | P154: 1
B155: GOOD VIBES TRANSPORT L.L.C | C155: 24-0153 | D155: 45360 | E155: 100483620900003 | F155: Job card | G155: 925 | I155: =G155-H155 -> 925 | J155: =G155*5% -> 46.25 | K155: =G155+J155 -> 971.25 | L155: REENA | P155: 1
... B161: Navitas Middle East FZ - LLC | C161: 24-0159 | D161: 45362 | E161: 100282822400003 | F161: Business Cards (Alejandro Celli) | G161: 135 | I161: =G161-H161 -> 135 | J161: =G161*5% -> 6.75 | K161: =G161+J161 -> 141.75 | L161: REENA | P161: 1
B162: Stellar Advertising LLC | C162: 24-0160 | D162: 45364 | F162: Taaleem Items | G162: 3703.5 | I162: =G162-H162 -> 3703.5 | J162: =G162*5% -> 185.175 | K162: =G162+J162 -> 3888.675 | L162: REENA | P162: 1
B163: Stellar Advertising LLC | C163: 24-0161 | D163: 45364 | F163: GIS Tshirts | G163: 3360 | I163: =G163-H163 -> 3360 | J163: =G163*5% -> 168 | K163: =G163+J163 -> 3528 | L163: REENA | P163: 1
B164: Stellar Advertising LLC | C164: 24-0162 | D164: 45364 | F164: DBSJP Journal 23 | G164: 475 | I164: =G164-H164 -> 475 | J164: =G164*5% -> 23.75 | K164: =G164+J164 -> 498.75 | L164: REENA | P164: 1
B165: Nanjing Stationery | C165: 24-0163 | D165: 45364 | F165: Note Books 50 | G165: 750 | I165: =G165-H165 -> 750 | J165: =G165*5% -> 37.5 | K165: =G165+J165 -> 787.5 | L165: MARINELLE | P165: 1
B166: Trane BVBA (Dubai Branch) | C166: 24-0164 | D166: 45365 | F166: BC Ifthikar | G166: 405 | I166: =G166-H166 -> 405 | J166: =G166*5% -> 20.25 | K166: =G166+J166 -> 425.25 | L166: REENA | P166: 1
B167: Stellar Advertising LLC | C167: 24-0165 | D167: 45366 | F167: AAG Gift Hampera | G167: 3600 | I167: =G167-H167 -> 3600 | J167: =G167*5% -> 180 | K167: =G167+J167 -> 3780 | L167: REENA | P167: 1
B168: Stellar Advertising LLC | C168: 24-0166 | D168: 45366 | F168: Taylor Wessing Journal | G168: 2242.5 | I168: =G168-H168 -> 2242.5 | J168: =G168*5% -> 112.125 | K168: =G168+J168 -> 2354.625 | L168: REENA | P168: 1
B169: Navitas Middle East FZ - LLC | C169: 24-0167 | D169: 45366 | F169: BC Yulia | G169: 275 | I169: =G169-H169 -> 275 | J169: =G169*5% -> 13.75 | K169: =G169+J169 -> 288.75 | L169: REENA | P169: 1
B170: Pacific Link | C170: 24-0168 | D170: 45369 | F170: Office Branding | G170: 5350 | I170: =G170-H170 -> 5350 | J170: =G170*5% -> 267.5 | K170: =G170+J170 -> 5617.5 | L170: REENA | P170: 1
B171: Stellar Advertising LLC | C171: 24-0169 | D171: 45370 | F171: DBSJ Flyer | G171: 290 | I171: =G171-H171 -> 290 | J171: =G171*5% -> 14.5 | K171: =G171+J171 -> 304.5 | L171: REENA | P171: 1
B172: The Woolwich Institute | C172: 24-0170 | D172: 45371 | F172: BC Anugha | G172: 195 | I172: =G172-H172 -> 195 | J172: =G172*5% -> 9.75 | K172: =G172+J172 -> 204.75 | L172: REENA | P172: 1
B173: BinGhatti | C173: 24-0171 | D173: 45377 | F173: Non Woven Bags | G173: 1725 | I173: =G173-H173 -> 1725 | J173: =G173*5% -> 86.25 | K173: =G173+J173 -> 1811.25 | L173: MARINELLE | P173: 1
... B177: Grandmatic | C177: 24-0175 | D177: 45374 | F177: NCR Book | G177: 285 | I177: =G177-H177 -> 285 | J177: =G177*5% -> 14.25 | K177: =G177+J177 -> 299.25 | L177: REENA | P177: 1
B178: Lloyds Energy DMCC | C178: 24-0176 | D178: 45376 | E178: 100056728700003 | F178: Office Signage | G178: 1250 | I178: =G178-H178 -> 1250 | J178: =G178*5% -> 62.5 | K178: =G178+J178 -> 1312.5 | L178: MARINELLE | P178: 1
B179: Pacific Link | C179: 24-0177 | D179: 45374 | E179: 100056728700003 | F179: Office Branding | G179: 1275 | I179: =G179-H179 -> 1275 | J179: =G179*5% -> 63.75 | K179: =G179+J179 -> 1338.75 | L179: REENA | P179: 1
...

Sheet Summary REA Adv
A3: Sum of INVOICE SUB-TOTAL | B3: Month | E3: Sum of INVOICE SUB-TOTAL | F3: Month | J3: Sum of INVOICE SUB-TOTAL | K3: Month
A4: Client Name | B4: Jun | C4: Grand Total | E4: Client Name | F4: Jul | G4: Grand Total | J4: Client Name | K4: Jan | L4: Feb | M4: Mar | N4: Apr | O4: May | P4: Jun | Q4: Jul | R4: Aug | S4: Grand Total
A5: Al Naser International FZE | B5: 485 | C5: 485 | E5: Al Naser International FZE | F5: 287.5 | G5: 287.5 | J5: GLEN | K5: 6081 | S5: 6081
A6: ANB AUTOMOBILES L.L.C | B6: 389.75 | C6: 389.75 | E6: AL RASHED UNITED DMCC | F6: 1395 | G6: 1395 | J6: MARINELLE | K6: 68501.24 | L6: 36948 | M6: 52520.87 | N6: 66984.5 | O6: 48692.26 | P6: 99968.08 | Q6: 51732.2 | R6: 1580 | S6: 426927.15
A7: Aurantius Real Estate Broker | B7: 2138 | C7: 2138 | E7: Aurantius Real Estate Broker | F7: 1000 | G7: 1000 | J7: PROFORMA | P7: 39130 | Q7: 13786.81 | S7: 52916.81
A8: Byyu Gift Trading LLC | B8: 5935 | C8: 5935 | E8: AUSTRAL INTERNATIONAL DMCC | F8: 287.5 | G8: 287.5 | J8: REENA | K8: 76931.497 | L8: 230704.47 | M8: 71536 | N8: 27060.45 | O8: 83866.69 | P8: 138844.77 | Q8: 39127.58 | S8: 668071.46
A9: Continental Middle East DMCC | B9: 3086 | C9: 3086 | E9: Bianca and Bianco Trading LLC | F9: 3210 | G9: 3210 | J9: BNI | P9: 999.29 | Q9: 1492 | S9: 2491.29
A10: Dubai Academic Health Corporation (DAHC) | B10: 24338.5 | C10: 24338.5 | E10: BorgRollsWarner Middle East LLC | F10: 1933.5 | G10: 1933.5 | J10: GAGANDEEP | P10: 0 | Q10: 3750 | S10: 3750
A11: DUNECREST AMERICAN SCHOOL L.L.C | B11: 358.75 | C11: 358.75 | E11: Byyu Gift Trading LLC | F11: 485 | G11: 485 | J11: Grand Total | K11: 151513.74 | L11: 267652.47 | M11: 124056.87 | N11: 94044.95 | O11: 132558.95 | P11: 278942.14 | Q11: 109888.59 | R11: 1580 | S11: 1160237.7
A12: Global Connect | B12: 820 | C12: 820 | E12: Continental Middle East DMCC | F12: 5528.75 | G12: 5528.75
A13: GrokGlobal Services | B13: 6445 | C13: 6445 | E13: DUNECREST AMERICAN SCHOOL L.L.C | F13: 14110 | G13: 14110
A14: Huxley Associates Global Limited | B14: 1233.75 | C14: 1233.75 | E14: GrokGlobal Services | F14: 275 | G14: 275
A15: IDP EDUCATION L.L.C | B15: 160 | C15: 160 | E15: IDP EDUCATION L.L.C | F15: 5885 | G15: 5885
A16: Ingersoll-Rand Technical and Services S A R L (Dubai Branch) | B16: 285 | C16: 285 | E16: Indo Tausch Trading DMCC | F16: 125 | G16: 125
A17: Lloyds Energy DMCC | B17: 870 | C17: 870 | E17: J C S ARTIFICIAL FLOWERS & PLANTS TRADING L.L.C | F17: 2435 | G17: 2435
A18: M E A D Medical Supplies & Equipment L.L.C | B18: 10070 | C18: 10070 | E18: Lloyds Energy DMCC | F18: 3110 | G18: 3110
A19: Navitas Middle East FZ - LLC | B19: 33682.5 | C19: 33682.5 | E19: Logic Utilities District Cooling Services LLC | F19: 700 | G19: 700
A20: Navitas SAE FZ-LLC | B20: 1325 | C20: 1325 | E20: Navitas Middle East FZ - LLC | F20: 977 | G20: 977
A21: SPH Global Holdings LLC | B21: 210 | C21: 210 | E21: Stellar Advertising LLC | F21: 15382.81 | G21: 15382.81
A22: Stellar Advertising LLC | B22: 76627.75 | C22: 76627.75 | E22: Trane BVBA (Abu Dhabi) | F22: 760 | G22: 760
A23: The Woolwich Institute | B23: 735 | C23: 735 | E23: Trane BVBA (Dubai Branch) | F23: 4369 | G23: 4369
... A41: Grand Total | B41: 278942.14 | C41: 278942.14 | E41: BLUE TANGERINE MARKETING MANAGEMENT | F41: 3750 | G41: 3750
E42: Locke Lifestyle Properties | F42: 1600 | G42: 1600
E43: IBM Global Middle East FZCO | F43: 333.33 | G43: 333.33
E44: Grand Total | F44: 109888.59 | G44: 109888.59

Sheet Sheet2
B3: Column Labels
B4: Jan | D4: Feb | F4: Mar | H4: Apr | J4: May | L4: Jun | N4: Total Sum of INVOICE SUB-TOTAL | O4: Total Sum of No of invoice
A5: Row Labels | B5: Sum of INVOICE SUB-TOTAL | C5: Sum of No of invoice | D5: Sum of INVOICE SUB-TOTAL | E5: Sum of No of invoice | F5: Sum of INVOICE SUB-TOTAL | G5: Sum of No of invoice | H5: Sum of INVOICE SUB-TOTAL | I5: Sum of No of invoice | J5: Sum of INVOICE SUB-TOTAL | K5: Sum of No of invoice | L5: Sum of INVOICE SUB-TOTAL | M5: Sum of No of invoice
A6: ADIRONDACK ARCHITECTURAL MODELS INDUSTRY L.L.C | D6: 47.62 | E6: 1 | N6: 47.62 | O6: 1
A7: Al Naser International FZE | D7: 3150 | E7: 2 | J7: 260 | K7: 1 | N7: 3410 | O7: 3
A8: AL RASHED UNITED DMCC | D8: 3490 | E8: 1 | N8: 3490 | O8: 1
A9: AL SHEMAIL GAR. & PERFUMES TR LLC | J9: 350 | K9: 1 | N9: 350 | O9: 1
A10: Al Tayer Insignia LLC | D10: 10965 | E10: 1 | N10: 10965 | O10: 1
A11: AL WASEEF INDUSTRIES LLC | H11: 380 | I11: 1 | N11: 380 | O11: 1
A12: Ali Salim Ali Salim Alqaydi | D12: 2715 | E12: 1 | N12: 2715 | O12: 1
A13: AMANI INVESTMENTS L.L.C - FZ | B13: 995 | C13: 1 | N13: 995 | O13: 1
A14: ANB AUTOMOBILES L.L.C | D14: 1580 | E14: 1 | F14: 1130 | G14: 1 | N14: 2710 | O14: 2
A15: Aplus Global FZE LLC | H15: 202.95 | I15: 1 | J15: 195 | K15: 1 | N15: 397.95 | O15: 2
A16: Aram Precious Metals Trading FZE | B16: 250 | C16: 1 | D16: 3150 | E16: 2 | J16: 85 | K16: 1 | N16: 3485 | O16: 4
A17: A-Technologies FZCO | B17: 6050 | C17: 2 | N17: 6050 | O17: 2
A18: Aurantius Real Estate Broker | B18: 553.75 | C18: 2 | D18: 2410.5 | E18: 2 | F18: 792.5 | G18: 1 | J18: 869 | K18: 1 | L18: 1788 | M18: 1 | N18: 6413.75 | O18: 7
A19: AUSTRAL INTERNATIONAL DMCC | B19: 745 | C19: 1 | D19: 3150 | E19: 2 | N19: 3895 | O19: 3
A20: Austral International FZE | B20: 250 | C20: 1 | N20: 250 | O20: 1
A21: Azalee Flower Boutique Limited | J21: 8385 | K21: 1 | N21: 8385 | O21: 1
A22: BECKMAN COULTER INTERNATIONAL S.A. (DUBAI BR) | J22: 2173.75 | K22: 1 | N22: 2173.75 | O22: 1
A23: Bianca and Bianco Trading LLC | B23: 825 | C23: 1 | D23: 310 | E23: 1 | H23: 825 | I23: 1 | N23: 1960 | O23: 3
A24: BinGhatti | F24: 1725 | G24: 1 | N24: 1725 | O24: 1
A25: Black Swan Business Setup Services LLC | H25: 285.5 | I25: 1 | N25: 285.5 | O25: 1
A26: Blu Orbit | B26: 1250 | C26: 1 | N26: 1250 | O26: 1
A27: BorgRollsWarner Middle East LLC | B27: 14375 | C27: 1 | N27: 14375 | O27: 1
A28: Byyu Gift Trading LLC | F28: 4225 | G28: 2 | J28: 350 | K28: 1 | N28: 4575 | O28: 3
A29: CACOGES | H29: 2850 | I29: 1 | N29: 2850 | O29: 1
A30: CJ ICM FZCO | B30: 3150 | C30: 1 | N30: 3150 | O30: 1
A31: CLARION SCHOOL LLC | B31: 0 | C31: 1 | N31: 0 | O31: 1
A32: Continental Middle East DMCC | D32: 3835 | E32: 2 | J32: 1266 | K32: 1 | N32: 5101 | O32: 3
A33: Crescent Real Estate | D33: 1920 | E33: 1 | N33: 1920 | O33: 1
A34: DHR MENA FZ-LLC | H34: 29332.5 | I34: 2 | N34: 29332.5 | O34: 2
A35: Dubai Academic Health Corporation (DAHC) | F35: 6920 | G35: 1 | J35: 12375 | K35: 1 | N35: 19295 | O35: 2
A36: DUNECREST AMERICAN SCHOOL L.L.C | B36: 19193.5 | C36: 2 | J36: 3831.3 | K36: 4 | L36: 358.75 | M36: 1 | N36: 23383.55 | O36: 7
A37: DYNAMIC EMPLOYMENT SERVICES L.L.C | D37: 892.5 | E37: 1 | N37: 892.5 | O37: 1
A38: E and S Luxury Car Rental LLC | B38: 300 | C38: 1 | N38: 300 | O38: 1
A39: E V OFFSHORE LIMITED (DUBAI BRANCH) | D39: 1400 | E39: 1 | J39: 944 | K39: 1 | N39: 2344 | O39: 2
A40: Ecotag | J40: 285.71 | K40: 1 | N40: 285.71 | O40: 1
A41: EMIRATES FOR UNIVERSAL TYRES L.L.C. | B41: 1315 | C41: 3 | J41: 450 | K41: 1 | N41: 1765 | O41: 4
A42: Enara Properties | B42: 95 | C42: 1 | N42: 95 | O42: 1
A43: FAD Institute of Luxury Fashion and Style Dubai | B43: 1690 | C43: 1 | N43: 1690 | O43: 1
A44: Finhub Middle East | J44: 2225 | K44: 1 | N44: 2225 | O44: 1
A45: Gamayun Consultancy Services FZE | J45: 175 | K45: 1 | N45: 175 | O45: 1
A46: Global Connect | B46: 120 | C46: 1 | D46: 190 | E46: 1 | J46: 1145 | K46: 1 | N46: 1455 | O46: 3
A47: Golden Tower Technologies | D47: 8850 | E47: 1 | N47: 8850 | O47: 1
A48: GOOD VIBES TRANSPORT L.L.C | F48: 925 | G48: 1 | N48: 925 | O48: 1
A49: GRAND STAR ALUMINUM & GLASS L.L.C | B49: 8360 | C49: 2 | N49: 8360 | O49: 2
A50: Grandmatic | F50: 285 | G50: 1 | N50: 285 | O50: 1
A51: Griffith College | D51: 1225 | E51: 1 | N51: 1225 | O51: 1
A52: GrokGlobal Services | B52: 4475 | C52: 2 | F52: 22177.5 | G52: 3 | H52: 310 | I52: 1 | J52: 975 | K52: 1 | L52: 2785 | M52: 1 | N52: 30722.5 | O52: 8
A53: Gulftainer | F53: 12626.25 | G53: 3 | J53: 1240 | K53: 1 | N53: 13866.25 | O53: 4
A54: Gulftainer Company Limited - Iraq Branch | F54: 7493.15 | G54: 2 | N54: 7493.15 | O54: 2
A55: HOLO MORTGAGE CONSULTANT | B55: 1060 | C55: 1 | N55: 1060 | O55: 1
A56: Huxley Associates Global Limited | B56: 1125 | C56: 1 | D56: 225 | E56: 1 | H56: 375 | I56: 1 | J56: 4355 | K56: 2 | L56: 1233.75 | M56: 1 | N56: 7313.75 | O56: 6
A57: IDP EDUCATION L.L.C | B57: 4813 | C57: 3 | D57: 165010.85 | E57: 8 | F57: 585 | G57: 1 | H57: 4197 | I57: 3 | J57: 16875.67 | K57: 9 | N57: 191481.52 | O57: 24
A58: IDP Education Services Nigeria Limited | B58: 227.907 | C58: 1 | N58: 227.907 | O58: 1
A59: Indo Tausch Trading DMCC | D59: 420 | E59: 1 | F59: 185 | G59: 1 | J59: 420 | K59: 2 | N59: 1025 | O59: 4
A60: Ingersoll-Rand Technical and Services S A R L (Dubai Branch) | B60: 310 | C60: 1 | J60: 1010 | K60: 2 | N60: 1320 | O60: 3
A61: J C S ARTIFICIAL FLOWERS & PLANTS TRADING L.L.C | D61: 779 | E61: 1 | J61: 770 | K61: 2 | N61: 1549 | O61: 3
A62: JUBAILI BROS S.A.L. | B62: 5975 | C62: 1 | J62: 1612.5 | K62: 1 | N62: 7587.5 | O62: 2
A63: KOTUG MIDDLE EAST DMCC | H63: 1167 | I63: 1 | J63: 250 | K63: 1 | N63: 1417 | O63: 2
A64: Krishna International FZCO | D64: 13000 | E64: 1 | N64: 13000 | O64: 1
A65: Lane Community College | D65: 140 | E65: 1 | N65: 140 | O65: 1
A66: LAYAN TRADING FZE | B66: 200 | C66: 1 | J66: 85 | K66: 1 | N66: 285 | O66: 2
A67: Liquid Telecommunications International FZE | D67: 6775 | E67: 2 | N67: 6775 | O67: 2
A68: Lloyds Energy DMCC | B68: 1250 | C68: 1 | F68: 9475 | G68: 3 | H68: 1100 | I68: 1 | N68: 11825 | O68: 5
A69: Logic Utilities District Cooling Services LLC | B69: 4252.5 | C69: 1 | N69: 4252.5 | O69: 1
A70: M E A D Medical Supplies & Equipment L.L.C | B70: 475 | C70: 1 | D70: 1347.5 | E70: 2 | J70: 1060 | K70: 1 | N70: 2882.5 | O70: 4
A71: M Y WORLD TRADING L.L.C | B71: 530 | C71: 1 | N71: 530 | O71: 1
A72: MAERSK LOGISTICS AND SERVICES L.L.C | H72: 1205 | I72: 1 | N72: 1205 | O72: 1
A73: MEINHARDT (SINGAPORE) PTE LTD (DUBAI BR) | H73: 1249.5 | I73: 1 | N73: 1249.5 | O73: 1
A74: Menlo Electric FZE | F74: 1440 | G74: 1 | N74: 1440 | O74: 1
A75: MIGHTHOUSE REALTY L.L.C | J75: 2195 | K75: 1 | N75: 2195 | O75: 1
A76: MIRA REAL ESTATE BROKERS L.L.C | D76: 3150 | E76: 2 | N76: 3150 | O76: 2
A77: Momentum Company Limited Saudi Arabia | F77: 2497.72 | G77: 1 | N77: 2497.72 | O77: 1
A78: Momentum Logistics | F78: 8463.75 | G78: 1 | N78: 8463.75 | O78: 1
A79: Mr. Waiz (Amity) | H79: 900 | I79: 1 | N79: 900 | O79: 1
A80: Ms. Eunice Lara Rosete | B80: 400 | C80: 1 | N80: 400 | O80: 1
A81: Ms. Karine Leonian | B81: 4687.5 | C81: 1 | N81: 4687.5 | O81: 1
A82: Nanjing Stationery | F82: 750 | G82: 1 | N82: 750 | O82: 1
A83: NARJIS Printing and Publishing | H83: 380 | I83: 1 | N83: 380 | O83: 1
A84: Navitas - Murdoch University | F84: 10720 | G84: 3 | N84: 10720 | O84: 3
A85: Navitas Middle East FZ - LLC | B85: 10803.35 | C85: 4 | F85: 550 | G85: 2 | H85: 4669 | I85: 4 | J85: 12497.5 | K85: 9 | N85: 28519.85 | O85: 19
A86: Navitas SAE FZ-LLC | F86: 1125 | G86: 3 | J86: 6202.5 | K86: 3 | N86: 7327.5 | O86: 6
A87: Onboard Sky Freight Services L.L.C | L87: 90 | M87: 1 | N87: 90 | O87: 1
A88: One Blue Clover FZCO | D88: 525 | E88: 1 | F88: 550 | G88: 1 | N88: 1075 | O88: 2
A89: Orthopro Clinic | B89: 525 | C89: 1 | N89: 525 | O89: 1
A90: Pacific Link | F90: 6625 | G90: 2 | N90: 6625 | O90: 2
A91: PHARMAPAL DRUG STORE L.L.C | B91: 5781 | C91: 2 | N91: 5781 | O91: 2
A92: PLUS971 CYBER SECURITY L.L.C | H92: 24600 | I92: 3 | N92: 24600 | O92: 3
A93: PMMUE Eduservices Private Limited | J93: 1183 | K93: 1 | N93: 1183 | O93: 1
A94: POWER LEASE VEHICLE RENTAL DMCC | F94: 435 | G94: 1 | N94: 435 | O94: 1
A95: Radiometer Medical ApS | B95: 14677.74 | C95: 2 | H95: 325 | I95: 1 | N95: 15002.74 | O95: 3
A96: RIF TRUST INVESTMENTS LLC | B96: 380 | C96: 1 | N96: 380 | O96: 1
A97: Right Fit Tailoring | J97: 2250 | K97: 1 | N97: 2250 | O97: 1
A98: Sea Centre Shipping Services LLC | B98: 3950 | C98: 1 | H98: 1050 | I98: 1 | J98: 190 | K98: 1 | N98: 5190 | O98: 3
A99: Shory Technology L.L.C | B99: 150 | C99: 1 | D99: 915 | E99: 1 | N99: 1065 | O99: 2
A100: SPECIALISED SPORTS EQUIPMENT LLC | D100: 625 | E100: 2 | N100: 625 | O100: 2
A101: SPH Global Holdings LLC | B101: 1250 | C101: 1 | N101: 1250 | O101: 1
A102: Stellar Advertising LLC | B102: 9650.49 | C102: 10 | D102: 16015.5 | E102: 10 | F102: 18431 | G102: 14 | H102: 9871 | I102: 10 | J102: 19695.77 | K102: 21 | L102: 24612 | M102: 4 | N102: 98275.76 | O102: 69
...

Sheet REA Adv - Invoices
B2: CLIENT | C2: INVOICE NO. | D2: INVOICE DATE | E2: CLIENT TRN | F2: DESCRIPTION | G2: INVOICE SUB-TOTAL | H2: REBATE | I2: INVOICE SUB-TOTAL AFTER REBATE | J2: VAT % AMOUNT | K2: TOTAL INVOICE AMOUNT | L2: Sales Person | M2: =COUNTA(C:C)-1 -> 842 | N2: =GETPIVOTDATA("Count of INVOICE NO.",#REF!)+GETPIVOTDATA("Count of INVOICE NO.",#REF!) -> #REF! | O2: =SUM(G:G) -> 2220393.1
B3: Stellar Advertising LLC | C3: 24-0001 | D3: 45293 | E3: 100542487200003 | F3: A3 Poster - Jebel Ali School | G3: 425.49 | I3: =G3-H3 -> 425.49 | J3: =G3*5% -> 21.2745 | K3: =G3+J3 -> 446.7645 | L3: REENA
B4: Stellar Advertising LLC | C4: 24-0002 | D4: 45295 | E4: 100542487200003 | F4: A5 Booklet - DBSJP (Nov/Dec) | G4: 415 | I4: =G4-H4 -> 415 | J4: =G4*5% -> 20.75 | K4: =G4+J4 -> 435.75 | L4: REENA
B5: Aurantius Real Estate Broker | C5: 24-0003 | D5: 45295 | E5: 104166051300003 | F5: Business Cards ( Ferhat Doghan ) | G5: 475 | I5: =G5-H5 -> 475 | J5: =G5*5% -> 23.75 | K5: =G5+J5 -> 498.75 | L5: REENA
B6: A-Technologies FZCO | C6: 24-0004 | D6: 45306 | E6: 100312976200003 | F6: Water Bottle , A5 Notebook (Anti-Microbial) , Metal Pen , Box | G6: 5850 | I6: =G6-H6 -> 5850 | J6: =G6*5% -> 292.5 | K6: =G6+J6 -> 6142.5 | L6: MARINELLE
B7: EMIRATES FOR UNIVERSAL TYRES L.L.C. | C7: 24-0005 | D7: 45297 | E7: 100032677500003 | F7: Sticker (Paper) | G7: 425 | I7: =G7-H7 -> 425 | J7: =G7*5% -> 21.25 | K7: =G7+J7 -> 446.25 | L7: REENA
B8: GRAND STAR ALUMINUM & GLASS L.L.C | C8: 24-0006 | D8: 45296 | E8: 100522321700003 | F8: Wooden Board | G8: 7600 | I8: =G8-H8 -> 7600 | J8: =G8*5% -> 380 | K8: =G8+J8 -> 7980 | L8: REENA
B9: VISIONARY FURNITURE TRADING L.L.C | C9: 24-0007 | D9: 45302 | E9: 104037069200003 | F9: Business Cards , Polo Shirts | G9: 848 | I9: =G9-H9 -> 848 | J9: =G9*5% -> 42.4 | K9: =G9+J9 -> 890.4 | L9: REENA
B10: Navitas Middle East FZ - LLC | C10: 24-0008 | D10: 45300 | E10: 100430750800003 | F10: Round neck Tshirt | G10: 380 | I10: =G10-H10 -> 380 | J10: =G10*5% -> 19 | K10: =G10+J10 -> 399 | L10: REENA
B11: Trane BVBA (Abu Dhabi) | C11: 24-0009 | D11: 45316 | E11: 100348311000003 | F11: Business Card ( Mohamed Ben Hamouda ) | G11: 405 | I11: =G11-H11 -> 405 | J11: =G11*5% -> 20.25 | K11: =G11+J11 -> 425.25 | L11: REENA
B12: M Y WORLD TRADING L.L.C | C12: 24-0010 | D12: 45300 | E12: 104014963300003 | F12: Business Cards ( Mr. Mehdi M Taki , Mr. Muhammed Midlaj ) | G12: 530 | I12: =G12-H12 -> 530 | J12: =G12*5% -> 26.5 | K12: =G12+J12 -> 556.5 | L12: REENA
B13: GRAND STAR ALUMINUM & GLASS L.L.C | C13: 24-0011 | D13: 45302 | E13: 100522321700003 | F13: Acrylic Stand | G13: 760 | I13: =G13-H13 -> 760 | J13: =G13*5% -> 38 | K13: =G13+J13 -> 798 | L13: REENA
B14: IDP Education Services Nigeria Limited | C14: 24-0012 | D14: 45300 | E14: - | F14: Polo Shirt | G14: =3.67*62.1 -> 227.907 | I14: =G14-H14 -> 227.907 | J14: =G14*5% -> 11.39535 | K14: =G14+J14 -> 239.30235 | L14: REENA
B15: M E A D Medical Supplies & Equipment L.L.C | C15: 24-0013 | D15: 45303 | E15: 100540543400003 | F15: NCR Book | G15: 475 | I15: =G15-H15 -> 475 | J15: =G15*5% -> 23.75 | K15: =G15+J15 -> 498.75 | L15: MARINELLE
B16: Stellar Advertising LLC | C16: 24-0014 | D16: 45303 | E16: 100542487200003 | F16: Poster , Flag ( Raha International School ) | G16: 440 | I16: =G16-H16 -> 440 | J16: =G16*5% -> 22 | K16: =G16+J16 -> 462 | L16: REENA
B17: Lloyds Energy DMCC | C17: 24-0015 | D17: 45303 | E17: 100056728700003 | F17: Signage (Without Light) | G17: 1250 | I17: =G17-H17 -> 1250 | J17: =G17*5% -> 62.5 | K17: =G17+J17 -> 1312.5 | L17: MARINELLE
B18: EMIRATES FOR UNIVERSAL TYRES L.L.C. | C18: 24-0016 | D18: 45303 | E18: 100032677500003 | F18: Business card ( Rineesh Ali ) | G18: 165 | I18: =G18-H18 -> 165 | J18: =G18*5% -> 8.25 | K18: =G18+J18 -> 173.25 | L18: REENA
B19: Bianca and Bianco Trading LLC | C19: 24-0017 | D19: 45304 | E19: 100482284500003 | F19: Business Card | G19: 825 | I19: =G19-H19 -> 825 | J19: =G19*5% -> 41.25 | K19: =G19+J19 -> 866.25 | L19: REENA
B20: Logic Utilities District Cooling Services LLC | C20: 24-0018 | D20: 45316 | E20: 100567483100003 | F20: Polo Shirts | G20: 4252.5 | I20: =G20-H20 -> 4252.5 | J20: =G20*5% -> 212.625 | K20: =G20+J20 -> 4465.125 | L20: MARINELLE
B21: FAD Institute of Luxury Fashion and Style Dubai | C21: 24-0019 | D21: 45307 | E21: - | F21: Certificate Holder | G21: 1690 | I21: =G21-H21 -> 1690 | J21: =G21*5% -> 84.5 | K21: =G21+J21 -> 1774.5 | L21: MARINELLE
B22: Ingersoll-Rand Technical and Services S A R L (Dubai Branch) | C22: 24-0020 | D22: 45306 | E22: 100399495900003 | F22: Business Card | G22: 310 | I22: =G22-H22 -> 310 | J22: =G22*5% -> 15.5 | K22: =G22+J22 -> 325.5 | L22: MARINELLE
B23: JUBAILI BROS S.A.L. | C23: 24-0021 | D23: 45307 | E23: 100293287700003 | F23: Car Sunshades (Tyvek) | G23: 5975 | I23: =G23-H23 -> 5975 | J23: =G23*5% -> 298.75 | K23: =G23+J23 -> 6273.75 | L23: MARINELLE
B24: Global Connect | C24: 24-0022 | D24: 45303 | E24: - | F24: Rubber stamp | G24: 120 | I24: =G24-H24 -> 120 | J24: =G24*5% -> 6 | K24: =G24+J24 -> 126 | L24: REENA
B25: IDP EDUCATION L.L.C | C25: 24-0023 | D25: 45303 | E25: 100593105800003 | F25: Rubber Stamp | G25: 0 | I25: =G25-H25 -> 0 | J25: =G25*5% -> 0 | K25: =G25+J25 -> 0 | L25: REENA
B26: A-Technologies FZCO | C26: 24-0024 | D26: 45307 | E26: 100312976200003 | F26: Prints for Gift Box | G26: 200 | I26: =G26-H26 -> 200 | J26: =G26*5% -> 10 | K26: =G26+J26 -> 210 | L26: MARINELLE
... B95: Trane BVBA (Dubai Branch) | C95: 24-0093 | D95: 45335 | E95: 100235699400003 | F95: Crystal Trophy | G95: 1800 | I95: =G95-H95 -> 1800 | J95: =G95*5% -> 90 | K95: =G95+J95 -> 1890 | L95: REENA
B96: Krishna International FZCO | C96: 24-0094 | D96: 45332 | E96: 100060213400003 | F96: Wedding Luggage Tags | G96: 13000 | I96: =G96-H96 -> 13000 | J96: =G96*5% -> 650 | K96: =G96+J96 -> 13650 | L96: REENA
B97: One Blue Clover FZCO | C97: 24-0095 | D97: 45338 | E97: - | F97: Letterhead | G97: 525 | I97: =G97-H97 -> 525 | J97: =G97*5% -> 26.25 | K97: =G97+J97 -> 551.25 | L97: BNI
B98: Stellar Advertising LLC | C98: 24-0096 | D98: 45337 | E98: 100542487200003 | F98: Selfie Frame - DBSJP , Prop - #Outstanding | G98: 595 | I98: =G98-H98 -> 595 | J98: =G98*5% -> 29.75 | K98: =G98+J98 -> 624.75 | L98: REENA
B99: Stellar Advertising LLC | C99: 24-0097 | D99: 45338 | E99: 100542487200003 | F99: Roll Up - AAG | G99: 145 | I99: =G99-H99 -> 145 | J99: =G99*5% -> 7.25 | K99: =G99+J99 -> 152.25 | L99: REENA
B100: M E A D Medical Supplies & Equipment L.L.C | C100: 24-0098 | D100: 45341 | E100: 100540543400003 | F100: NCR Book , Business Cards | G100: 860 | I100: =G100-H100 -> 860 | J100: =G100*5% -> 43 | K100: =G100+J100 -> 903 | L100: MARINELLE
B101: Stellar Advertising LLC | C101: 24-0099 | D101: 45342 | E101: 100542487200003 | F101: Letterhead - FICHTE | G101: 625 | I101: =G101-H101 -> 625 | J101: =G101*5% -> 31.25 | K101: =G101+J101 -> 656.25 | L101: REENA
B102: Golden Tower Technologies | C102: 24-0100 | D102: 45338 | E102: 100470289800003 | F102: Flex to be changed for existing light box | G102: 8850 | I102: =G102-H102 -> 8850 | J102: =G102*5% -> 442.5 | K102: =G102+J102 -> 9292.5 | L102: REENA
B103: Thermo Fisher Scientific S.P.A. | C103: 24-0101 | D103: 45338 | E103: IT 07817950152 | F103: Flyer , Recycled 6-in-1 Charging Cable | G103: 3335 | I103: =G103-H103 -> 3335 | J103: =G103*5% -> 166.75 | K103: =G103+J103 -> 3501.75 | L103: MARINELLE
B104: Griffith College | C104: 24-0102 | D104: 45338 | E104: - | F104: Brochure | G104: 1225 | I104: =G104-H104 -> 1225 | J104: =G104*5% -> 61.25 | K104: =G104+J104 -> 1286.25 | L104: REENA
B105: IDP EDUCATION L.L.C | C105: 24-0103 | D105: 45341 | E105: 100593105800003 | F105: Dubai Roadshow Millenium Downtown, 17th Feb 2024 | G105: 103245.5 | I105: =G105-H105 -> 103245.5 | J105: =G105*5% -> 5162.275 | K105: =G105+J105 -> 108407.77 | L105: REENA
B106: IDP EDUCATION L.L.C | C106: 24-0104 | D106: 45341 | E106: 100593105800003 | F106: Abu Dhabi Roadshow 18 Feb 2024, InterContinental | G106: 51717.75 | I106: =G106-H106 -> 51717.75 | J106: =G106*5% -> 2585.8875 | K106: =G106+J106 -> 54303.637 | L106: REENA
B107: DYNAMIC EMPLOYMENT SERVICES L.L.C | C107: 24-0105 | D107: 45343 | E107: 100323347300003 | F107: Parking Signage | G107: 892.5 | I107: =G107-H107 -> 892.5 | J107: =G107*5% -> 44.625 | K107: =G107+J107 -> 937.125 | L107: MARINELLE
B108: Stellar Advertising LLC | C108: 24-0106 | D108: 45343 | E108: 100542487200003 | F108: Flyer - Taylor Wessing | G108: 190 | I108: =G108-H108 -> 190 | J108: =G108*5% -> 9.5 | K108: =G108+J108 -> 199.5 | L108: REENA
B109: Stellar Advertising LLC | C109: 24-0107 | D109: 45342 | E109: 100542487200003 | F109: Journal - DBSEH | G109: 585 | I109: =G109-H109 -> 585 | J109: =G109*5% -> 29.25 | K109: =G109+J109 -> 614.25 | L109: REENA
B110: Crescent Real Estate | C110: 24-0108 | D110: 45343 | E110: 100359923800003 | F110: Polo Shirts | G110: 1920 | I110: =G110-H110 -> 1920 | J110: =G110*5% -> 96 | K110: =G110+J110 -> 2016 | L110: MARINELLE
B111: Indo Tausch Trading DMCC | C111: 24-0109 | D111: 45344 | E111: 100484375900003 | F111: Business Cards , ID Cards | G111: 420 | I111: =G111-H111 -> 420 | J111: =G111*5% -> 21 | K111: =G111+J111 -> 441 | L111: REENA
B112: Stellar Advertising LLC | C112: 24-0110 | D112: 45344 | E112: 100542487200003 | F112: Top Curve Flags - Al Salaam Charter School | G112: 6250 | I112: =G112-H112 -> 6250 | J112: =G112*5% -> 312.5 | K112: =G112+J112 -> 6562.5 | L112: REENA
B113: Stellar Advertising LLC | C113: 24-0111 | D113: 45345 | E113: 100542487200003 | F113: Rollup Banners (GIS) , Designing charges | G113: 390 | I113: =G113-H113 -> 390 | J113: =G113*5% -> 19.5 | K113: =G113+J113 -> 409.5 | L113: REENA
B114: Stellar Advertising LLC | C114: 24-0112 | D114: 45345 | E114: 100542487200003 | F114: Round Neck Tshirts (Wellbeing) - Charter School | G114: 4220.5 | I114: =G114-H114 -> 4220.5 | J114: =G114*5% -> 211.025 | K114: =G114+J114 -> 4431.525 | L114: REENA
B115: Trane BVBA (Dubai Branch) | C115: 24-0113 | D115: 45345 | E115: 100235699400003 | F115: Business Cards ( Dipak M Shelke ) | G115: 405 | I115: =G115-H115 -> 405 | J115: =G115*5% -> 20.25 | K115: =G115+J115 -> 425.25 | L115: REENA
B116: Huxley Associates Global Limited | C116: 24-0114 | D116: 45348 | E116: 100349055200003 | F116: Vertical Matt Veneer Wooden Plaque | G116: 225 | I116: =G116-H116 -> 225 | J116: =G116*5% -> 11.25 | K116: =G116+J116 -> 236.25 | L116: MARINELLE
... B118: Continental Middle East DMCC | C118: 24-0116 | D118: 45350 | E118: 100377505100003 | F118: Trophy | G118: 3150 | I118: =G118-H118 -> 3150 | J118: =G118*5% -> 157.5 | K118: =G118+J118 -> 3307.5 | L118: REENA
B119: IDP EDUCATION L.L.C | C119: 24-0117 | D119: 45345 | E119: 100593105800003 | F119: Name Tags , Expo Cards | G119: 0 | I119: =G119-H119 -> 0 | J119: =G119*5% -> 0 | K119: =G119+J119 -> 0 | L119: REENA
B120: IDP EDUCATION L.L.C | C120: 24-0118 | D120: 45345 | E120: 100593105800003 | F120: IDP Excellence Awards - 21-Feb-24 | G120: 7142.1 | I120: =G120-H120 -> 7142.1 | J120: =G120*5% -> 357.105 | K120: =G120+J120 -> 7499.205 | L120: REENA
B121: IDP EDUCATION L.L.C | C121: 24-0119 | D121: 45345 | E121: 100593105800003 | F121: Roll up , A3 Posters , Certificates | G121: 1419 | I121: =G121-H121 -> 1419 | J121: =G121*5% -> 70.95 | K121: =G121+J121 -> 1489.95 | L121: REENA
B122: IDP EDUCATION L.L.C | C122: 24-0120 | D122: 45345 | E122: 100593105800003 | F122: IDP Business Cards - (Abu Dhabi) | G122: 960 | I122: =G122-H122 -> 960 | J122: =G122*5% -> 48 | K122: =G122+J122 -> 1008 | L122: REENA
B123: IDP EDUCATION L.L.C | C123: 24-0121 | D123: 45345 | E123: 100593105800003 | F123: IDP Business Cards - (Dubai ) | G123: 0 | I123: =G123-H123 -> 0 | J123: =G123*5% -> 0 | K123: =G123+J123 -> 0 | L123: REENA
B124: AL RASHED UNITED DMCC | C124: 24-0122 | D124: 45351 | E124: 100246622300003 | F124: Business card , Ribbons with printing , Paper Bag , Paper Stickers , Wrapping Paper | G124: 3490 | I124: =G124-H124 -> 3490 | J124: 174 | K124: =G124+J124 -> 3664 | L124: REENA
B125: Liquid Telecommunications International FZE | C125: 24-0123 | D125: 45348 | E125: 100247605700003 | F125: Gift Box - Black , Paper Bag | G125: 0 | I125: =G125-H125 -> 0 | J125: =G125*5% -> 0 | K125: =G125+J125 -> 0 | L125: REENA
B126: Bianca and Bianco Trading LLC | C126: 24-0124 | D126: 45351 | E126: 100482284500003 | F126: Business Card | G126: 310 | I126: =G126-H126 -> 310 | J126: =G126*5% -> 15.5 | K126: =G126+J126 -> 325.5 | L126: REENA
B127: Liquid Telecommunications International FZE | C127: 24-0125 | D127: 45349 | E127: 100247605700003 | F127: Gift Box - Black , Paper Bag | G127: 6775 | I127: =G127-H127 -> 6775 | J127: =G127*5% -> 338.75 | K127: =G127+J127 -> 7113.75 | L127: REENA
B128: Shory Technology L.L.C | C128: 24-0126 | D128: 45349 | E128: 100435244700003 | F128: Big Card, Small Card, Thank You Card | G128: 915 | I128: =G128-H128 -> 915 | J128: =G128*5% -> 45.75 | K128: =G128+J128 -> 960.75 | L128: MARINELLE
B129: Technological University of the Shannon - Ireland | C129: 24-0127 | D129: 45349 | E129: - | F129: Brochure 2024 , Courier Charges to Abu Dhabi | G129: 1925 | I129: =G129-H129 -> 1925 | J129: =G129*5% -> 96.25 | K129: =G129+J129 -> 2021.25 | L129: REENA
B130: Aram Precious Metals Trading FZE | C130: 24-0128 | D130: 45350 | E130: 104020641700003 | F130: Website Designing and Development ( 75% Advance Invoice ) | G130: 2362.38 | I130: =G130-H130 -> 2362.38 | J130: =G130*5% -> 118.119 | K130: =G130+J130 -> 2480.499 | L130: MARINELLE
B131: Al Naser International FZE | C131: 24-0129 | D131: 45350 | E131: 100566746200003 | F131: Website Designing and Development ( 75% Advance Invoice ) | G131: 2362.38 | I131: =G131-H131 -> 2362.38 | J131: =G131*5% -> 118.119 | K131: =G131+J131 -> 2480.499 | L131: MARINELLE
B132: AUSTRAL INTERNATIONAL DMCC | C132: 24-0130 | D132: 45350 | E132: 100494671900003 | F132: Website Designing and Development ( 75% Advance Invoice ) | G132: 2362.38 | I132: =G132-H132 -> 2362.38 | J132: =G132*5% -> 118.119 | K132: =G132+J132 -> 2480.499 | L132: MARINELLE
B133: ADIRONDACK ARCHITECTURAL MODELS INDUSTRY L.L.C | C133: 24-0131 | D133: 45350 | E133: 104061117800003 | F133: Sampling Charges - Polo Shirt | G133: 47.62 | I133: =G133-H133 -> 47.62 | J133: =G133*5% -> 2.381 | K133: =G133+J133 -> 50.001 | L133: REENA
B134: Aurantius Real Estate Broker | C134: 24-0132 | D134: 45351 | E134: 104166051300003 | F134: A4 Envelopes (customized) , DL Envelopes (customized) , Top spiral Notebook | G134: 1248 | I134: =G134-H134 -> 1248 | J134: =G134*5% -> 62.4 | K134: =G134+J134 -> 1310.4 | L134: REENA
B135: Unique World Business Centre LLC | C135: 24-0133 | D135: 45351 | E135: 100048520900003 | F135: Board Supply February, 2024 | G135: 90 | I135: =G135-H135 -> 90 | J135: =G135*5% -> 4.5 | K135: =G135+J135 -> 94.5 | L135: REENA
B136: Unique World Business Centre LLC | C136: 24-0134 | D136: 45351 | E136: 100048520900003 | F136: Board Supply February, 2024 | G136: 105 | I136: =G136-H136 -> 105 | J136: =G136*5% -> 5.25 | K136: =G136+J136 -> 110.25 | L136: REENA
B137: Navitas SAE FZ-LLC | C137: 24-0135 | D137: 45352 | E137: 100282822400003 | F137: Table cloth - Bridal Satin , A4 Flyer (ICN) | G137: 485 | I137: =G137-H137 -> 485 | J137: =G137*5% -> 24.25 | K137: =G137+J137 -> 509.25 | L137: REENA
B138: Stellar Advertising LLC | C138: 24-0136 | D138: 45351 | E138: 100542487200003 | F138: Customized Vest - Taaleem | G138: 1890 | I138: =G138-H138 -> 1890 | J138: =G138*5% -> 94.5 | K138: =G138+J138 -> 1984.5 | L138: REENA
B139: M E A D Medical Supplies & Equipment L.L.C | C139: 24-0137 | D139: 45351 | E139: 100540543400003 | F139: Receipt Voucher | G139: 487.5 | I139: =G139-H139 -> 487.5 | J139: =G139*5% -> 24.375 | K139: =G139+J139 -> 511.875 | L139: MARINELLE
B140: Aurantius Real Estate Broker | C140: 24-0138 | D140: 45351 | E140: 104166051300003 | F140: Metal Pen , A4 Notepad | G140: 1162.5 | I140: =G140-H140 -> 1162.5 | J140: =G140*5% -> 58.125 | K140: =G140+J140 -> 1220.625 | L140: REENA
B141: Aram Precious Metals Trading FZE | C141: 24-0139 | D141: 45350 | E141: 104020641700003 | F141: Website Designing and Development ( 25% Final Invoice ) | G141: 787.62 | I141: =G141-H141 -> 787.62 | J141: =G141*5% -> 39.381 | K141: =G141+J141 -> 827.001 | L141: MARINELLE | P141: IN
B142: Al Naser International FZE | C142: 24-0140 | D142: 45350 | E142: 100566746200003 | F142: Website Designing and Development ( 25% Final Invoice ) | G142: 787.62 | I142: =G142-H142 -> 787.62 | J142: =G142*5% -> 39.381 | K142: =G142+J142 -> 827.001 | L142: MARINELLE | P142: IN
B143: AUSTRAL INTERNATIONAL DMCC | C143: 24-0141 | D143: 45350 | E143: 100494671900003 | F143: Website Designing and Development ( 25% Final Invoice ) | G143: 787.62 | I143: =G143-H143 -> 787.62 | J143: =G143*5% -> 39.381 | K143: =G143+J143 -> 827.001 | L143: MARINELLE | P143: IN
B144: Stellar Advertising LLC | C144: 24-0142 | D144: 45352 | E144: 100542487200003 | F144: Business cards (Taaleem) | G144: 450 | I144: =G144-H144 -> 450 | J144: =G144*5% -> 22.5 | K144: =G144+J144 -> 472.5 | L144: REENA
B145: Navitas Middle East FZ - LLC | C145: 24-0143 | D145: 45355 | E145: 100430750800003 | F145: Business card | G145: 275 | I145: =G145-H145 -> 275 | J145: =G145*5% -> 13.75 | K145: =G145+J145 -> 288.75 | L145: REENA
B146: Navitas SAE FZ-LLC | C146: 24-0144 | D146: 45355 | E146: 100282822400003 | F146: Rollup Banner , A3 Desktop Rollup , A4 Flyer (ICN) | G146: 505 | I146: =G146-H146 -> 505 | J146: =G146*5% -> 25.25 | K146: =G146+J146 -> 530.25 | L146: REENA
B147: Stellar Advertising LLC | C147: 24-0145 | D147: 45355 | E147: 100542487200003 | F147: Business Card - DBSJ | G147: 220 | I147: =G147-H147 -> 220 | J147: =G147*5% -> 11 | K147: =G147+J147 -> 231 | L147: REENA
B148: Trane BVBA (Dubai Branch) | C148: 24-0146 | D148: 45356 | E148: 100235699400003 | F148: Business Cards (Jomer Pinohermoso) | G148: 405 | I148: =G148-H148 -> 405 | J148: =G148*5% -> 20.25 | K148: =G148+J148 -> 425.25 | L148: REENA
B149: GrokGlobal Services | C149: 24-0147 | D149: 45353 | E149: - | F149: Student Gift Set of A5 Notebook and Pen With Bamboo Element , Jute Bag | G149: 18930 | I149: =G149-H149 -> 18930 | J149: =G149*5% -> 946.5 | K149: =G149+J149 -> 19876.5 | L149: REENA
B150: GrokGlobal Services | C150: 24-0148 | D150: 45355 | E150: - | F150: Brochure - Pre Departure | G150: 2585 | I150: =G150-H150 -> 2585 | J150: =G150*5% -> 129.25 | K150: =G150+J150 -> 2714.25 | L150: REENA
B151: ANB AUTOMOBILES L.L.C | C151: 24-0149 | D151: 45358 | E151: 100433257100003 | F151: Black Mug | G151: 1130 | I151: =G151-H151 -> 1130 | J151: =G151*5% -> 56.5 | K151: =G151+J151 -> 1186.5 | L151: MARINELLE
B152: Trane BVBA (Dubai Branch) | C152: 24-0150 | D152: 45356 | E152: 100235699400003 | F152: Business Cards (HAKIM LABRAHMI) | G152: 405 | I152: =G152-H152 -> 405 | J152: =G152*5% -> 20.25 | K152: =G152+J152 -> 425.25 | L152: REENA
B153: Stellar Advertising LLC | C153: 24-0151 | D153: 45357 | E153: 100542487200003 | F153: Leaflet - 3 fold (DBSJ) | G153: 840 | I153: =G153-H153 -> 840 | J153: =G153*5% -> 42 | K153: =G153+J153 -> 882 | L153: REENA
B154: Trane BVBA (Abu Dhabi) | C154: 24-0152 | D154: 45360 | E154: 100348311000003 | F154: A5 Envelopes | G154: 540 | I154: =G154-H154 -> 540 | J154: =G154*5% -> 27 | K154: =G154+J154 -> 567 | L154: REENA
B155: GOOD VIBES TRANSPORT L.L.C | C155: 24-0153 | D155: 45360 | E155: 100483620900003 | F155: Job card | G155: 925 | I155: =G155-H155 -> 925 | J155: =G155*5% -> 46.25 | K155: =G155+J155 -> 971.25 | L155: REENA
... B161: Navitas SAE FZ-LLC | C161: 24-0159 | D161: 45362 | E161: 100282822400003 | F161: Business Cards (Alejandro Celli) | G161: 135 | I161: =G161-H161 -> 135 | J161: =G161*5% -> 6.75 | K161: =G161+J161 -> 141.75 | L161: REENA
B162: Stellar Advertising LLC | C162: 24-0160 | D162: 45364 | F162: Taaleem Items | G162: 3703.5 | I162: =G162-H162 -> 3703.5 | J162: =G162*5% -> 185.175 | K162: =G162+J162 -> 3888.675 | L162: REENA
B163: Stellar Advertising LLC | C163: 24-0161 | D163: 45364 | F163: GIS Tshirts | G163: 3360 | I163: =G163-H163 -> 3360 | J163: =G163*5% -> 168 | K163: =G163+J163 -> 3528 | L163: REENA
B164: Stellar Advertising LLC | C164: 24-0162 | D164: 45364 | F164: DBSJP Journal 23 | G164: 475 | I164: =G164-H164 -> 475 | J164: =G164*5% -> 23.75 | K164: =G164+J164 -> 498.75 | L164: REENA
B165: Nanjing Stationery | C165: 24-0163 | D165: 45364 | F165: Note Books 50 | G165: 750 | I165: =G165-H165 -> 750 | J165: =G165*5% -> 37.5 | K165: =G165+J165 -> 787.5 | L165: MARINELLE
B166: Trane BVBA (Dubai Branch) | C166: 24-0164 | D166: 45365 | F166: BC Ifthikar | G166: 405 | I166: =G166-H166 -> 405 | J166: =G166*5% -> 20.25 | K166: =G166+J166 -> 425.25 | L166: REENA
B167: Stellar Advertising LLC | C167: 24-0165 | D167: 45366 | F167: AAG Gift Hampera | G167: 3600 | I167: =G167-H167 -> 3600 | J167: =G167*5% -> 180 | K167: =G167+J167 -> 3780 | L167: REENA
B168: Stellar Advertising LLC | C168: 24-0166 | D168: 45366 | F168: Taylor Wessing Journal | G168: 2242.5 | I168: =G168-H168 -> 2242.5 | J168: =G168*5% -> 112.125 | K168: =G168+J168 -> 2354.625 | L168: REENA
B169: Navitas Middle East FZ - LLC | C169: 24-0167 | D169: 45366 | F169: BC Yulia | G169: 275 | I169: =G169-H169 -> 275 | J169: =G169*5% -> 13.75 | K169: =G169+J169 -> 288.75 | L169: REENA
B170: Pacific Link | C170: 24-0168 | D170: 45369 | F170: Office Branding | G170: 5350 | I170: =G170-H170 -> 5350 | J170: =G170*5% -> 267.5 | K170: =G170+J170 -> 5617.5 | L170: REENA
B171: Stellar Advertising LLC | C171: 24-0169 | D171: 45370 | F171: DBSJ Flyer | G171: 290 | I171: =G171-H171 -> 290 | J171: =G171*5% -> 14.5 | K171: =G171+J171 -> 304.5 | L171: REENA
B172: The Woolwich Institute | C172: 24-0170 | D172: 45371 | F172: BC Anugha | G172: 195 | I172: =G172-H172 -> 195 | J172: =G172*5% -> 9.75 | K172: =G172+J172 -> 204.75 | L172: REENA
B173: BinGhatti | C173: 24-0171 | D173: 45377 | F173: Non Woven Bags | G173: 1725 | I173: =G173-H173 -> 1725 | J173: =G173*5% -> 86.25 | K173: =G173+J173 -> 1811.25 | L173: MARINELLE
... B177: Grandmatic | C177: 24-0175 | D177: 45374 | F177: NCR Book | G177: 285 | I177: =G177-H177 -> 285 | J177: =G177*5% -> 14.25 | K177: =G177+J177 -> 299.25 | L177: REENA
B178: Lloyds Energy DMCC | C178: 24-0176 | D178: 45376 | E178: 100056728700003 | F178: Office Signage | G178: 1250 | I178: =G178-H178 -> 1250 | J178: =G178*5% -> 62.5 | K178: =G178+J178 -> 1312.5 | L178: MARINELLE
...

Sheet Summary REA Ins
B3: Sum of INVOICE SUB-TOTAL | C3: 2024 | L3: Summary Sales per Month | M3: 2024
B4: Client Names | C4: Jan | D4: Feb | E4: Grand Total | L4: Team | M4: Jan | N4: Feb | O4: Grand Total
B5: Continental Middle East DMCC | C5: 450 | E5: 450 | L5: REENA | M5: 750 | N5: 1100 | O5: 1850
B6: IDP EDUCATION L.L.C | C6: 300 | D6: 1100 | E6: 1400 | L6: Grand Total | M6: 750 | N6: 1100 | O6: 1850
B7: Grand Total | C7: 750 | D7: 1100 | E7: 1850

Sheet 2024-curated
A1: 2024 - REA Advertising - Month wise Customer wise Sales History ( WITHOUT VAT)
B4: Client Names | C4: Jan | D4: Feb | E4: Mar | F4: Apr | G4: May | H4: Jun | I4: Jul | J4: Grand Total | K4: No of Invoices | L4: Average Amount | M4: Average /month
B5: TOP 10
A6: 1 | B6: IDP EDUCATION L.L.C | C6: 5040.907 | D6: 165010.85 | E6: 585 | F6: 4197 | G6: 16715.67 | H6: 160 | I6: 3845 | J6: 195554.43 | K6: 28 | L6: =J6/K6 -> 6984.0867 | M6: =+J6/7 -> 27936.347
A7: 2 | B7: Stellar Advertising LLC | C7: 9650.49 | D7: 16015.5 | E7: 18431 | F7: 9871 | G7: 20166.02 | H7: 76627.75 | I7: 13364.81 | J7: 164126.57 | K7: 90 | L7: =J7/K7 -> 1823.6286 | M7: =+J7/7 -> 23446.653
A8: 3 | B8: Navitas Middle East FZ - LLC | C8: 10803.35 | E8: 12395 | F8: 4669 | G8: 18700 | H8: 35007.5 | I8: 977 | J8: 82551.85 | K8: 34 | L8: =J8/K8 -> 2427.9956 | M8: =+J8/7 -> 11793.121
A9: 4 | B9: MSB Private School | H9: 45667.08 | J9: 45667.08 | K9: 1 | L9: =J9/K9 -> 45667.08 | M9: =+J9/7 -> 6523.8686
A10: 5 | B10: Dubai Academic Health Corporation (DAHC) | E10: 6920 | G10: 12375 | H10: 24338.5 | J10: 43633.5 | K10: 5 | L10: =J10/K10 -> 8726.7 | M10: =+J10/7 -> 6233.3571
A11: 6 | B11: SWISS BUSINESS COUNCIL (DMCC BRANCH) | H11: 39130 | J11: 39130 | K11: 1 | L11: =J11/K11 -> 39130 | M11: =+J11/7 -> 5590
A12: 7 | B12: DUNECREST AMERICAN SCHOOL L.L.C | C12: 19193.5 | G12: 3831.3 | H12: 358.75 | I12: 14110 | J12: 37493.55 | K12: 8 | L12: =J12/K12 -> 4686.6938 | M12: =+J12/7 -> 5356.2214
A13: 8 | B13: GrokGlobal Services | C13: 4475 | E13: 22177.5 | F13: 310 | G13: 975 | H13: 6445 | I13: 275 | J13: 34657.5 | K13: 10 | L13: =J13/K13 -> 3465.75 | M13: =+J13/7 -> 4951.0714
A14: 9 | B14: Gulftainer | E14: 31080.87 | G14: 1240 | J14: 32320.87 | K14: 8 | L14: =J14/K14 -> 4040.1088 | M14: =+J14/7 -> 4617.2671
A15: 10 | B15: DHR MENA FZ-LLC | F15: 29332.5 | J15: 29332.5 | K15: 2 | L15: =J15/K15 -> 14666.25 | M15: =+J15/7 -> 4190.3571
C16: =SUM(C6:C15) -> 49163.247 | D16: =SUM(D6:D15) -> 181026.35 | E16: =SUM(E6:E15) -> 91589.37 | F16: =SUM(F6:F15) -> 48379.5 | G16: =SUM(G6:G15) -> 74002.99 | H16: =SUM(H6:H15) -> 227734.58 | I16: =SUM(I6:I15) -> 32571.81 | J16: =SUM(J6:J15) -> 704467.85 | K16: =SUM(K6:K15) -> 187 | L16: =+J16/K16 -> 3767.2077 | M16: =SUM(M6:M15) -> 100638.26 | N16: =+J16/J132*100 -> 62.512486
B18: THE NEXT 20- GROUP A
A19: 1 | B19: PLUS971 CYBER SECURITY L.L.C | F19: 24100 | J19: 24100 | K19: 3 | L19: =J19/K19 -> 8033.3333 | M19: =+J19/7 -> 3442.8571
A20: 2 | B20: Trane BVBA (Dubai Branch) | C20: 6380 | D20: 3000 | E20: 3370 | F20: 1250 | G20: 4864 | H20: 1731 | I20: 1669 | J20: 22264 | K20: 30 | L20: =J20/K20 -> 742.13333 | M20: =+J20/7 -> 3180.5714
A21: 3 | B21: Ducon Industries FZCO (Dubai Branch) | I21: 17900 | J21: 17900 | K21: 1 | L21: =J21/K21 -> 17900 | M21: =+J21/7 -> 2557.1429
A22: 4 | B22: BorgRollsWarner Middle East LLC | C22: 14375 | I22: 1933.5 | J22: 16308.5 | K22: 2 | L22: =J22/K22 -> 8154.25 | M22: =+J22/7 -> 2329.7857
A23: 5 | B23: TETR, College of Business | G23: 11490.5 | H23: 4517.5 | J23: 16008 | K23: 5 | L23: =J23/K23 -> 3201.6 | M23: =+J23/7 -> 2286.8571
A24: 6 | B24: Radiometer Medical ApS | C24: 14677.74 | F24: 325 | J24: 15002.74 | K24: 3 | L24: =J24/K24 -> 5000.9133 | M24: =+J24/7 -> 2143.2486
A25: 7 | B25: Lloyds Energy DMCC | C25: 1250 | E25: 9475 | F25: 1100 | H25: 870 | I25: 435 | J25: 13130 | K25: 8 | L25: =J25/K25 -> 1641.25 | M25: =+J25/7 -> 1875.7143
A26: 8 | B26: Krishna International FZCO | D26: 13000 | J26: 13000 | K26: 1 | L26: =J26/K26 -> 13000 | M26: =+J26/7 -> 1857.1429
A27: 9 | B27: M E A D Medical Supplies & Equipment L.L.C | C27: 475 | D27: 1347.5 | G27: 1060 | H27: 10070 | J27: 12952.5 | K27: 6 | L27: =J27/K27 -> 2158.75 | M27: =+J27/7 -> 1850.3571
A28: 10 | B28: AL NASER INTERNATIONAL FZE | C28: 1445 | D28: 9450 | G28: 430 | H28: 485 | I28: 575 | J28: 12385 | K28: 16 | L28: =J28/K28 -> 774.0625 | M28: =+J28/7 -> 1769.2857
A29: 11 | B29: Al Jalila Foundation | H29: 11142.25 | J29: 11142.25 | K29: 2 | L29: =J29/K29 -> 5571.125 | M29: =+J29/7 -> 1591.75
A30: 12 | B30: Byyu Gift Trading LLC | E30: 4225 | G30: 350 | H30: 5935 | I30: 485 | J30: 10995 | K30: 5 | L30: =J30/K30 -> 2199 | M30: =+J30/7 -> 1570.7143
A31: 13 | B31: Al Tayer Insignia LLC | D31: 10965 | J31: 10965 | K31: 1 | L31: =J31/K31 -> 10965 | M31: =+J31/7 -> 1566.4286
A32: 14 | B32: Golden Tower Technologies | D32: 8850 | J32: 8850 | K32: 1 | L32: =J32/K32 -> 8850 | M32: =+J32/7 -> 1264.2857
A33: 15 | B33: Tappy Toes Nursery DWC-LLC | D33: 989 | G33: 7425 | J33: 8414 | K33: 2 | L33: =J33/K33 -> 4207 | M33: =+J33/7 -> 1202
A34: 16 | B34: Azalee Flower Boutique Limited | G34: 8385 | J34: 8385 | K34: 1 | L34: =J34/K34 -> 8385 | M34: =+J34/7 -> 1197.8571
A35: 17 | B35: GRAND STAR ALUMINUM & GLASS L.L.C | C35: 8360 | J35: 8360 | K35: 2 | L35: =J35/K35 -> 4180 | M35: =+J35/7 -> 1194.2857
A36: 18 | B36: Continental Middle East DMCC | D36: 3835 | G36: 1266 | H36: 3086 | J36: 8187 | K36: 5 | L36: =J36/K36 -> 1637.4 | M36: =+J36/7 -> 1169.5714
A37: 19 | B37: JUBAILI BROS S.A.L. | C37: 5975 | G37: 1612.5 | J37: 7587.5 | K37: 2 | L37: =J37/K37 -> 3793.75 | M37: =+J37/7 -> 1083.9286
A38: 20 | B38: Aurantius Real Estate Broker | C38: 553.75 | D38: 2410.5 | E38: 792.5 | G38: 869 | H38: 2138 | I38: 725 | J38: 7488.75 | K38: 9 | L38: =J38/K38 -> 832.08333 | M38: =+J38/7 -> 1069.8214
C39: =SUM(C19:C38) -> 53491.49 | D39: =SUM(D19:D38) -> 53847 | E39: =SUM(E19:E38) -> 17862.5 | F39: =SUM(F19:F38) -> 26775 | G39: =SUM(G19:G38) -> 37752 | H39: =SUM(H19:H38) -> 39974.75 | I39: =SUM(I19:I38) -> 23722.5 | J39: =SUM(J19:J38) -> 253425.24 | K39: =SUM(K19:K38) -> 105 | L39: =+J39/K39 -> 2413.5737 | M39: =SUM(M19:M38) -> 36203.606 | N39: =+J39/J132*100 -> 22.48824
B41: THEY GAVE US BUSINESS TOO !!!
A42: 1 | B42: Huxley Associates Global Limited | C42: 1125 | D42: 225 | F42: 375 | G42: 4355 | H42: 1233.75 | J42: 7313.75 | K42: 6 | L42: =J42/K42 -> 1218.9583 | M42: =+J42/7 -> 1044.8214
A43: 2 | B43: Tristar Transport LLC | C43: 1140 | F43: 6000 | J43: 7140 | K43: 2 | L43: =J43/K43 -> 3570 | M43: =+J43/7 -> 1020
A44: 3 | B44: Liquid Telecommunications International FZE | D44: 6775 | J44: 6775 | K44: 2 | L44: =J44/K44 -> 3387.5 | M44: =+J44/7 -> 967.85714
A45: 4 | B45: Pacific Link | E45: 6625 | J45: 6625 | K45: 2 | L45: =J45/K45 -> 3312.5 | M45: =+J45/7 -> 946.42857
A46: 5 | B46: A-Technologies FZCO | C46: 6050 | J46: 6050 | K46: 2 | L46: =J46/K46 -> 3025 | M46: =+J46/7 -> 864.28571
A47: 6 | B47: PHARMAPAL DRUG STORE L.L.C | C47: 5781 | J47: 5781 | K47: 2 | L47: =J47/K47 -> 2890.5 | M47: =+J47/7 -> 825.85714
A48: 7 | B48: VISIONARY FURNITURE TRADING L.L.C | C48: 5373 | G48: 217.5 | J48: 5590.5 | K48: 3 | L48: =J48/K48 -> 1863.5 | M48: =+J48/7 -> 798.64286
A49: 8 | B49: MAERSK LOGISTICS AND SERVICES FZE | F49: 1205 | H49: 4000 | J49: 5205 | K49: 2 | L49: =J49/K49 -> 2602.5 | M49: =+J49/7 -> 743.57143
A50: 9 | B50: Sea Centre Shipping Services LLC | C50: 3950 | F50: 1050 | G50: 190 | J50: 5190 | K50: 3 | L50: =J50/K50 -> 1730 | M50: =+J50/7 -> 741.42857
A51: 10 | B51: Bianca and Bianco Trading LLC | C51: 825 | D51: 310 | F51: 825 | I51: 3210 | J51: 5170 | K51: 4 | L51: =J51/K51 -> 1292.5 | M51: =+J51/7 -> 738.57143
A52: 11 | B52: Thermo Fisher Scientific Middle East | D52: 3335 | F52: 1750.5 | J52: 5085.5 | K52: 2 | L52: =J52/K52 -> 2542.75 | M52: =+J52/7 -> 726.5
A53: 12 | B53: Logic Utilities District Cooling Services LLC | C53: 4252.5 | I53: 700 | J53: 4952.5 | K53: 2 | L53: =J53/K53 -> 2476.25 | M53: =+J53/7 -> 707.5
A54: 13 | B54: AL RASHED UNITED DMCC | D54: 3490 | I54: 1395 | J54: 4885 | K54: 2 | L54: =J54/K54 -> 2442.5 | M54: =+J54/7 -> 697.85714
A55: 14 | B55: Ms. Karine Leonian | C55: 4687.5 | J55: 4687.5 | K55: 1 | L55: =J55/K55 -> 4687.5 | M55: =+J55/7 -> 669.64286
A56: 15 | B56: J C S ARTIFICIAL FLOWERS & PLANTS TRADING L.L.C | D56: 779 | G56: 770 | I56: 2435 | J56: 3984 | K56: 5 | L56: =J56/K56 -> 796.8 | M56: =+J56/7 -> 569.14286
A57: 16 | B57: MIGHTHOUSE REALTY L.L.C | G57: 2195 | H57: 893 | I57: 700 | J57: 3788 | K57: 5 | L57: =J57/K57 -> 757.6 | M57: =+J57/7 -> 541.14286
A58: 17 | B58: CJ ICM FZCO | C58: 3150 | J58: 3150 | K58: 1 | L58: =J58/K58 -> 3150 | M58: =+J58/7 -> 450
A59: 18 | B59: MIRA REAL ESTATE BROKERS L.L.C | D59: 3150 | J59: 3150 | K59: 2 | L59: =J59/K59 -> 1575 | M59: =+J59/7 -> 450
A60: 19 | B60: ANB AUTOMOBILES L.L.C | D60: 1580 | E60: 1130 | H60: 389.75 | J60: 3099.75 | K60: 3 | L60: =J60/K60 -> 1033.25 | M60: =+J60/7 -> 442.82143
A61: 20 | B61: CACOGES | F61: 2850 | J61: 2850 | K61: 1 | L61: =J61/K61 -> 2850 | M61: =+J61/7 -> 407.14286
A62: 21 | B62: Saint Vincent Group GT LLC | I62: 2800 | J62: 2800 | K62: 1 | L62: =J62/K62 -> 2800 | M62: =+J62/7 -> 400
A63: 22 | B63: MAV Access LLC | I63: 2750 | J63: 2750 | K63: 1 | L63: =J63/K63 -> 2750 | M63: =+J63/7 -> 392.85714
A64: 23 | B64: Ali Salim Ali Salim Alqaydi | D64: 2715 | J64: 2715 | K64: 1 | L64: =J64/K64 -> 2715 | M64: =+J64/7 -> 387.85714
A65: 24 | B65: E V OFFSHORE LIMITED (DUBAI BRANCH) | D65: 1400 | G65: 944 | J65: 2344 | K65: 2 | L65: =J65/K65 -> 1172 | M65: =+J65/7 -> 334.85714
A66: 25 | B66: Global Connect | C66: 120 | D66: 190 | G66: 1145 | H66: 820 | J66: 2275 | K66: 4 | L66: =J66/K66 -> 568.75 | M66: =+J66/7 -> 325
A67: 26 | B67: Finhub Middle East | G67: 2225 | J67: 2225 | K67: 1 | L67: =J67/K67 -> 2225 | M67: =+J67/7 -> 317.85714
A68: 27 | B68: BECKMAN COULTER INTERNATIONAL S.A. (DUBAI BR) | G68: 2173.75 | J68: 2173.75 | K68: 1 | L68: =J68/K68 -> 2173.75 | M68: =+J68/7 -> 310.53571
A69: 28 | B69: CHINT MIDDLE EAST AND AFRICA DMCC | I69: 2032.5 | J69: 2032.5 | K69: 1 | L69: =J69/K69 -> 2032.5 | M69: =+J69/7 -> 290.35714
A70: 29 | B70: Right Fit Tailoring | G70: 2000 | J70: 2000 | K70: 1 | L70: =J70/K70 -> 2000 | M70: =+J70/7 -> 285.71429
A71: 30 | B71: Technological University of the Shannon - Ireland | D71: 1925 | J71: 1925 | K71: 1 | L71: =J71/K71 -> 1925 | M71: =+J71/7 -> 275
A72: 31 | B72: Crescent Real Estate | D72: 1920 | J72: 1920 | K72: 1 | L72: =J72/K72 -> 1920 | M72: =+J72/7 -> 274.28571
A73: 32 | B73: BorgRollsWarner Middle East LLC | I73: 1803.75 | J73: 1803.75 | K73: 1 | L73: =J73/K73 -> 1803.75 | M73: =+J73/7 -> 257.67857
A74: 33 | B74: World Data Feasibility Studies Consultancies | C74: 1780 | J74: 1780 | K74: 1 | L74: =J74/K74 -> 1780 | M74: =+J74/7 -> 254.28571
A75: 34 | B75: EMIRATES FOR UNIVERSAL TYRES L.L.C. | C75: 1315 | G75: 450 | J75: 1765 | K75: 4 | L75: =J75/K75 -> 441.25 | M75: =+J75/7 -> 252.14286
A76: 35 | B76: BinGhatti | E76: 1725 | J76: 1725 | K76: 1 | L76: =J76/K76 -> 1725 | M76: =+J76/7 -> 246.42857
A77: 36 | B77: FAD Institute of Luxury Fashion and Style Dubai | C77: 1690 | J77: 1690 | K77: 1 | L77: =J77/K77 -> 1690 | M77: =+J77/7 -> 241.42857
A78: 37 | B78: Ingersoll-Rand Technical and Services S A R L (Dubai Branch) | C78: 310 | G78: 1010 | H78: 285 | J78: 1605 | K78: 4 | L78: =J78/K78 -> 401.25 | M78: =+J78/7 -> 229.28571
C79: =SUM(C42:C78) -> 41549 | D79: =SUM(D42:D78) -> 27794 | E79: =SUM(E42:E78) -> 9480 | F79: =SUM(F42:F78) -> 14055.5 | G79: =SUM(G42:G78) -> 17675.25 | H79: =SUM(H42:H78) -> 7621.5 | I79: =SUM(I42:I78) -> 17826.25 | J79: =SUM(J42:J78) -> 136001.5 | K79: =SUM(K42:K78) -> 79 | L79: =J79/K79 -> 1721.538 | M79: =SUM(M42:M77) -> 19199.5 | N79: =+J79/J132*100 -> 12.068389
B81: THE SUB 1500 and less
A82: 1 | B82: SPH Global Holdings LLC | C82: 1250 | H82: 210 | J82: 1460 | K82: 2 | L82: =J82/K82 -> 730 | M82: =+J82/7 -> 208.57143
A83: 2 | B83: Menlo Electric FZE | E83: 1440 | J83: 1440 | K83: 1 | L83: =J83/K83 -> 1440 | M83: =+J83/7 -> 205.71429
A84: 3 | B84: KOTUG MIDDLE EAST DMCC | F84: 1167 | G84: 250 | J84: 1417 | K84: 2 | L84: =J84/K84 -> 708.5 | M84: =+J84/7 -> 202.42857
A85: 4 | B85: Unique World Business Centre LLC | C85: 375 | D85: 195 | E85: 150 | F85: 270 | G85: 270 | H85: 90 | J85: 1350 | K85: 12 | L85: =J85/K85 -> 112.5 | M85: =+J85/7 -> 192.85714
A86: 5 | B86: Blu Orbit | C86: 1250 | J86: 1250 | K86: 1 | L86: =J86/K86 -> 1250 | M86: =+J86/7 -> 178.57143
A87: 6 | B87: MEINHARDT (SINGAPORE) PTE LTD (DUBAI BR) | F87: 1249.5 | J87: 1249.5 | K87: 1 | L87: =J87/K87 -> 1249.5 | M87: =+J87/7 -> 178.5
A88: 7 | B88: Genenis Digital Assets Limited | I88: 1243.75 | J88: 1243.75 | K88: 1 | L88: =J88/K88 -> 1243.75 | M88: =+J88/7 -> 177.67857
A89: 8 | B89: Griffith College | D89: 1225 | J89: 1225 | K89: 1 | L89: =J89/K89 -> 1225 | M89: =+J89/7 -> 175
A90: 9 | B90: Waterline Freight Solutions LLC | I90: 1195 | J90: 1195 | K90: 1 | L90: =J90/K90 -> 1195 | M90: =+J90/7 -> 170.71429
A91: 10 | B91: PMMUE Eduservices Private Limited | G91: 1183 | J91: 1183 | K91: 1 | L91: =J91/K91 -> 1183 | M91: =+J91/7 -> 169
A92: 11 | B92: Indo Tausch Trading DMCC | D92: 420 | E92: 185 | G92: 420 | I92: 125 | J92: 1150 | K92: 5 | L92: =J92/K92 -> 230 | M92: =+J92/7 -> 164.28571
A93: 12 | B93: The Woolwich Institute | E93: 405 | H93: 735 | J93: 1140 | K93: 3 | L93: =J93/K93 -> 380 | M93: =+J93/7 -> 162.85714
A94: 13 | B94: One Blue Clover FZCO | D94: 525 | E94: 550 | J94: 1075 | K94: 2 | L94: =J94/K94 -> 537.5 | M94: =+J94/7 -> 153.57143
A95: 14 | B95: Shory Technology L.L.C | C95: 150 | D95: 915 | J95: 1065 | K95: 2 | L95: =J95/K95 -> 532.5 | M95: =+J95/7 -> 152.14286
A96: 15 | B96: HOLO MORTGAGE CONSULTANT | C96: 1060 | J96: 1060 | K96: 1 | L96: =J96/K96 -> 1060 | M96: =+J96/7 -> 151.42857
A97: 16 | B97: AMANI INVESTMENTS L.L.C - FZ | C97: 995 | J97: 995 | K97: 1 | L97: =J97/K97 -> 995 | M97: =+J97/7 -> 142.14286
A98: 17 | B98: GOOD VIBES TRANSPORT L.L.C | E98: 925 | J98: 925 | K98: 1 | L98: =J98/K98 -> 925 | M98: =+J98/7 -> 132.14286
A99: 18 | B99: Mr. Waiz (Amity) | F99: 900 | J99: 900 | K99: 1 | L99: =J99/K99 -> 900 | M99: =+J99/7 -> 128.57143
A100: 19 | B100: DYNAMIC EMPLOYMENT SERVICES L.L.C | D100: 892.5 | J100: 892.5 | K100: 1 | L100: =J100/K100 -> 892.5 | M100: =+J100/7 -> 127.5
A101: 20 | B101: NARJIS Printing and Publishing | F101: 380 | H101: 459.52 | J101: 839.52 | K101: 2 | L101: =J101/K101 -> 419.76 | M101: =+J101/7 -> 119.93143
A102: 21 | B102: Nanjing Stationery | E102: 750 | J102: 750 | K102: 1 | L102: =J102/K102 -> 750 | M102: =+J102/7 -> 107.14286
A103: 22 | B103: BNI Polaris | H103: 714.29 | J103: 714.29 | K103: 1 | L103: =J103/K103 -> 714.29 | M103: =+J103/7 -> 102.04143
A104: 23 | B104: Blackswan business center L.L.C | F104: 285.5 | H104: 367.5 | J104: 653 | K104: 2 | L104: =J104/K104 -> 326.5 | M104: =+J104/7 -> 93.285714
A105: 24 | B105: Medical Regulations Gate | I105: 625 | J105: 625 | K105: 1 | L105: =J105/K105 -> 625 | M105: =+J105/7 -> 89.285714
...

Sheet 2024
B3: Column Labels
B4: Jan | D4: Feb | F4: Mar | H4: Apr | J4: May | L4: Jun | N4: Jul | P4: Aug | R4: Total Sum of INVOICE SUB-TOTAL | S4: Total Sum of No of invoice
A5: Row Labels | B5: Sum of INVOICE SUB-TOTAL | C5: Sum of No of invoice | D5: Sum of INVOICE SUB-TOTAL | E5: Sum of No of invoice | F5: Sum of INVOICE SUB-TOTAL | G5: Sum of No of invoice | H5: Sum of INVOICE SUB-TOTAL | I5: Sum of No of invoice | J5: Sum of INVOICE SUB-TOTAL | K5: Sum of No of invoice | L5: Sum of INVOICE SUB-TOTAL | M5: Sum of No of invoice | N5: Sum of INVOICE SUB-TOTAL | O5: Sum of No of invoice | P5: Sum of INVOICE SUB-TOTAL | Q5: Sum of No of invoice
A6: IDP EDUCATION L.L.C | B6: 4813 | C6: 3 | D6: 165010.85 | E6: 8 | F6: 585 | G6: 1 | H6: 4197 | I6: 3 | J6: 16715.67 | K6: 9 | L6: 160 | M6: 1 | N6: 5885 | O6: 3 | R6: 197366.52 | S6: 28
A7: Stellar Advertising LLC | B7: 9650.49 | C7: 10 | D7: 16015.5 | E7: 10 | F7: 18431 | G7: 14 | H7: 9871 | I7: 10 | J7: 20166.02 | K7: 21 | L7: 76627.75 | M7: 18 | N7: 15382.81 | O7: 10 | R7: 166144.57 | S7: 93
A8: Navitas Middle East FZ - LLC | B8: 10803.35 | C8: 4 | F8: 550 | G8: 2 | H8: 4669 | I8: 4 | J8: 12497.5 | K8: 9 | L8: 33682.5 | M8: 3 | N8: 977 | O8: 2 | R8: 63179.35 | S8: 24
A9: MSB Private School | L9: 45667.08 | M9: 1 | R9: 45667.08 | S9: 1
A10: Dubai Academic Health Corporation (DAHC) | F10: 6920 | G10: 1 | J10: 12375 | K10: 1 | L10: 24338.5 | M10: 3 | R10: 43633.5 | S10: 5
A11: SWISS BUSINESS COUNCIL (DMCC BRANCH) | L11: 39130 | M11: 1 | R11: 39130 | S11: 1
A12: DUNECREST AMERICAN SCHOOL L.L.C | B12: 19193.5 | C12: 2 | J12: 3831.3 | K12: 4 | L12: 358.75 | M12: 1 | N12: 14110 | O12: 1 | R12: 37493.55 | S12: 8
A13: GrokGlobal Services | B13: 4475 | C13: 2 | F13: 22177.5 | G13: 3 | H13: 310 | I13: 1 | J13: 975 | K13: 1 | L13: 6445 | M13: 2 | N13: 275 | O13: 1 | R13: 34657.5 | S13: 10
A14: DHR MENA FZ-LLC | H14: 29332.5 | I14: 2 | R14: 29332.5 | S14: 2
A15: Ducon Industries FZCO (Dubai Branch) | N15: 24876 | O15: 2 | R15: 24876 | S15: 2
A16: PLUS971 CYBER SECURITY L.L.C | H16: 24100 | I16: 3 | R16: 24100 | S16: 3
A17: Trane BVBA (Dubai Branch) | B17: 5975 | C17: 5 | D17: 3000 | E17: 4 | F17: 2830 | G17: 4 | H17: 405 | I17: 1 | J17: 4864 | K17: 7 | L17: 1731 | M17: 2 | N17: 4369 | O17: 4 | R17: 23174 | S17: 27
A18: BorgRollsWarner Middle East LLC | B18: 14375 | C18: 1 | N18: 1933.5 | O18: 1 | R18: 16308.5 | S18: 2
A19: Lloyds Energy DMCC | B19: 1250 | C19: 1 | F19: 9475 | G19: 3 | H19: 1100 | I19: 1 | L19: 870 | M19: 2 | N19: 3110 | O19: 2 | R19: 15805 | S19: 9
A20: Radiometer Medical ApS | B20: 14677.74 | C20: 2 | H20: 325 | I20: 1 | R20: 15002.74 | S20: 3
A21: Gulftainer | F21: 12626.25 | G21: 3 | J21: 1240 | K21: 1 | R21: 13866.25 | S21: 4
A22: Continental Middle East DMCC | D22: 3835 | E22: 2 | J22: 1266 | K22: 1 | L22: 3086 | M22: 2 | N22: 5528.75 | O22: 1 | R22: 13715.75 | S22: 6
A23: Krishna International FZCO | D23: 13000 | E23: 1 | R23: 13000 | S23: 1
A24: M E A D Medical Supplies & Equipment L.L.C | B24: 475 | C24: 1 | D24: 1347.5 | E24: 2 | J24: 1060 | K24: 1 | L24: 10070 | M24: 2 | R24: 12952.5 | S24: 6
A25: TETR, College of Business | J25: 11490.5 | K25: 3 | R25: 11490.5 | S25: 3
A26: Al Jalila Foundation | L26: 11142.25 | M26: 2 | R26: 11142.25 | S26: 2
A27: Byyu Gift Trading LLC | F27: 4225 | G27: 2 | J27: 350 | K27: 1 | L27: 5935 | M27: 1 | N27: 485 | O27: 1 | R27: 10995 | S27: 5
A28: Al Tayer Insignia LLC | D28: 10965 | E28: 1 | R28: 10965 | S28: 1
A29: Navitas - Murdoch University | F29: 10720 | G29: 3 | R29: 10720 | S29: 3
A30: Golden Tower Technologies | D30: 8850 | E30: 1 | R30: 8850 | S30: 1
A31: Navitas SAE FZ-LLC | F31: 1125 | G31: 3 | J31: 6202.5 | K31: 3 | L31: 1325 | M31: 1 | R31: 8652.5 | S31: 7
A32: Momentum Logistics | F32: 8463.75 | G32: 1 | R32: 8463.75 | S32: 1
A33: Tappy Toes Nursery DWC-LLC | D33: 989 | E33: 1 | J33: 7425 | K33: 1 | R33: 8414 | S33: 2
A34: Azalee Flower Boutique Limited | J34: 8385 | K34: 1 | R34: 8385 | S34: 1
A35: GRAND STAR ALUMINUM & GLASS L.L.C | B35: 8360 | C35: 2 | R35: 8360 | S35: 2
A36: Aurantius Real Estate Broker | B36: 553.75 | C36: 2 | D36: 2410.5 | E36: 2 | F36: 792.5 | G36: 1 | J36: 869 | K36: 1 | L36: 2138 | M36: 2 | N36: 1000 | O36: 2 | R36: 7763.75 | S36: 10
A37: JUBAILI BROS S.A.L. | B37: 5975 | C37: 1 | J37: 1612.5 | K37: 1 | R37: 7587.5 | S37: 2
A38: Gulftainer Company Limited - Iraq Branch | F38: 7493.15 | G38: 2 | R38: 7493.15 | S38: 2
A39: Huxley Associates Global Limited | B39: 1125 | C39: 1 | D39: 225 | E39: 1 | H39: 375 | I39: 1 | J39: 4355 | K39: 2 | L39: 1233.75 | M39: 1 | R39: 7313.75 | S39: 6
A40: Tristar Transport LLC | B40: 1140 | C40: 1 | H40: 6000 | I40: 1 | R40: 7140 | S40: 2
A41: Liquid Telecommunications International FZE | D41: 6775 | E41: 2 | R41: 6775 | S41: 2
A42: Pacific Link | F42: 6625 | G42: 2 | R42: 6625 | S42: 2
A43: A-Technologies FZCO | B43: 6050 | C43: 2 | R43: 6050 | S43: 2
A44: PHARMAPAL DRUG STORE L.L.C | B44: 5781 | C44: 2 | R44: 5781 | S44: 2
A45: VISIONARY FURNITURE TRADING L.L.C | B45: 5373 | C45: 2 | J45: 217.5 | K45: 1 | R45: 5590.5 | S45: 3
A46: MAERSK LOGISTICS AND SERVICES FZE | H46: 1205 | I46: 1 | L46: 4000 | M46: 1 | R46: 5205 | S46: 2
A47: Sea Centre Shipping Services LLC | B47: 3950 | C47: 1 | H47: 1050 | I47: 1 | J47: 190 | K47: 1 | R47: 5190 | S47: 3
A48: Bianca and Bianco Trading LLC | B48: 825 | C48: 1 | D48: 310 | E48: 1 | H48: 825 | I48: 1 | N48: 3210 | O48: 1 | R48: 5170 | S48: 4
A49: Logic Utilities District Cooling Services LLC | B49: 4252.5 | C49: 1 | N49: 700 | O49: 1 | R49: 4952.5 | S49: 2
A50: AL RASHED UNITED DMCC | D50: 3490 | E50: 1 | N50: 1395 | O50: 1 | R50: 4885 | S50: 2
A51: Ms. Karine Leonian | B51: 4687.5 | C51: 1 | R51: 4687.5 | S51: 1
A52: ANB AUTOMOBILES L.L.C | D52: 1580 | E52: 1 | F52: 1130 | G52: 1 | L52: 389.75 | M52: 1 | P52: 1580 | Q52: 1 | R52: 4679.75 | S52: 4
A53: TETR College of Business | L53: 4517.5 | M53: 2 | R53: 4517.5 | S53: 2
A54: AUSTRAL INTERNATIONAL DMCC | B54: 745 | C54: 1 | D54: 3150 | E54: 2 | N54: 287.5 | O54: 1 | R54: 4182.5 | S54: 4
A55: Al Naser International FZE | D55: 3150 | E55: 2 | J55: 260 | K55: 1 | L55: 485 | M55: 1 | N55: 287.5 | O55: 1 | R55: 4182.5 | S55: 5
A56: J C S ARTIFICIAL FLOWERS & PLANTS TRADING L.L.C | D56: 779 | E56: 1 | J56: 770 | K56: 2 | N56: 2435 | O56: 2 | R56: 3984 | S56: 5
A57: MIGHTHOUSE REALTY L.L.C | J57: 2195 | K57: 1 | L57: 893 | M57: 2 | N57: 700 | O57: 2 | R57: 3788 | S57: 5
A58: BLUE TANGERINE MARKETING MANAGEMENT | N58: 3750 | O58: 1 | R58: 3750 | S58: 1
A59: Aram Precious Metals Trading FZE | B59: 250 | C59: 1 | D59: 3150 | E59: 2 | J59: 85 | K59: 1 | R59: 3485 | S59: 4
A60: Thermo Fisher Scientific S.P.A. | D60: 3335 | E60: 1 | R60: 3335 | S60: 1
A61: MIRA REAL ESTATE BROKERS L.L.C | D61: 3150 | E61: 2 | R61: 3150 | S61: 2
A62: CJ ICM FZCO | B62: 3150 | C62: 1 | R62: 3150 | S62: 1
A63: CACOGES | H63: 2850 | I63: 1 | R63: 2850 | S63: 1
A64: Saint Vincent Group GT LLC | N64: 2800 | O64: 1 | R64: 2800 | S64: 1
A65: MAV Access LLC | N65: 2750 | O65: 1 | R65: 2750 | S65: 1
A66: Ali Salim Ali Salim Alqaydi | D66: 2715 | E66: 1 | R66: 2715 | S66: 1
A67: Trane BVBA (Abu Dhabi) | B67: 405 | C67: 1 | F67: 540 | G67: 1 | H67: 845 | I67: 2 | N67: 760 | O67: 1 | R67: 2550 | S67: 5
A68: Momentum Company Limited Saudi Arabia | F68: 2497.72 | G68: 1 | R68: 2497.72 | S68: 1
A69: E V OFFSHORE LIMITED (DUBAI BRANCH) | D69: 1400 | E69: 1 | J69: 944 | K69: 1 | R69: 2344 | S69: 2
A70: Global Connect | B70: 120 | C70: 1 | D70: 190 | E70: 1 | J70: 1145 | K70: 1 | L70: 820 | M70: 1 | R70: 2275 | S70: 4
A71: Finhub Middle East | J71: 2225 | K71: 1 | R71: 2225 | S71: 1
A72: BECKMAN COULTER INTERNATIONAL S.A. (DUBAI BR) | J72: 2173.75 | K72: 1 | R72: 2173.75 | S72: 1
A73: BNI Polaris | L73: 714.29 | M73: 1 | N73: 1412 | O73: 2 | R73: 2126.29 | S73: 3
A74: CHINT MIDDLE EAST AND AFRICA DMCC | N74: 2032.5 | O74: 1 | R74: 2032.5 | S74: 1
A75: Right Fit Tailoring | J75: 2000 | K75: 1 | R75: 2000 | S75: 1
A76: Technological University of the Shannon - Ireland | D76: 1925 | E76: 1 | R76: 1925 | S76: 1
A77: Crescent Real Estate | D77: 1920 | E77: 1 | R77: 1920 | S77: 1
A78: BorgRollsWarner Middle East LLC | N78: 1803.75 | O78: 1 | R78: 1803.75 | S78: 1
A79: World Data Feasibility Studies Consultancies | B79: 1780 | C79: 1 | R79: 1780 | S79: 1
A80: EMIRATES FOR UNIVERSAL TYRES L.L.C. | B80: 1315 | C80: 3 | J80: 450 | K80: 1 | R80: 1765 | S80: 4
A81: Thermo Fisher Scientific Middle East | H81: 1750.5 | I81: 1 | R81: 1750.5 | S81: 1
A82: BinGhatti | F82: 1725 | G82: 1 | R82: 1725 | S82: 1
A83: FAD Institute of Luxury Fashion and Style Dubai | B83: 1690 | C83: 1 | R83: 1690 | S83: 1
A84: Ingersoll-Rand Technical and Services S A R L (Dubai Branch) | B84: 310 | C84: 1 | J84: 1010 | K84: 2 | L84: 285 | M84: 1 | R84: 1605 | S84: 4
A85: Locke Lifestyle Properties | N85: 1600 | O85: 2 | R85: 1600 | S85: 2
A86: SPH Global Holdings LLC | B86: 1250 | C86: 1 | L86: 210 | M86: 1 | R86: 1460 | S86: 2
A87: Menlo Electric FZE | F87: 1440 | G87: 1 | R87: 1440 | S87: 1
A88: KOTUG MIDDLE EAST DMCC | H88: 1167 | I88: 1 | J88: 250 | K88: 1 | R88: 1417 | S88: 2
A89: Blu Orbit | B89: 1250 | C89: 1 | R89: 1250 | S89: 1
A90: MEINHARDT (SINGAPORE) PTE LTD (DUBAI BR) | H90: 1249.5 | I90: 1 | R90: 1249.5 | S90: 1
A91: Genenis Digital Assets Limited | N91: 1243.75 | O91: 1 | R91: 1243.75 | S91: 1
A92: Griffith College | D92: 1225 | E92: 1 | R92: 1225 | S92: 1
A93: Waterline Freight Solutions LLC | N93: 1195 | O93: 1 | R93: 1195 | S93: 1
A94: PMMUE Eduservices Private Limited | J94: 1183 | K94: 1 | R94: 1183 | S94: 1
A95: VOXTEL COMMUNICATIONS DMCC | N95: 1175 | O95: 1 | R95: 1175 | S95: 1
A96: Indo Tausch Trading DMCC | D96: 420 | E96: 1 | F96: 185 | G96: 1 | J96: 420 | K96: 2 | N96: 125 | O96: 1 | R96: 1150 | S96: 5
A97: The Woolwich Institute | F97: 405 | G97: 2 | L97: 735 | M97: 1 | R97: 1140 | S97: 3
A98: One Blue Clover FZCO | D98: 525 | E98: 1 | F98: 550 | G98: 1 | R98: 1075 | S98: 2
A99: Shory Technology L.L.C | B99: 150 | C99: 1 | D99: 915 | E99: 1 | R99: 1065 | S99: 2
A100: HOLO MORTGAGE CONSULTANT | B100: 1060 | C100: 1 | R100: 1060 | S100: 1
A101: AMANI INVESTMENTS L.L.C - FZ | B101: 995 | C101: 1 | R101: 995 | S101: 1
A102: GOOD VIBES TRANSPORT L.L.C | F102: 925 | G102: 1 | R102: 925 | S102: 1
...

Sheet COMP
A2: AL NASER INTERNATIONAL FZE | B2: AL NASER INTERNATIONAL FZE
B3: AUSTRAL INTERNATIONAL DMCC
B4: AUSTRAL INTERNATIONAL FZE
B5: LAYAN TRADING FZE
B6: ARAM
A8: GULFTAINER | B8: GULFTAINER
A9: GULFTAINER | B9: GULTAINER COMPANY LIMITED - IRAQ BRANCH
B10: MOMENTUM COMPANY LIMITED SAUDI ARABIA
B11: MOMENTUM LOGISTICS
A13: MURDOCH | B13: NAVITAS - MURDOCH UNIVERSITY
B14: NAVITAS MIDDLE EAST FZ - LLC
B15: NAVITAS SAE FZ - LLC
A17: THERMO FISHER | B17: THERMO FISHER SCIENTIFIC MIDDLE EAST
A18: THERMO FISHER | B18: THERMO FISHER SCIENTIFIC S.P.A
A21: UNIQUE WORLD BUSINESS | B21: UNIQUE WORLD BUSINESS CENTRE LLC
B22: UNIQUE WORLD BUSINESS CENTRE LLC-(BR)
B23: UNIQUE WORLD BUSINESS CENTRE LLC-(HO)

Sheet REA Ins - Inv
B2: CLIENT | C2: INVOICE NO. | D2: INVOICE DATE | E2: CLIENT TRN | F2: DESCRIPTION | G2: INVOICE SUB-TOTAL | H2: Rebate | I2: Invoice Sub-Total after Rebate | J2: VAT % AMOUNT | K2: TOTAL INVOICE AMOUNT | L2: Sales Person | N2: =SUM(G:G) -> 1850
B3: Continental Middle East DMCC | C3: 24-0001 | D3: 45310 | E3: 100377505100003 | F3: Trophy - RONY DOMINIC | G3: 450 | I3: =G3-H3 -> 450 | J3: =G3*5% -> 22.5 | K3: =G3+J3 -> 472.5 | L3: REENA
B4: IDP EDUCATION L.L.C | C4: 24-0002 | D4: 45320 | E4: 100593105800003 | F4: Rubber Stamp | G4: 300 | I4: =G4-H4 -> 300 | J4: =G4*5% -> 15 | K4: =G4+J4 -> 315 | L4: REENA
B5: IDP EDUCATION L.L.C | C5: 24-0003 | D5: 45348 | E5: 100593105800003 | F5: Business Cards - Dubai | G5: 720 | I5: =G5-H5 -> 720 | J5: =G5*5% -> 36 | K5: =G5+J5 -> 756 | L5: REENA
B6: IDP EDUCATION L.L.C | C6: 24-0004 | D6: 45350 | E6: 100593105800003 | F6: Name Tags , Expo Cards | G6: 380 | I6: =G6-H6 -> 380 | J6: =G6*5% -> 19 | K6: =G6+J6 -> 399 | L6: REENA
G7: 0 | I7: =G7-H7 -> 0 | J7: =G7*5% -> 0 | K7: =G7+J7 -> 0
G8: 0 | I8: =G8-H8 -> 0 | J8: =G8*5% -> 0 | K8: =G8+J8 -> 0
G9: 0 | I9: =G9-H9 -> 0 | J9: =G9*5% -> 0 | K9: =G9+J9 -> 0
G10: 0 | I10: =G10-H10 -> 0 | J10: =G10*5% -> 0 | K10: =G10+J10 -> 0
G11: 0 | I11: =G11-H11 -> 0 | J11: =G11*5% -> 0 | K11: =G11+J11 -> 0
G12: 0 | I12: =G12-H12 -> 0 | J12: =G12*5% -> 0 | K12: =G12+J12 -> 0
G13: 0 | I13: =G13-H13 -> 0 | J13: =G13*5% -> 0 | K13: =G13+J13 -> 0
G14: 0 | I14: =G14-H14 -> 0 | J14: =G14*5% -> 0 | K14: =G14+J14 -> 0
G15: 0 | I15: =G15-H15 -> 0 | J15: =G15*5% -> 0 | K15: =G15+J15 -> 0
G16: 0 | I16: =G16-H16 -> 0 | J16: =G16*5% -> 0 | K16: =G16+J16 -> 0
G17: 0 | I17: =G17-H17 -> 0 | J17: =G17*5% -> 0 | K17: =G17+J17 -> 0
G18: 0 | I18: =G18-H18 -> 0 | J18: =G18*5% -> 0 | K18: =G18+J18 -> 0
... G21: 0 | I21: =G21-H21 -> 0 | J21: =G21*5% -> 0 | K21: =G21+J21 -> 0
G22: 0 | H22: 0 | I22: =G22-H22 -> 0 | J22: =I22*5% -> 0 | K22: =I22+J22 -> 0
I23: =SUM(I3:I22) -> 1850 | J23: =SUM(J3:J22) -> 92.5 | K23: =SUM(K3:K22) -> 1942.5
